Workbook
Name \a: #REF!
Name \a: #REF!
Name \a: #REF!
Name \d: #REF!
Name \d: #REF!
Name \d: #REF!
Name \E: #REF!
Name \E: #REF!
Name \E: #REF!
Name \i: #REF!
Name \i: #REF!
Name \i: #REF!
Name \p: #REF!
Name \p: #REF!
Name \p: #REF!
Name \t: #REF!
Name \t: #REF!
Name \t: #REF!
Name _____________________________________________________________________________DAT1: #REF!
Name _____________________________________________________________________________DAT1: #REF!
Name _____________________________________________________________________________DAT1: #REF!
Name _____________________________________________________________________________DAT2: #REF!
Name _____________________________________________________________________________DAT2: #REF!
Name _____________________________________________________________________________DAT2: #REF!
Name _____________________________________________________________________________DAT3: #REF!
Name _____________________________________________________________________________DAT3: #REF!
Name _____________________________________________________________________________DAT3: #REF!
Name _____________________________________________________________________________DAT4: #REF!
Name _____________________________________________________________________________DAT4: #REF!
Name _____________________________________________________________________________DAT4: #REF!
Name _____________________________________________________________________________DAT5: #REF!
Name _____________________________________________________________________________DAT5: #REF!
Name _____________________________________________________________________________DAT5: #REF!
Name _____________________________________________________________________________DAT6: #REF!
Name _____________________________________________________________________________DAT6: #REF!
Name _____________________________________________________________________________DAT6: #REF!
Name ____________________________________________________________________________DAT1: #REF!
Name ____________________________________________________________________________DAT1: #REF!
Name ____________________________________________________________________________DAT1: #REF!
Name ____________________________________________________________________________DAT2: #REF!
Name ____________________________________________________________________________DAT2: #REF!
Name ____________________________________________________________________________DAT2: #REF!
Name ____________________________________________________________________________DAT3: #REF!
Name ____________________________________________________________________________DAT3: #REF!
Name ____________________________________________________________________________DAT3: #REF!
Name ____________________________________________________________________________DAT4: #REF!
Name ____________________________________________________________________________DAT4: #REF!
Name ____________________________________________________________________________DAT4: #REF!
Name ____________________________________________________________________________DAT5: #REF!
Name ____________________________________________________________________________DAT5: #REF!
Name ____________________________________________________________________________DAT5: #REF!
Name ____________________________________________________________________________DAT6: #REF!
Name ____________________________________________________________________________DAT6: #REF!
Name ____________________________________________________________________________DAT6: #REF!
Name __________________________________________________________________________DAT1: #REF!
Name __________________________________________________________________________DAT1: #REF!
Name __________________________________________________________________________DAT1: #REF!
Name __________________________________________________________________________DAT2: #REF!
Name __________________________________________________________________________DAT2: #REF!
Name __________________________________________________________________________DAT2: #REF!

Sheet Breakdown Alocação de Despesas
C2: Resultado Trimestral StartSe
D5: Fechamento | I5: Orçamento | P5: Orçamento | AA5: Forecast
C6: P&L | D6: 46023 | E6: 46054 | F6: 46082 | G6: 1T2026 | I6: 46023 | J6: 46054 | K6: 46082 | L6: 1T2026 | N6: A/B | P6: 46113 | Q6: 46143 | R6: 46174 | S6: 46204 | T6: 46235 | U6: 46266 | V6: 46296 | W6: 46327 | X6: 46357 | Y6: 2026 | AA6: 46023 | AB6: 46054 | AC6: 46082 | AD6: 46113 | AE6: 46143 | AF6: 46174 | AG6: 46204 | AH6: 46235 | AI6: 46266 | AJ6: 46296 | AK6: 46327 | AL6: 46357 | AM6: 2026
C8: Alocação de Despesas
C10: People | D10: =SUMIFS('Rateio Fopag'!$F:$F,'Rateio Fopag'!$H:$H,MONTH(D$6)) -> 3600312.7 | E10: =SUMIFS('Rateio Fopag'!$F:$F,'Rateio Fopag'!$H:$H,MONTH(E$6)) -> 3418096.2 | F10: =SUMIFS('Rateio Fopag'!$F:$F,'Rateio Fopag'!$H:$H,MONTH(F$6)) -> 3875704.1 | G10: =SUM(D10:F10) -> 10894113 | I10: =SUMIFS('Rateio Folha'!$BW:$BW,'Rateio Folha'!$C:$C,MONTH('Breakdown Alocação de Despesas'!I$6)) -> 3478663.2 | J10: =SUMIFS('Rateio Folha'!$BW:$BW,'Rateio Folha'!$C:$C,MONTH('Breakdown Alocação de Despesas'!J$6)) -> 3541853.3 | K10: =SUMIFS('Rateio Folha'!$BW:$BW,'Rateio Folha'!$C:$C,MONTH('Breakdown Alocação de Despesas'!K$6)) -> 3713270.3 | L10: =SUM(I10:K10) -> 10733787 | N10: =G10/L10-1 -> 0.014936593 | P10: =SUMIFS('Rateio Folha'!$BW:$BW,'Rateio Folha'!$C:$C,MONTH('Breakdown Alocação de Despesas'!P$6)) -> 3670871.5 | Q10: =SUMIFS('Rateio Folha'!$BW:$BW,'Rateio Folha'!$C:$C,MONTH('Breakdown Alocação de Despesas'!Q$6)) -> 4247867.8 | R10: =SUMIFS('Rateio Folha'!$BW:$BW,'Rateio Folha'!$C:$C,MONTH('Breakdown Alocação de Despesas'!R$6)) -> 4379296.5 | S10: =SUMIFS('Rateio Folha'!$BW:$BW,'Rateio Folha'!$C:$C,MONTH('Breakdown Alocação de Despesas'!S$6)) -> 3980869.2 | T10: =SUMIFS('Rateio Folha'!$BW:$BW,'Rateio Folha'!$C:$C,MONTH('Breakdown Alocação de Despesas'!T$6)) -> 4516393 | U10: =SUMIFS('Rateio Folha'!$BW:$BW,'Rateio Folha'!$C:$C,MONTH('Breakdown Alocação de Despesas'!U$6)) -> 4454520.3 | V10: =SUMIFS('Rateio Folha'!$BW:$BW,'Rateio Folha'!$C:$C,MONTH('Breakdown Alocação de Despesas'!V$6)) -> 4524485.5 | W10: =SUMIFS('Rateio Folha'!$BW:$BW,'Rateio Folha'!$C:$C,MONTH('Breakdown Alocação de Despesas'!W$6)) -> 4569625.1 | X10: =SUMIFS('Rateio Folha'!$BW:$BW,'Rateio Folha'!$C:$C,MONTH('Breakdown Alocação de Despesas'!X$6)) -> 3669025.7 | Y10: =SUM(I10:K10,P10:X10) -> 48746741 | AA10: =SUM('Folha Forescast 3+9'!DL20:DL228) -> 4092749 | AB10: =SUM('Folha Forescast 3+9'!DM20:DM228) -> 3627867.3 | AC10: =SUM('Folha Forescast 3+9'!DN20:DN228) -> 3637565.6 | AD10: =SUM('Folha Forescast 3+9'!DO20:DO228) -> 3855026 | AE10: =SUM('Folha Forescast 3+9'!DP20:DP228) -> 3813012 | AF10: =SUM('Folha Forescast 3+9'!DQ20:DQ228) -> 3904544.1 | AG10: =SUM('Folha Forescast 3+9'!DR20:DR228) -> 3945282.2 | AH10: =SUM('Folha Forescast 3+9'!DS20:DS228) -> 3939840.4 | ... AL10: =SUM('Folha Forescast 3+9'!DW20:DW228) -> 3957682.1 | AM10: =SUM(AA10:AL10) -> 46613759
A13: Marketing | C13: Marketing | D13: =SUMIFS('Rateio Fopag'!$F:$F,'Rateio Fopag'!$H:$H,MONTH(D$6),'Rateio Fopag'!$K:$K,'Breakdown Alocação de Despesas'!$C13) -> 327918.8 | E13: =SUMIFS('Rateio Fopag'!$F:$F,'Rateio Fopag'!$H:$H,MONTH(E$6),'Rateio Fopag'!$K:$K,'Breakdown Alocação de Despesas'!$C13) -> 348699.9 | F13: =SUMIFS('Rateio Fopag'!$F:$F,'Rateio Fopag'!$H:$H,MONTH(F$6),'Rateio Fopag'!$K:$K,'Breakdown Alocação de Despesas'!$C13) -> 448649.26 | G13: =SUM(D13:F13) -> 1125268 | I13: =SUMIFS('Rateio Folha'!$BY:$BY,'Rateio Folha'!$C:$C,MONTH('Breakdown Alocação de Despesas'!I$6)) -> 375658.8 | J13: =SUMIFS('Rateio Folha'!$BY:$BY,'Rateio Folha'!$C:$C,MONTH('Breakdown Alocação de Despesas'!J$6)) -> 389297.59 | K13: =SUMIFS('Rateio Folha'!$BY:$BY,'Rateio Folha'!$C:$C,MONTH('Breakdown Alocação de Despesas'!K$6)) -> 412147.5 | L13: =SUM(I13:K13) -> 1177103.9 | N13: =G13/L13-1 -> -0.044036837 | P13: =SUMIFS('Rateio Folha'!$BY:$BY,'Rateio Folha'!$C:$C,MONTH('Breakdown Alocação de Despesas'!P$6)) -> 412147.5 | Q13: =SUMIFS('Rateio Folha'!$BY:$BY,'Rateio Folha'!$C:$C,MONTH('Breakdown Alocação de Despesas'!Q$6)) -> 517182.5 | R13: =SUMIFS('Rateio Folha'!$BY:$BY,'Rateio Folha'!$C:$C,MONTH('Breakdown Alocação de Despesas'!R$6)) -> 529132.83 | S13: =SUMIFS('Rateio Folha'!$BY:$BY,'Rateio Folha'!$C:$C,MONTH('Breakdown Alocação de Despesas'!S$6)) -> 455387.47 | T13: =SUMIFS('Rateio Folha'!$BY:$BY,'Rateio Folha'!$C:$C,MONTH('Breakdown Alocação de Despesas'!T$6)) -> 530264.52 | U13: =SUMIFS('Rateio Folha'!$BY:$BY,'Rateio Folha'!$C:$C,MONTH('Breakdown Alocação de Despesas'!U$6)) -> 508423.92 | V13: =SUMIFS('Rateio Folha'!$BY:$BY,'Rateio Folha'!$C:$C,MONTH('Breakdown Alocação de Despesas'!V$6)) -> 527681.82 | W13: =SUMIFS('Rateio Folha'!$BY:$BY,'Rateio Folha'!$C:$C,MONTH('Breakdown Alocação de Despesas'!W$6)) -> 533564.16 | X13: =SUMIFS('Rateio Folha'!$BY:$BY,'Rateio Folha'!$C:$C,MONTH('Breakdown Alocação de Despesas'!X$6)) -> 427521.46 | Y13: =SUM(I13:K13,P13:X13) -> 5618410.1 | AA13: =SUMIFS('Folha Forescast 3+9'!DL:DL,'Folha Forescast 3+9'!$H:$H,'Breakdown Alocação de Despesas'!$C13) -> 347637.4 | AB13: =SUMIFS('Folha Forescast 3+9'!DM:DM,'Folha Forescast 3+9'!$H:$H,'Breakdown Alocação de Despesas'!$C13) -> 355767.08 | AC13: =SUMIFS('Folha Forescast 3+9'!DN:DN,'Folha Forescast 3+9'!$H:$H,'Breakdown Alocação de Despesas'!$C13) -> 342573.06 | AD13: =SUMIFS('Folha Forescast 3+9'!DO:DO,'Folha Forescast 3+9'!$H:$H,'Breakdown Alocação de Despesas'!$C13) -> 332903.79 | AE13: =SUMIFS('Folha Forescast 3+9'!DP:DP,'Folha Forescast 3+9'!$H:$H,'Breakdown Alocação de Despesas'!$C13) -> 389568.25 | AF13: =SUMIFS('Folha Forescast 3+9'!DQ:DQ,'Folha Forescast 3+9'!$H:$H,'Breakdown Alocação de Despesas'!$C13) -> 403529.93 | AG13: =SUMIFS('Folha Forescast 3+9'!DR:DR,'Folha Forescast 3+9'!$H:$H,'Breakdown Alocação de Despesas'!$C13) -> 403529.93 | AH13: =SUMIFS('Folha Forescast 3+9'!DS:DS,'Folha Forescast 3+9'!$H:$H,'Breakdown Alocação de Despesas'!$C13) -> 403529.93 | AI13: =SUMIFS('Folha Forescast 3+9'!DT:DT,'Folha Forescast 3+9'!$H:$H,'Breakdown Alocação de Despesas'!$C13) -> 414467.48 | AJ13: =SUMIFS('Folha Forescast 3+9'!DU:DU,'Folha Forescast 3+9'!$H:$H,'Breakdown Alocação de Despesas'!$C13) -> 414467.48 | AK13: =SUMIFS('Folha Forescast 3+9'!DV:DV,'Folha Forescast 3+9'!$H:$H,'Breakdown Alocação de Despesas'!$C13) -> 414467.48 | AL13: =SUMIFS('Folha Forescast 3+9'!DW:DW,'Folha Forescast 3+9'!$H:$H,'Breakdown Alocação de Despesas'!$C13) -> 414467.48 | AM13: =SUM(AA13:AL13) -> 4636909.3
C14: % Alocada da Folha Total | D14: =D13/D$10 -> 0.091080644 | E14: =E13/E$10 -> 0.10201582 | F14: =F13/F$10 -> 0.11575942 | G14: =G13/G$10 -> 0.10329138 | I14: =I13/I$10 -> 0.10798941 | J14: =J13/J$10 -> 0.10991353 | K14: =K13/K$10 -> 0.11099313 | L14: =L13/L$10 -> 0.10966343 | P14: =P13/P$10 -> 0.11227511 | Q14: =Q13/Q$10 -> 0.12175108 | R14: =R13/R$10 -> 0.12082599 | S14: =S13/S$10 -> 0.11439398 | T14: =T13/T$10 -> 0.11740885 | U14: =U13/U$10 -> 0.11413663 | V14: =V13/V$10 -> 0.11662803 | W14: =W13/W$10 -> 0.11676322 | ... Y14: =Y13/Y$10 -> 0.11525714 | AA14: =AA13/AA$10 -> 0.08493983 | AB14: =AB13/AB$10 -> 0.098065074 | AC14: =AC13/AC$10 -> 0.094176463 | AD14: =AD13/AD$10 -> 0.086355784 | AE14: =AE13/AE$10 -> 0.10216812 | AF14: =AF13/AF$10 -> 0.1033488 | AG14: =AG13/AG$10 -> 0.10228164 | AH14: =AH13/AH$10 -> 0.10242291 | ... AM14: =AM13/AM$10 -> 0.099475121
A16: =C16 -> Marketing B2C | C16: Marketing B2C | D16: =SUMIFS('Rateio Fopag'!$F:$F,'Rateio Fopag'!$H:$H,MONTH(D$6),'Rateio Fopag'!$J:$J,'Breakdown Alocação de Despesas'!$C16) -> 270557.22 | E16: =SUMIFS('Rateio Fopag'!$F:$F,'Rateio Fopag'!$H:$H,MONTH(E$6),'Rateio Fopag'!$J:$J,'Breakdown Alocação de Despesas'!$C16) -> 292022.64 | F16: =SUMIFS('Rateio Fopag'!$F:$F,'Rateio Fopag'!$H:$H,MONTH(F$6),'Rateio Fopag'!$J:$J,'Breakdown Alocação de Despesas'!$C16) -> 358501.78 | G16: =SUM(D16:F16) -> 921081.64 | I16: =SUMIFS('Rateio Folha'!BZ:BZ,'Rateio Folha'!$C:$C,MONTH('Breakdown Alocação de Despesas'!I$6)) -> 308232.15 | J16: =SUMIFS('Rateio Folha'!$CA:$CA,'Rateio Folha'!$C:$C,MONTH('Breakdown Alocação de Despesas'!J$6)) -> 67426.65 | K16: =SUMIFS('Rateio Folha'!$CA:$CA,'Rateio Folha'!$C:$C,MONTH('Breakdown Alocação de Despesas'!K$6)) -> 90276.56 | L16: =SUM(I16:K16) -> 465935.36 | N16: =G16/L16-1 -> 0.97684427 | P16: =SUMIFS('Rateio Folha'!$CA:$CA,'Rateio Folha'!$C:$C,MONTH('Breakdown Alocação de Despesas'!P$6)) -> 90276.56 | Q16: =SUMIFS('Rateio Folha'!$CA:$CA,'Rateio Folha'!$C:$C,MONTH('Breakdown Alocação de Despesas'!Q$6)) -> 136812.17 | R16: =SUMIFS('Rateio Folha'!$CA:$CA,'Rateio Folha'!$C:$C,MONTH('Breakdown Alocação de Despesas'!R$6)) -> 140150.97 | S16: =SUMIFS('Rateio Folha'!$CA:$CA,'Rateio Folha'!$C:$C,MONTH('Breakdown Alocação de Despesas'!S$6)) -> 119547.29 | T16: =SUMIFS('Rateio Folha'!$CA:$CA,'Rateio Folha'!$C:$C,MONTH('Breakdown Alocação de Despesas'!T$6)) -> 142860.88 | U16: =SUMIFS('Rateio Folha'!$CA:$CA,'Rateio Folha'!$C:$C,MONTH('Breakdown Alocação de Despesas'!U$6)) -> 136654.86 | V16: =SUMIFS('Rateio Folha'!$CA:$CA,'Rateio Folha'!$C:$C,MONTH('Breakdown Alocação de Despesas'!V$6)) -> 142127 | W16: =SUMIFS('Rateio Folha'!$CA:$CA,'Rateio Folha'!$C:$C,MONTH('Breakdown Alocação de Despesas'!W$6)) -> 143798.47 | X16: =SUMIFS('Rateio Folha'!$CA:$CA,'Rateio Folha'!$C:$C,MONTH('Breakdown Alocação de Despesas'!X$6)) -> 113666.37 | Y16: =SUM(I16:K16,P16:X16) -> 1631829.9 | AA16: =SUMIFS('Folha Forescast 3+9'!DL:DL,'Folha Forescast 3+9'!$I:$I,$C16) -> 279980 | AB16: =SUMIFS('Folha Forescast 3+9'!DM:DM,'Folha Forescast 3+9'!$I:$I,$C16) -> 297173.65 | AC16: =SUMIFS('Folha Forescast 3+9'!DN:DN,'Folha Forescast 3+9'!$I:$I,$C16) -> 274979.2 | AD16: =SUMIFS('Folha Forescast 3+9'!DO:DO,'Folha Forescast 3+9'!$I:$I,$C16) -> 265309.93 | AE16: =SUMIFS('Folha Forescast 3+9'!DP:DP,'Folha Forescast 3+9'!$I:$I,$C16) -> 309876.26 | AF16: =SUMIFS('Folha Forescast 3+9'!DQ:DQ,'Folha Forescast 3+9'!$I:$I,$C16) -> 301083.6 | AG16: =SUMIFS('Folha Forescast 3+9'!DR:DR,'Folha Forescast 3+9'!$I:$I,$C16) -> 301083.6 | AH16: =SUMIFS('Folha Forescast 3+9'!DS:DS,'Folha Forescast 3+9'!$I:$I,$C16) -> 301083.6 | AI16: =SUMIFS('Folha Forescast 3+9'!DT:DT,'Folha Forescast 3+9'!$I:$I,$C16) -> 312021.14 | AJ16: =SUMIFS('Folha Forescast 3+9'!DU:DU,'Folha Forescast 3+9'!$I:$I,$C16) -> 312021.14 | AK16: =SUMIFS('Folha Forescast 3+9'!DV:DV,'Folha Forescast 3+9'!$I:$I,$C16) -> 312021.14 | AL16: =SUMIFS('Folha Forescast 3+9'!DW:DW,'Folha Forescast 3+9'!$I:$I,$C16) -> 312021.14 | AM16: =SUM(AA16:AL16) -> 3578654.4
C17: % Alocada da Folha de Marketing | D17: =D16/D$10 -> 0.075148255 | E17: =E16/E$10 -> 0.085434295 | F17: =F16/F$10 -> 0.092499781 | G17: =G16/G$10 -> 0.084548567 | I17: =I16/I$10 -> 0.088606492 | J17: =J16/J$10 -> 0.01903711 | K17: =K16/K$10 -> 0.024311874 | L17: =L16/L$10 -> 0.043408292 | N17: =G17/L17-1 -> 0.9477515 | P17: =P16/P$10 -> 0.024592678 | Q17: =Q16/Q$10 -> 0.032207257 | R17: =R16/R$10 -> 0.032003078 | S17: =S16/S$10 -> 0.030030448 | T17: =T16/T$10 -> 0.031631631 | U17: =U16/U$10 -> 0.030677794 | V17: =V16/V$10 -> 0.031412854 | W17: =W16/W$10 -> 0.03146833 | ... Y17: =Y16/Y$10 -> 0.033475672 | AA17: =AA16/AA$10 -> 0.068408789 | AB17: =AB16/AB$10 -> 0.081914145 | AC17: =AC16/AC$10 -> 0.075594294 | AD17: =AD16/AD$10 -> 0.068821827 | AE17: =AE16/AE$10 -> 0.081268107 | AF17: =AF16/AF$10 -> 0.077111077 | AG17: =AG16/AG$10 -> 0.076314845 | AH17: =AH16/AH$10 -> 0.076420254 | ... AM17: =AM16/AM$10 -> 0.076772493
A19: =C19 -> Marketing B2B | C19: Marketing B2B | D19: =SUMIFS('Rateio Fopag'!$F:$F,'Rateio Fopag'!$H:$H,MONTH(D$6),'Rateio Fopag'!$J:$J,'Breakdown Alocação de Despesas'!$C19) -> 57361.581 | E19: =SUMIFS('Rateio Fopag'!$F:$F,'Rateio Fopag'!$H:$H,MONTH(E$6),'Rateio Fopag'!$J:$J,'Breakdown Alocação de Despesas'!$C19) -> 56677.259 | F19: =SUMIFS('Rateio Fopag'!$F:$F,'Rateio Fopag'!$H:$H,MONTH(F$6),'Rateio Fopag'!$J:$J,'Breakdown Alocação de Despesas'!$C19) -> 90147.477 | G19: =SUM(D19:F19) -> 204186.32 | I19: =SUMIFS('Rateio Folha'!CA:CA,'Rateio Folha'!$C:$C,MONTH('Breakdown Alocação de Despesas'!I$6)) -> 67426.65 | J19: =SUMIFS('Rateio Folha'!$BZ:$BZ,'Rateio Folha'!$C:$C,MONTH('Breakdown Alocação de Despesas'!J$6)) -> 321870.94 | K19: =SUMIFS('Rateio Folha'!$BZ:$BZ,'Rateio Folha'!$C:$C,MONTH('Breakdown Alocação de Despesas'!K$6)) -> 321870.94 | L19: =SUM(I19:K19) -> 711168.53 | N19: =G19/L19-1 -> -0.71288618 | P19: =SUMIFS('Rateio Folha'!$BZ:$BZ,'Rateio Folha'!$C:$C,MONTH('Breakdown Alocação de Despesas'!P$6)) -> 321870.94 | Q19: =SUMIFS('Rateio Folha'!$BZ:$BZ,'Rateio Folha'!$C:$C,MONTH('Breakdown Alocação de Despesas'!Q$6)) -> 380370.33 | R19: =SUMIFS('Rateio Folha'!$BZ:$BZ,'Rateio Folha'!$C:$C,MONTH('Breakdown Alocação de Despesas'!R$6)) -> 388981.86 | S19: =SUMIFS('Rateio Folha'!$BZ:$BZ,'Rateio Folha'!$C:$C,MONTH('Breakdown Alocação de Despesas'!S$6)) -> 335840.19 | T19: =SUMIFS('Rateio Folha'!$BZ:$BZ,'Rateio Folha'!$C:$C,MONTH('Breakdown Alocação de Despesas'!T$6)) -> 387403.64 | U19: =SUMIFS('Rateio Folha'!$BZ:$BZ,'Rateio Folha'!$C:$C,MONTH('Breakdown Alocação de Despesas'!U$6)) -> 371769.07 | V19: =SUMIFS('Rateio Folha'!$BZ:$BZ,'Rateio Folha'!$C:$C,MONTH('Breakdown Alocação de Despesas'!V$6)) -> 385554.82 | W19: =SUMIFS('Rateio Folha'!$BZ:$BZ,'Rateio Folha'!$C:$C,MONTH('Breakdown Alocação de Despesas'!W$6)) -> 389765.69 | X19: =SUMIFS('Rateio Folha'!$BZ:$BZ,'Rateio Folha'!$C:$C,MONTH('Breakdown Alocação de Despesas'!X$6)) -> 313855.1 | Y19: =SUM(I19:K19,P19:X19) -> 3986580.2 | AA19: =SUMIFS('Folha Forescast 3+9'!DL:DL,'Folha Forescast 3+9'!$I:$I,$C19) -> 67657.398 | AB19: =SUMIFS('Folha Forescast 3+9'!DM:DM,'Folha Forescast 3+9'!$I:$I,$C19) -> 58593.428 | AC19: =SUMIFS('Folha Forescast 3+9'!DN:DN,'Folha Forescast 3+9'!$I:$I,$C19) -> 67593.859 | AD19: =SUMIFS('Folha Forescast 3+9'!DO:DO,'Folha Forescast 3+9'!$I:$I,$C19) -> 67593.859 | AE19: =SUMIFS('Folha Forescast 3+9'!DP:DP,'Folha Forescast 3+9'!$I:$I,$C19) -> 79691.982 | AF19: =SUMIFS('Folha Forescast 3+9'!DQ:DQ,'Folha Forescast 3+9'!$I:$I,$C19) -> 102446.33 | AG19: =SUMIFS('Folha Forescast 3+9'!DR:DR,'Folha Forescast 3+9'!$I:$I,$C19) -> 102446.33 | AH19: =SUMIFS('Folha Forescast 3+9'!DS:DS,'Folha Forescast 3+9'!$I:$I,$C19) -> 102446.33 | AI19: =SUMIFS('Folha Forescast 3+9'!DT:DT,'Folha Forescast 3+9'!$I:$I,$C19) -> 102446.33 | AJ19: =SUMIFS('Folha Forescast 3+9'!DU:DU,'Folha Forescast 3+9'!$I:$I,$C19) -> 102446.33 | AK19: =SUMIFS('Folha Forescast 3+9'!DV:DV,'Folha Forescast 3+9'!$I:$I,$C19) -> 102446.33 | AL19: =SUMIFS('Folha Forescast 3+9'!DW:DW,'Folha Forescast 3+9'!$I:$I,$C19) -> 102446.33 | AM19: =SUM(AA19:AL19) -> 1058254.8
C20: % Alocada da Folha de Marketing | D20: =D19/D$10 -> 0.015932389 | E20: =E19/E$10 -> 0.016581528 | F20: =F19/F$10 -> 0.023259639 | G20: =G19/G$10 -> 0.018742813 | I20: =I19/I$10 -> 0.01938292 | J20: =J19/J$10 -> 0.090876419 | K20: =K19/K$10 -> 0.086681258 | L20: =L19/L$10 -> 0.066255139 | N20: =G20/L20-1 -> -0.71711156 | P20: =P19/P$10 -> 0.087682432 | Q20: =Q19/Q$10 -> 0.089543823 | R20: =R19/R$10 -> 0.08882291 | S20: =S19/S$10 -> 0.084363532 | T20: =T19/T$10 -> 0.085777221 | U20: =U19/U$10 -> 0.083458832 | V20: =V19/V$10 -> 0.085215174 | W20: =W19/W$10 -> 0.085294894 | ... Y20: =Y19/Y$10 -> 0.08178147 | AA20: =AA19/AA$10 -> 0.01653104 | AB20: =AB19/AB$10 -> 0.016150929 | AC20: =AC19/AC$10 -> 0.018582169 | AD20: =AD19/AD$10 -> 0.017533957 | AE20: =AE19/AE$10 -> 0.020900008 | AF20: =AF19/AF$10 -> 0.026237719 | AG20: =AG19/AG$10 -> 0.025966794 | AH20: =AH19/AH$10 -> 0.02600266 | ... AM20: =AM19/AM$10 -> 0.022702629
A22: =C22 -> Vendas | C22: Vendas | D22: =SUMIFS('Rateio Fopag'!$F:$F,'Rateio Fopag'!$H:$H,MONTH(D$6),'Rateio Fopag'!$K:$K,'Breakdown Alocação de Despesas'!$C22) -> 661214.49 | E22: =SUMIFS('Rateio Fopag'!$F:$F,'Rateio Fopag'!$H:$H,MONTH(E$6),'Rateio Fopag'!$K:$K,'Breakdown Alocação de Despesas'!$C22) -> 650085.15 | F22: =SUMIFS('Rateio Fopag'!$F:$F,'Rateio Fopag'!$H:$H,MONTH(F$6),'Rateio Fopag'!$K:$K,'Breakdown Alocação de Despesas'!$C22) -> 745764.09 | G22: =SUM(D22:F22) -> 2057063.7 | I22: =SUMIFS('Rateio Folha'!$CB:$CB,'Rateio Folha'!$C:$C,MONTH('Breakdown Alocação de Despesas'!I$6)) -> 557625.36 | J22: =SUMIFS('Rateio Folha'!$CB:$CB,'Rateio Folha'!$C:$C,MONTH('Breakdown Alocação de Despesas'!J$6)) -> 557625.36 | K22: =SUMIFS('Rateio Folha'!$CB:$CB,'Rateio Folha'!$C:$C,MONTH('Breakdown Alocação de Despesas'!K$6)) -> 632725.05 | L22: =SUM(I22:K22) -> 1747975.8 | N22: =G22/L22-1 -> 0.17682623 | P22: =SUMIFS('Rateio Folha'!$CB:$CB,'Rateio Folha'!$C:$C,MONTH('Breakdown Alocação de Despesas'!P$6)) -> 669620.48 | Q22: =SUMIFS('Rateio Folha'!$CB:$CB,'Rateio Folha'!$C:$C,MONTH('Breakdown Alocação de Despesas'!Q$6)) -> 811332.46 | R22: =SUMIFS('Rateio Folha'!$CB:$CB,'Rateio Folha'!$C:$C,MONTH('Breakdown Alocação de Despesas'!R$6)) -> 833887.31 | S22: =SUMIFS('Rateio Folha'!$CB:$CB,'Rateio Folha'!$C:$C,MONTH('Breakdown Alocação de Despesas'!S$6)) -> 745855.27 | T22: =SUMIFS('Rateio Folha'!$CB:$CB,'Rateio Folha'!$C:$C,MONTH('Breakdown Alocação de Despesas'!T$6)) -> 903155.53 | U22: =SUMIFS('Rateio Folha'!$CB:$CB,'Rateio Folha'!$C:$C,MONTH('Breakdown Alocação de Despesas'!U$6)) -> 865659.18 | V22: =SUMIFS('Rateio Folha'!$CB:$CB,'Rateio Folha'!$C:$C,MONTH('Breakdown Alocação de Despesas'!V$6)) -> 898721.49 | W22: =SUMIFS('Rateio Folha'!$CB:$CB,'Rateio Folha'!$C:$C,MONTH('Breakdown Alocação de Despesas'!W$6)) -> 908820.41 | X22: =SUMIFS('Rateio Folha'!$CB:$CB,'Rateio Folha'!$C:$C,MONTH('Breakdown Alocação de Despesas'!X$6)) -> 726764.33 | Y22: =SUM(I22:K22,P22:X22) -> 9111792.2 | AA22: =SUMIFS('Folha Forescast 3+9'!DL:DL,'Folha Forescast 3+9'!$H:$H,'Breakdown Alocação de Despesas'!$C22) -> 984896.81 | AB22: =SUMIFS('Folha Forescast 3+9'!DM:DM,'Folha Forescast 3+9'!$H:$H,'Breakdown Alocação de Despesas'!$C22) -> 981189.39 | AC22: =SUMIFS('Folha Forescast 3+9'!DN:DN,'Folha Forescast 3+9'!$H:$H,'Breakdown Alocação de Despesas'!$C22) -> 973192.21 | AD22: =SUMIFS('Folha Forescast 3+9'!DO:DO,'Folha Forescast 3+9'!$H:$H,'Breakdown Alocação de Despesas'!$C22) -> 984552.64 | AE22: =SUMIFS('Folha Forescast 3+9'!DP:DP,'Folha Forescast 3+9'!$H:$H,'Breakdown Alocação de Despesas'!$C22) -> 1032203.6 | AF22: =SUMIFS('Folha Forescast 3+9'!DQ:DQ,'Folha Forescast 3+9'!$H:$H,'Breakdown Alocação de Despesas'!$C22) -> 1080065.4 | AG22: =SUMIFS('Folha Forescast 3+9'!DR:DR,'Folha Forescast 3+9'!$H:$H,'Breakdown Alocação de Despesas'!$C22) -> 1139256 | AH22: =SUMIFS('Folha Forescast 3+9'!DS:DS,'Folha Forescast 3+9'!$H:$H,'Breakdown Alocação de Despesas'!$C22) -> 1160779.4 | AI22: =SUMIFS('Folha Forescast 3+9'!DT:DT,'Folha Forescast 3+9'!$H:$H,'Breakdown Alocação de Despesas'!$C22) -> 1160779.4 | AJ22: =SUMIFS('Folha Forescast 3+9'!DU:DU,'Folha Forescast 3+9'!$H:$H,'Breakdown Alocação de Despesas'!$C22) -> 1160779.4 | AK22: =SUMIFS('Folha Forescast 3+9'!DV:DV,'Folha Forescast 3+9'!$H:$H,'Breakdown Alocação de Despesas'!$C22) -> 1160779.4 | AL22: =SUMIFS('Folha Forescast 3+9'!DW:DW,'Folha Forescast 3+9'!$H:$H,'Breakdown Alocação de Despesas'!$C22) -> 1160779.4 | AM22: =SUM(AA22:AL22) -> 12979253
C23: % Alocada da Folha Total | D23: =D22/D$10 -> 0.18365474 | E23: =E22/E$10 -> 0.19018925 | F23: =F22/F$10 -> 0.19242029 | G23: =G22/G$10 -> 0.18882343 | I23: =I22/I$10 -> 0.16029875 | J23: =J22/J$10 -> 0.15743887 | K23: =K22/K$10 -> 0.17039563 | L23: =L22/L$10 -> 0.16284801 | P23: =P22/P$10 -> 0.18241458 | Q23: =Q22/Q$10 -> 0.19099758 | R23: =R22/R$10 -> 0.19041581 | S23: =S22/S$10 -> 0.18735991 | T23: =T22/T$10 -> 0.19997275 | U23: =U22/U$10 -> 0.19433275 | V23: =V22/V$10 -> 0.19863507 | W23: =W22/W$10 -> 0.19888292 | ... Y23: =Y22/Y$10 -> 0.18692105 | AA23: =AA22/AA$10 -> 0.24064432 | AB23: =AB22/AB$10 -> 0.270459 | AC23: =AC22/AC$10 -> 0.26753943 | AD23: =AD22/AD$10 -> 0.25539455 | AE23: =AE22/AE$10 -> 0.27070558 | AF23: =AF22/AF$10 -> 0.27661754 | AG23: =AG22/AG$10 -> 0.28876414 | AH23: =AH22/AH$10 -> 0.29462599 | ... AM23: =AM22/AM$10 -> 0.27844253
A25: =C25 -> Vendas B2C | C25: Vendas B2C | D25: =SUMIFS('Rateio Fopag'!$F:$F,'Rateio Fopag'!$H:$H,MONTH(D$6),'Rateio Fopag'!$J:$J,'Breakdown Alocação de Despesas'!$C25) -> 310408.26 | E25: =SUMIFS('Rateio Fopag'!$F:$F,'Rateio Fopag'!$H:$H,MONTH(E$6),'Rateio Fopag'!$J:$J,'Breakdown Alocação de Despesas'!$C25) -> 317192.51 | F25: =SUMIFS('Rateio Fopag'!$F:$F,'Rateio Fopag'!$H:$H,MONTH(F$6),'Rateio Fopag'!$J:$J,'Breakdown Alocação de Despesas'!$C25) -> 353725.64 | G25: =SUM(D25:F25) -> 981326.41 | I25: =SUMIFS('Rateio Folha'!$CD:$CD,'Rateio Folha'!$C:$C,MONTH('Breakdown Alocação de Despesas'!I$6)) -> 248960.81 | J25: =SUMIFS('Rateio Folha'!$CD:$CD,'Rateio Folha'!$C:$C,MONTH('Breakdown Alocação de Despesas'!J$6)) -> 248960.81 | K25: =SUMIFS('Rateio Folha'!$CD:$CD,'Rateio Folha'!$C:$C,MONTH('Breakdown Alocação de Despesas'!K$6)) -> 280476.73 | L25: =SUM(I25:K25) -> 778398.34 | N25: =G25/L25-1 -> 0.26069951 | P25: =SUMIFS('Rateio Folha'!$CD:$CD,'Rateio Folha'!$C:$C,MONTH('Breakdown Alocação de Despesas'!P$6)) -> 288473.91 | Q25: =SUMIFS('Rateio Folha'!$CD:$CD,'Rateio Folha'!$C:$C,MONTH('Breakdown Alocação de Despesas'!Q$6)) -> 359419.76 | R25: =SUMIFS('Rateio Folha'!$CD:$CD,'Rateio Folha'!$C:$C,MONTH('Breakdown Alocação de Despesas'!R$6)) -> 371922.19 | S25: =SUMIFS('Rateio Folha'!$CD:$CD,'Rateio Folha'!$C:$C,MONTH('Breakdown Alocação de Despesas'!S$6)) -> 345923.51 | T25: =SUMIFS('Rateio Folha'!$CD:$CD,'Rateio Folha'!$C:$C,MONTH('Breakdown Alocação de Despesas'!T$6)) -> 405654.8 | U25: =SUMIFS('Rateio Folha'!$CD:$CD,'Rateio Folha'!$C:$C,MONTH('Breakdown Alocação de Despesas'!U$6)) -> 388032.75 | V25: =SUMIFS('Rateio Folha'!$CD:$CD,'Rateio Folha'!$C:$C,MONTH('Breakdown Alocação de Despesas'!V$6)) -> 403570.95 | W25: =SUMIFS('Rateio Folha'!$CD:$CD,'Rateio Folha'!$C:$C,MONTH('Breakdown Alocação de Despesas'!W$6)) -> 408317.11 | X25: =SUMIFS('Rateio Folha'!$CD:$CD,'Rateio Folha'!$C:$C,MONTH('Breakdown Alocação de Despesas'!X$6)) -> 322756.72 | Y25: =SUM(I25:K25,P25:X25) -> 4072470 | AA25: =SUMIFS('Folha Forescast 3+9'!DL:DL,'Folha Forescast 3+9'!$I:$I,$C25) -> 472707.43 | AB25: =SUMIFS('Folha Forescast 3+9'!DM:DM,'Folha Forescast 3+9'!$I:$I,$C25) -> 488701.79 | AC25: =SUMIFS('Folha Forescast 3+9'!DN:DN,'Folha Forescast 3+9'!$I:$I,$C25) -> 480704.61 | AD25: =SUMIFS('Folha Forescast 3+9'!DO:DO,'Folha Forescast 3+9'!$I:$I,$C25) -> 485720.86 | AE25: =SUMIFS('Folha Forescast 3+9'!DP:DP,'Folha Forescast 3+9'!$I:$I,$C25) -> 496674.96 | AF25: =SUMIFS('Folha Forescast 3+9'!DQ:DQ,'Folha Forescast 3+9'!$I:$I,$C25) -> 507612.5 | AG25: =SUMIFS('Folha Forescast 3+9'!DR:DR,'Folha Forescast 3+9'!$I:$I,$C25) -> 522067.11 | AH25: =SUMIFS('Folha Forescast 3+9'!DS:DS,'Folha Forescast 3+9'!$I:$I,$C25) -> 543590.49 | AI25: =SUMIFS('Folha Forescast 3+9'!DT:DT,'Folha Forescast 3+9'!$I:$I,$C25) -> 543590.49 | AJ25: =SUMIFS('Folha Forescast 3+9'!DU:DU,'Folha Forescast 3+9'!$I:$I,$C25) -> 543590.49 | AK25: =SUMIFS('Folha Forescast 3+9'!DV:DV,'Folha Forescast 3+9'!$I:$I,$C25) -> 543590.49 | AL25: =SUMIFS('Folha Forescast 3+9'!DW:DW,'Folha Forescast 3+9'!$I:$I,$C25) -> 543590.49 | AM25: =SUM(AA25:AL25) -> 6172141.7
C26: % Alocada da Folha de Vendas | D26: =D25/D$10 -> 0.086217028 | E26: =E25/E$10 -> 0.092798006 | F26: =F25/F$10 -> 0.091267452 | G26: =G25/G$10 -> 0.090078597 | I26: =I25/I$10 -> 0.071567953 | J26: =J25/J$10 -> 0.070291113 | K26: =K25/K$10 -> 0.075533615 | L26: =L25/L$10 -> 0.072518521 | P26: =P25/P$10 -> 0.078584583 | Q26: =Q25/Q$10 -> 0.084611803 | R26: =R25/R$10 -> 0.084927381 | S26: =S25/S$10 -> 0.086896477 | T26: =T25/T$10 -> 0.089818313 | U26: =U25/U$10 -> 0.087109883 | V26: =V25/V$10 -> 0.089197093 | W26: =W25/W$10 -> 0.089354619 | ... Y26: =Y25/Y$10 -> 0.083543431 | AA26: =AA25/AA$10 -> 0.11549876 | AB26: =AB25/AB$10 -> 0.13470773 | AC26: =AC25/AC$10 -> 0.13215009 | AD26: =AD25/AD$10 -> 0.12599678 | AE26: =AE25/AE$10 -> 0.13025791 | AF26: =AF25/AF$10 -> 0.13000558 | AG26: =AG25/AG$10 -> 0.13232694 | AH26: =AH25/AH$10 -> 0.13797272 | ... AM26: =AM25/AM$10 -> 0.1324103
A28: =C28 -> Vendas B2B | C28: Vendas B2B | D28: =SUMIFS('Rateio Fopag'!$F:$F,'Rateio Fopag'!$H:$H,MONTH(D$6),'Rateio Fopag'!$J:$J,'Breakdown Alocação de Despesas'!$C28) -> 350806.23 | E28: =SUMIFS('Rateio Fopag'!$F:$F,'Rateio Fopag'!$H:$H,MONTH(E$6),'Rateio Fopag'!$J:$J,'Breakdown Alocação de Despesas'!$C28) -> 332892.63 | F28: =SUMIFS('Rateio Fopag'!$F:$F,'Rateio Fopag'!$H:$H,MONTH(F$6),'Rateio Fopag'!$J:$J,'Breakdown Alocação de Despesas'!$C28) -> 392038.46 | G28: =SUM(D28:F28) -> 1075737.3 | I28: =SUMIFS('Rateio Folha'!$CC:$CC,'Rateio Folha'!$C:$C,MONTH('Breakdown Alocação de Despesas'!I$6)) -> 308664.55 | J28: =SUMIFS('Rateio Folha'!$CC:$CC,'Rateio Folha'!$C:$C,MONTH('Breakdown Alocação de Despesas'!J$6)) -> 308664.55 | K28: =SUMIFS('Rateio Folha'!$CC:$CC,'Rateio Folha'!$C:$C,MONTH('Breakdown Alocação de Despesas'!K$6)) -> 352248.32 | L28: =SUM(I28:K28) -> 969577.42 | N28: =G28/L28-1 -> 0.10949089 | P28: =SUMIFS('Rateio Folha'!$CC:$CC,'Rateio Folha'!$C:$C,MONTH('Breakdown Alocação de Despesas'!P$6)) -> 381146.57 | Q28: =SUMIFS('Rateio Folha'!$CC:$CC,'Rateio Folha'!$C:$C,MONTH('Breakdown Alocação de Despesas'!Q$6)) -> 451912.71 | R28: =SUMIFS('Rateio Folha'!$CC:$CC,'Rateio Folha'!$C:$C,MONTH('Breakdown Alocação de Despesas'!R$6)) -> 461965.12 | S28: =SUMIFS('Rateio Folha'!$CC:$CC,'Rateio Folha'!$C:$C,MONTH('Breakdown Alocação de Despesas'!S$6)) -> 399931.77 | T28: =SUMIFS('Rateio Folha'!$CC:$CC,'Rateio Folha'!$C:$C,MONTH('Breakdown Alocação de Despesas'!T$6)) -> 497500.73 | U28: =SUMIFS('Rateio Folha'!$CC:$CC,'Rateio Folha'!$C:$C,MONTH('Breakdown Alocação de Despesas'!U$6)) -> 477626.43 | V28: =SUMIFS('Rateio Folha'!$CC:$CC,'Rateio Folha'!$C:$C,MONTH('Breakdown Alocação de Despesas'!V$6)) -> 495150.54 | W28: =SUMIFS('Rateio Folha'!$CC:$CC,'Rateio Folha'!$C:$C,MONTH('Breakdown Alocação de Despesas'!W$6)) -> 500503.3 | X28: =SUMIFS('Rateio Folha'!$CC:$CC,'Rateio Folha'!$C:$C,MONTH('Breakdown Alocação de Despesas'!X$6)) -> 404007.61 | Y28: =SUM(I28:K28,P28:X28) -> 5039322.2 | AA28: =SUMIFS('Folha Forescast 3+9'!DL:DL,'Folha Forescast 3+9'!$I:$I,$C28) -> 512189.38 | AB28: =SUMIFS('Folha Forescast 3+9'!DM:DM,'Folha Forescast 3+9'!$I:$I,$C28) -> 492487.6 | AC28: =SUMIFS('Folha Forescast 3+9'!DN:DN,'Folha Forescast 3+9'!$I:$I,$C28) -> 492487.6 | AD28: =SUMIFS('Folha Forescast 3+9'!DO:DO,'Folha Forescast 3+9'!$I:$I,$C28) -> 498831.77 | AE28: =SUMIFS('Folha Forescast 3+9'!DP:DP,'Folha Forescast 3+9'!$I:$I,$C28) -> 535528.64 | AF28: =SUMIFS('Folha Forescast 3+9'!DQ:DQ,'Folha Forescast 3+9'!$I:$I,$C28) -> 572452.9 | AG28: =SUMIFS('Folha Forescast 3+9'!DR:DR,'Folha Forescast 3+9'!$I:$I,$C28) -> 617188.9 | AH28: =SUMIFS('Folha Forescast 3+9'!DS:DS,'Folha Forescast 3+9'!$I:$I,$C28) -> 617188.9 | AI28: =SUMIFS('Folha Forescast 3+9'!DT:DT,'Folha Forescast 3+9'!$I:$I,$C28) -> 617188.9 | AJ28: =SUMIFS('Folha Forescast 3+9'!DU:DU,'Folha Forescast 3+9'!$I:$I,$C28) -> 617188.9 | AK28: =SUMIFS('Folha Forescast 3+9'!DV:DV,'Folha Forescast 3+9'!$I:$I,$C28) -> 617188.9 | AL28: =SUMIFS('Folha Forescast 3+9'!DW:DW,'Folha Forescast 3+9'!$I:$I,$C28) -> 617188.9 | AM28: =SUM(AA28:AL28) -> 6807111.3
C29: % Alocada da Folha de Vendas | D29: =D28/D$10 -> 0.097437712 | E29: =E28/E$10 -> 0.09739124 | F29: =F28/F$10 -> 0.10115284 | G29: =G28/G$10 -> 0.098744829 | I29: =I28/I$10 -> 0.088730794 | J29: =J28/J$10 -> 0.087147753 | K29: =K28/K$10 -> 0.094862019 | L29: =L28/L$10 -> 0.090329484 | P29: =P28/P$10 -> 0.10382999 | Q29: =Q28/Q$10 -> 0.10638577 | R29: =R28/R$10 -> 0.10548843 | S29: =S28/S$10 -> 0.10046343 | T29: =T28/T$10 -> 0.11015444 | U29: =U28/U$10 -> 0.10722286 | V29: =V28/V$10 -> 0.10943798 | W29: =W28/W$10 -> 0.10952831 | ... Y29: =Y28/Y$10 -> 0.10337762 | AA29: =AA28/AA$10 -> 0.12514556 | AB29: =AB28/AB$10 -> 0.13575127 | AC29: =AC28/AC$10 -> 0.13538934 | AD29: =AD28/AD$10 -> 0.12939777 | AE29: =AE28/AE$10 -> 0.14044767 | AF29: =AF28/AF$10 -> 0.14661197 | AG29: =AG28/AG$10 -> 0.1564372 | AH29: =AH28/AH$10 -> 0.15665327 | ... AM29: =AM28/AM$10 -> 0.14603223
A31: =C31 -> Produtos | C31: Produtos | D31: =SUMIFS('Rateio Fopag'!$F:$F,'Rateio Fopag'!$H:$H,MONTH(D$6),'Rateio Fopag'!$K:$K,'Breakdown Alocação de Despesas'!$C31) -> 903497.41 | E31: =SUMIFS('Rateio Fopag'!$F:$F,'Rateio Fopag'!$H:$H,MONTH(E$6),'Rateio Fopag'!$K:$K,'Breakdown Alocação de Despesas'!$C31) -> 833055.57 | F31: =SUMIFS('Rateio Fopag'!$F:$F,'Rateio Fopag'!$H:$H,MONTH(F$6),'Rateio Fopag'!$K:$K,'Breakdown Alocação de Despesas'!$C31) -> 886985.76 | G31: =SUM(D31:F31) -> 2623538.7 | I31: =SUMIFS('Rateio Folha'!$CE:$CE,'Rateio Folha'!$C:$C,MONTH('Breakdown Alocação de Despesas'!I$6)) -> 871773 | J31: =SUMIFS('Rateio Folha'!$CE:$CE,'Rateio Folha'!$C:$C,MONTH('Breakdown Alocação de Despesas'!J$6)) -> 900308 | K31: =SUMIFS('Rateio Folha'!$CE:$CE,'Rateio Folha'!$C:$C,MONTH('Breakdown Alocação de Despesas'!K$6)) -> 916811.21 | L31: =SUM(I31:K31) -> 2688892.2 | N31: =G31/L31-1 -> -0.02430498 | P31: =SUMIFS('Rateio Folha'!$CE:$CE,'Rateio Folha'!$C:$C,MONTH('Breakdown Alocação de Despesas'!P$6)) -> 856311.21 | Q31: =SUMIFS('Rateio Folha'!$CE:$CE,'Rateio Folha'!$C:$C,MONTH('Breakdown Alocação de Despesas'!Q$6)) -> 958848.58 | R31: =SUMIFS('Rateio Folha'!$CE:$CE,'Rateio Folha'!$C:$C,MONTH('Breakdown Alocação de Despesas'!R$6)) -> 971732.43 | S31: =SUMIFS('Rateio Folha'!$CE:$CE,'Rateio Folha'!$C:$C,MONTH('Breakdown Alocação de Despesas'!S$6)) -> 915226.29 | T31: =SUMIFS('Rateio Folha'!$CE:$CE,'Rateio Folha'!$C:$C,MONTH('Breakdown Alocação de Despesas'!T$6)) -> 1012716.4 | U31: =SUMIFS('Rateio Folha'!$CE:$CE,'Rateio Folha'!$C:$C,MONTH('Breakdown Alocação de Despesas'!U$6)) -> 988788.97 | V31: =SUMIFS('Rateio Folha'!$CE:$CE,'Rateio Folha'!$C:$C,MONTH('Breakdown Alocação de Despesas'!V$6)) -> 1009886.9 | W31: =SUMIFS('Rateio Folha'!$CE:$CE,'Rateio Folha'!$C:$C,MONTH('Breakdown Alocação de Despesas'!W$6)) -> 1016331.3 | X31: =SUMIFS('Rateio Folha'!$CE:$CE,'Rateio Folha'!$C:$C,MONTH('Breakdown Alocação de Despesas'!X$6)) -> 702742.96 | Y31: =SUM(I31:K31,P31:X31) -> 11121477 | AA31: =SUMIFS('Folha Forescast 3+9'!DL:DL,'Folha Forescast 3+9'!$H:$H,'Breakdown Alocação de Despesas'!$C31) -> 835426.78 | AB31: =SUMIFS('Folha Forescast 3+9'!DM:DM,'Folha Forescast 3+9'!$H:$H,'Breakdown Alocação de Despesas'!$C31) -> 732689.67 | AC31: =SUMIFS('Folha Forescast 3+9'!DN:DN,'Folha Forescast 3+9'!$H:$H,'Breakdown Alocação de Despesas'!$C31) -> 758007.43 | AD31: =SUMIFS('Folha Forescast 3+9'!DO:DO,'Folha Forescast 3+9'!$H:$H,'Breakdown Alocação de Despesas'!$C31) -> 958487.36 | AE31: =SUMIFS('Folha Forescast 3+9'!DP:DP,'Folha Forescast 3+9'!$H:$H,'Breakdown Alocação de Despesas'!$C31) -> 769982.63 | AF31: =SUMIFS('Folha Forescast 3+9'!DQ:DQ,'Folha Forescast 3+9'!$H:$H,'Breakdown Alocação de Despesas'!$C31) -> 769411.11 | AG31: =SUMIFS('Folha Forescast 3+9'!DR:DR,'Folha Forescast 3+9'!$H:$H,'Breakdown Alocação de Despesas'!$C31) -> 855315.37 | AH31: =SUMIFS('Folha Forescast 3+9'!DS:DS,'Folha Forescast 3+9'!$H:$H,'Breakdown Alocação de Despesas'!$C31) -> 851565.37 | AI31: =SUMIFS('Folha Forescast 3+9'!DT:DT,'Folha Forescast 3+9'!$H:$H,'Breakdown Alocação de Despesas'!$C31) -> 887190.37 | AJ31: =SUMIFS('Folha Forescast 3+9'!DU:DU,'Folha Forescast 3+9'!$H:$H,'Breakdown Alocação de Despesas'!$C31) -> 855315.37 | AK31: =SUMIFS('Folha Forescast 3+9'!DV:DV,'Folha Forescast 3+9'!$H:$H,'Breakdown Alocação de Despesas'!$C31) -> 851565.37 | AL31: =SUMIFS('Folha Forescast 3+9'!DW:DW,'Folha Forescast 3+9'!$H:$H,'Breakdown Alocação de Despesas'!$C31) -> 855315.37 | AM31: =SUM(AA31:AL31) -> 9980272.2
C32: % Alocada da Folha Total | D32: =D31/D$10 -> 0.2509497 | E32: =E31/E$10 -> 0.24371917 | F32: =F31/F$10 -> 0.22885797 | G32: =G31/G$10 -> 0.24082169 | I32: =I31/I$10 -> 0.25060575 | J32: =J31/J$10 -> 0.25419122 | K32: =K31/K$10 -> 0.24690128 | L32: =L31/L$10 -> 0.25050732 | P32: =P31/P$10 -> 0.23327191 | Q32: =Q31/Q$10 -> 0.22572467 | R32: =R31/R$10 -> 0.22189236 | S32: =S31/S$10 -> 0.22990615 | T32: =T31/T$10 -> 0.22423124 | U32: =U31/U$10 -> 0.22197429 | V32: =V31/V$10 -> 0.22320481 | W32: =W31/W$10 -> 0.22241022 | ... Y32: =Y31/Y$10 -> 0.22814812 | AA32: =AA31/AA$10 -> 0.20412363 | AB32: =AB31/AB$10 -> 0.20196154 | AC32: =AC31/AC$10 -> 0.20838317 | AD32: =AD31/AD$10 -> 0.24863318 | AE32: =AE31/AE$10 -> 0.20193554 | AF32: =AF31/AF$10 -> 0.1970553 | AG32: =AG31/AG$10 -> 0.21679447 | AH32: =AH31/AH$10 -> 0.2161421 | ... AM32: =AM31/AM$10 -> 0.21410572
A34: Consulting | C34: Consulting | D34: =SUMIFS('Rateio Fopag'!$F:$F,'Rateio Fopag'!$H:$H,MONTH(D$6),'Rateio Fopag'!$J:$J,'Breakdown Alocação de Despesas'!$C34) -> 175500 | E34: =SUMIFS('Rateio Fopag'!$F:$F,'Rateio Fopag'!$H:$H,MONTH(E$6),'Rateio Fopag'!$J:$J,'Breakdown Alocação de Despesas'!$C34) -> 160500 | F34: =SUMIFS('Rateio Fopag'!$F:$F,'Rateio Fopag'!$H:$H,MONTH(F$6),'Rateio Fopag'!$J:$J,'Breakdown Alocação de Despesas'!$C34) -> 189800 | G34: =SUM(D34:F34) -> 525800 | I34: =SUMIFS('Rateio Folha'!$CF:$CF,'Rateio Folha'!$C:$C,MONTH('Breakdown Alocação de Despesas'!I$6)) -> 178500 | J34: =SUMIFS('Rateio Folha'!$CF:$CF,'Rateio Folha'!$C:$C,MONTH('Breakdown Alocação de Despesas'!J$6)) -> 178500 | K34: =SUMIFS('Rateio Folha'!$CF:$CF,'Rateio Folha'!$C:$C,MONTH('Breakdown Alocação de Despesas'!K$6)) -> 193500 | L34: =SUM(I34:K34) -> 550500 | N34: =G34/L34-1 -> -0.044868302 | P34: =SUMIFS('Rateio Folha'!$CF:$CF,'Rateio Folha'!$C:$C,MONTH('Breakdown Alocação de Despesas'!P$6)) -> 193500 | Q34: =SUMIFS('Rateio Folha'!$CF:$CF,'Rateio Folha'!$C:$C,MONTH('Breakdown Alocação de Despesas'!Q$6)) -> 208500 | R34: =SUMIFS('Rateio Folha'!$CF:$CF,'Rateio Folha'!$C:$C,MONTH('Breakdown Alocação de Despesas'!R$6)) -> 208500 | S34: =SUMIFS('Rateio Folha'!$CF:$CF,'Rateio Folha'!$C:$C,MONTH('Breakdown Alocação de Despesas'!S$6)) -> 231500 | T34: =SUMIFS('Rateio Folha'!$CF:$CF,'Rateio Folha'!$C:$C,MONTH('Breakdown Alocação de Despesas'!T$6)) -> 239500 | U34: =SUMIFS('Rateio Folha'!$CF:$CF,'Rateio Folha'!$C:$C,MONTH('Breakdown Alocação de Despesas'!U$6)) -> 239500 | V34: =SUMIFS('Rateio Folha'!$CF:$CF,'Rateio Folha'!$C:$C,MONTH('Breakdown Alocação de Despesas'!V$6)) -> 239500 | W34: =SUMIFS('Rateio Folha'!$CF:$CF,'Rateio Folha'!$C:$C,MONTH('Breakdown Alocação de Despesas'!W$6)) -> 239500 | X34: =SUMIFS('Rateio Folha'!$CF:$CF,'Rateio Folha'!$C:$C,MONTH('Breakdown Alocação de Despesas'!X$6)) -> 239500 | Y34: =SUM(I34:K34,P34:X34) -> 2590000 | AA34: =SUMIFS('Folha Forescast 3+9'!DL:DL,'Folha Forescast 3+9'!$I:$I,$C34) -> 178500 | AB34: =SUMIFS('Folha Forescast 3+9'!DM:DM,'Folha Forescast 3+9'!$I:$I,$C34) -> 163500 | AC34: =SUMIFS('Folha Forescast 3+9'!DN:DN,'Folha Forescast 3+9'!$I:$I,$C34) -> 175500 | AD34: =SUMIFS('Folha Forescast 3+9'!DO:DO,'Folha Forescast 3+9'!$I:$I,$C34) -> 195500 | AE34: =SUMIFS('Folha Forescast 3+9'!DP:DP,'Folha Forescast 3+9'!$I:$I,$C34) -> 195500 | AF34: =SUMIFS('Folha Forescast 3+9'!DQ:DQ,'Folha Forescast 3+9'!$I:$I,$C34) -> 226500 | AG34: =SUMIFS('Folha Forescast 3+9'!DR:DR,'Folha Forescast 3+9'!$I:$I,$C34) -> 249500 | AH34: =SUMIFS('Folha Forescast 3+9'!DS:DS,'Folha Forescast 3+9'!$I:$I,$C34) -> 249500 | AI34: =SUMIFS('Folha Forescast 3+9'!DT:DT,'Folha Forescast 3+9'!$I:$I,$C34) -> 249500 | AJ34: =SUMIFS('Folha Forescast 3+9'!DU:DU,'Folha Forescast 3+9'!$I:$I,$C34) -> 249500 | AK34: =SUMIFS('Folha Forescast 3+9'!DV:DV,'Folha Forescast 3+9'!$I:$I,$C34) -> 249500 | AL34: =SUMIFS('Folha Forescast 3+9'!DW:DW,'Folha Forescast 3+9'!$I:$I,$C34) -> 249500 | AM34: =SUM(AA34:AL34) -> 2632000
C35: % Alocada da Folha de Produtos | D35: =D34/D$31 -> 0.19424516 | E35: =E34/E$31 -> 0.19266422 | F35: =F34/F$31 -> 0.21398314 | G35: =G34/G$31 -> 0.20041633 | I35: =I34/I$31 -> 0.20475514 | J35: =J34/J$31 -> 0.19826548 | K35: =K34/K$31 -> 0.21105763 | L35: =L34/L$31 -> 0.20473115 | P35: =P34/P$31 -> 0.22596925 | Q35: =Q34/Q$31 -> 0.21744831 | R35: =R34/R$31 -> 0.21456524 | S35: =S34/S$31 -> 0.25294291 | T35: =T34/T$31 -> 0.23649266 | U35: =U34/U$31 -> 0.24221548 | V35: =V34/V$31 -> 0.23715526 | W35: =W34/W$31 -> 0.2356515 | ... Y35: =Y34/Y$31 -> 0.23288273 | AA35: =AA34/AA$31 -> 0.21366325 | AB35: =AB34/AB$31 -> 0.22315041 | AC35: =AC34/AC$31 -> 0.23152807 | AD35: =AD34/AD$31 -> 0.20396722 | AE35: =AE34/AE$31 -> 0.25390183 | AF35: =AF34/AF$31 -> 0.29438098 | AG35: =AG34/AG$31 -> 0.29170527 | AH35: =AH34/AH$31 -> 0.29298984 | ... AM35: =AM34/AM$31 -> 0.26372026
A37: =C37 -> Produtos Corporate | C37: Produtos Corporate | D37: =SUMIFS('Rateio Fopag'!$F:$F,'Rateio Fopag'!$H:$H,MONTH(D$6),'Rateio Fopag'!$J:$J,'Breakdown Alocação de Despesas'!$C37) -> 197234.75 | E37: =SUMIFS('Rateio Fopag'!$F:$F,'Rateio Fopag'!$H:$H,MONTH(E$6),'Rateio Fopag'!$J:$J,'Breakdown Alocação de Despesas'!$C37) -> 244442.67 | F37: =SUMIFS('Rateio Fopag'!$F:$F,'Rateio Fopag'!$H:$H,MONTH(F$6),'Rateio Fopag'!$J:$J,'Breakdown Alocação de Despesas'!$C37) -> 179786.5 | G37: =SUM(D37:F37) -> 621463.92 | I37: =SUMIFS('Rateio Folha'!$CG:$CG,'Rateio Folha'!$C:$C,MONTH('Breakdown Alocação de Despesas'!I$6)) -> 212291.95 | J37: =SUMIFS('Rateio Folha'!$CG:$CG,'Rateio Folha'!$C:$C,MONTH('Breakdown Alocação de Despesas'!J$6)) -> 240826.95 | K37: =SUMIFS('Rateio Folha'!$CG:$CG,'Rateio Folha'!$C:$C,MONTH('Breakdown Alocação de Despesas'!K$6)) -> 240826.95 | L37: =SUM(I37:K37) -> 693945.85 | N37: =G37/L37-1 -> -0.10444896 | P37: =SUMIFS('Rateio Folha'!$CG:$CG,'Rateio Folha'!$C:$C,MONTH('Breakdown Alocação de Despesas'!P$6)) -> 240826.95 | Q37: =SUMIFS('Rateio Folha'!$CG:$CG,'Rateio Folha'!$C:$C,MONTH('Breakdown Alocação de Despesas'!Q$6)) -> 276079.84 | R37: =SUMIFS('Rateio Folha'!$CG:$CG,'Rateio Folha'!$C:$C,MONTH('Breakdown Alocação de Despesas'!R$6)) -> 281109.06 | S37: =SUMIFS('Rateio Folha'!$CG:$CG,'Rateio Folha'!$C:$C,MONTH('Breakdown Alocação de Despesas'!S$6)) -> 250073.79 | T37: =SUMIFS('Rateio Folha'!$CG:$CG,'Rateio Folha'!$C:$C,MONTH('Breakdown Alocação de Despesas'!T$6)) -> 292262.77 | U37: =SUMIFS('Rateio Folha'!$CG:$CG,'Rateio Folha'!$C:$C,MONTH('Breakdown Alocação de Despesas'!U$6)) -> 282607.45 | V37: =SUMIFS('Rateio Folha'!$CG:$CG,'Rateio Folha'!$C:$C,MONTH('Breakdown Alocação de Despesas'!V$6)) -> 291121.01 | W37: =SUMIFS('Rateio Folha'!$CG:$CG,'Rateio Folha'!$C:$C,MONTH('Breakdown Alocação de Despesas'!W$6)) -> 293721.48 | X37: =SUMIFS('Rateio Folha'!$CG:$CG,'Rateio Folha'!$C:$C,MONTH('Breakdown Alocação de Despesas'!X$6)) -> 201841.99 | Y37: =SUM(I37:K37,P37:X37) -> 3103590.2 | AA37: =SUMIFS('Folha Forescast 3+9'!DL:DL,'Folha Forescast 3+9'!$I:$I,$C37) -> 169497.03 | AB37: =SUMIFS('Folha Forescast 3+9'!DM:DM,'Folha Forescast 3+9'!$I:$I,$C37) -> 147759.92 | AC37: =SUMIFS('Folha Forescast 3+9'!DN:DN,'Folha Forescast 3+9'!$I:$I,$C37) -> 159101.27 | AD37: =SUMIFS('Folha Forescast 3+9'!DO:DO,'Folha Forescast 3+9'!$I:$I,$C37) -> 164716.81 | AE37: =SUMIFS('Folha Forescast 3+9'!DP:DP,'Folha Forescast 3+9'!$I:$I,$C37) -> 173071.54 | AF37: =SUMIFS('Folha Forescast 3+9'!DQ:DQ,'Folha Forescast 3+9'!$I:$I,$C37) -> 202860.02 | AG37: =SUMIFS('Folha Forescast 3+9'!DR:DR,'Folha Forescast 3+9'!$I:$I,$C37) -> 202860.02 | AH37: =SUMIFS('Folha Forescast 3+9'!DS:DS,'Folha Forescast 3+9'!$I:$I,$C37) -> 202860.02 | AI37: =SUMIFS('Folha Forescast 3+9'!DT:DT,'Folha Forescast 3+9'!$I:$I,$C37) -> 202860.02 | AJ37: =SUMIFS('Folha Forescast 3+9'!DU:DU,'Folha Forescast 3+9'!$I:$I,$C37) -> 202860.02 | AK37: =SUMIFS('Folha Forescast 3+9'!DV:DV,'Folha Forescast 3+9'!$I:$I,$C37) -> 202860.02 | AL37: =SUMIFS('Folha Forescast 3+9'!DW:DW,'Folha Forescast 3+9'!$I:$I,$C37) -> 202860.02 | AM37: =SUM(AA37:AL37) -> 2234166.7
C38: % Alocada da Folha de Produtos | D38: =D37/D$31 -> 0.2183014 | E38: =E37/E$31 -> 0.29342902 | F38: =F37/F$31 -> 0.20269378 | G38: =G37/G$31 -> 0.23688003 | I38: =I37/I$31 -> 0.24351746 | J38: =J37/J$31 -> 0.26749396 | K38: =K37/K$31 -> 0.26267889 | L38: =L37/L$31 -> 0.25807872 | P38: =P37/P$31 -> 0.28123765 | Q38: =Q37/Q$31 -> 0.28792851 | R38: =R37/R$31 -> 0.28928649 | S38: =S37/S$31 -> 0.27323711 | T38: =T37/T$31 -> 0.28859291 | U38: =U37/U$31 -> 0.2858117 | V38: =V37/V$31 -> 0.28827089 | W38: =W37/W$31 -> 0.2890017 | ... Y38: =Y37/Y$31 -> 0.27906276 | AA38: =AA37/AA$31 -> 0.20288675 | AB38: =AB37/AB$31 -> 0.2016678 | AC38: =AC37/AC$31 -> 0.20989408 | AD38: =AD37/AD$31 -> 0.17185079 | AE38: =AE37/AE$31 -> 0.22477331 | AF38: =AF37/AF$31 -> 0.26365621 | AG38: =AG37/AG$31 -> 0.2371757 | AH38: =AH37/AH$31 -> 0.23822014 | ... AM38: =AM37/AM$31 -> 0.22385829
C39: Produtos Corporate s/ Amit | I39: =SUMIFS('Rateio Folha'!$CG:$CG,'Rateio Folha'!$C:$C,MONTH('Breakdown Alocação de Despesas'!I$6)) -> 212291.95 | J39: =SUMIFS('Rateio Folha'!$CG:$CG,'Rateio Folha'!$C:$C,MONTH('Breakdown Alocação de Despesas'!J$6)) -> 240826.95 | K39: =SUMIFS('Rateio Folha'!$CG:$CG,'Rateio Folha'!$C:$C,MONTH('Breakdown Alocação de Despesas'!K$6)) -> 240826.95 | L39: =SUM(I39:K39) -> 693945.85 | P39: =SUMIFS('Rateio Folha'!$CG:$CG,'Rateio Folha'!$C:$C,MONTH('Breakdown Alocação de Despesas'!P$6))+P41 -> 195826.95 | Q39: =SUMIFS('Rateio Folha'!$CG:$CG,'Rateio Folha'!$C:$C,MONTH('Breakdown Alocação de Despesas'!Q$6))+Q41 -> 231079.84 | R39: =SUMIFS('Rateio Folha'!$CG:$CG,'Rateio Folha'!$C:$C,MONTH('Breakdown Alocação de Despesas'!R$6))+R41 -> 236109.06 | S39: =SUMIFS('Rateio Folha'!$CG:$CG,'Rateio Folha'!$C:$C,MONTH('Breakdown Alocação de Despesas'!S$6))+S41 -> 205073.79 | T39: =SUMIFS('Rateio Folha'!$CG:$CG,'Rateio Folha'!$C:$C,MONTH('Breakdown Alocação de Despesas'!T$6))+T41 -> 247262.77 | U39: =SUMIFS('Rateio Folha'!$CG:$CG,'Rateio Folha'!$C:$C,MONTH('Breakdown Alocação de Despesas'!U$6))+U41 -> 237607.45 | V39: =SUMIFS('Rateio Folha'!$CG:$CG,'Rateio Folha'!$C:$C,MONTH('Breakdown Alocação de Despesas'!V$6))+V41 -> 246121.01 | W39: =SUMIFS('Rateio Folha'!$CG:$CG,'Rateio Folha'!$C:$C,MONTH('Breakdown Alocação de Despesas'!W$6))+W41 -> 248721.48 | X39: =SUMIFS('Rateio Folha'!$CG:$CG,'Rateio Folha'!$C:$C,MONTH('Breakdown Alocação de Despesas'!X$6))+X41 -> 201841.99 | Y39: =SUM(I39:K39,P39:X39) -> 2743590.2 | AA39: =SUMIFS('Rateio Folha'!$CG:$CG,'Rateio Folha'!$C:$C,MONTH('Breakdown Alocação de Despesas'!AA$6))+AA41 -> 167291.95 | AB39: =SUMIFS('Rateio Folha'!$CG:$CG,'Rateio Folha'!$C:$C,MONTH('Breakdown Alocação de Despesas'!AB$6))+AB41 -> 195826.95 | AC39: =SUMIFS('Rateio Folha'!$CG:$CG,'Rateio Folha'!$C:$C,MONTH('Breakdown Alocação de Despesas'!AC$6))+AC41 -> 195826.95 | AD39: =SUMIFS('Rateio Folha'!$CG:$CG,'Rateio Folha'!$C:$C,MONTH('Breakdown Alocação de Despesas'!AD$6))+AD41 -> 195826.95 | AE39: =SUMIFS('Rateio Folha'!$CG:$CG,'Rateio Folha'!$C:$C,MONTH('Breakdown Alocação de Despesas'!AE$6))+AE41 -> 231079.84 | AF39: =SUMIFS('Rateio Folha'!$CG:$CG,'Rateio Folha'!$C:$C,MONTH('Breakdown Alocação de Despesas'!AF$6))+AF41 -> 236109.06 | AG39: =SUMIFS('Rateio Folha'!$CG:$CG,'Rateio Folha'!$C:$C,MONTH('Breakdown Alocação de Despesas'!AG$6))+AG41 -> 205073.79 | AH39: =SUMIFS('Rateio Folha'!$CG:$CG,'Rateio Folha'!$C:$C,MONTH('Breakdown Alocação de Despesas'!AH$6))+AH41 -> 247262.77 | ... AL39: =SUMIFS('Rateio Folha'!$CG:$CG,'Rateio Folha'!$C:$C,MONTH('Breakdown Alocação de Despesas'!AL$6))+AL41 -> 201841.99 | AM39: =SUM(T39:V39,AD39:AL39) -> 2780635.6
C40: % Alocada da Folha de Produtos | D40: =D37/D$31 -> 0.2183014 | E40: =E37/E$31 -> 0.29342902 | F40: =F37/F$31 -> 0.20269378 | G40: =G37/G$31 -> 0.23688003 | I40: =I37/I$31 -> 0.24351746 | J40: =J37/J$31 -> 0.26749396 | K40: =K37/K$31 -> 0.26267889 | L40: =L37/L$31 -> 0.25807872 | P40: =P39/P$31 -> 0.22868666 | Q40: =Q39/Q$31 -> 0.24099722 | R40: =R39/R$31 -> 0.24297744 | S40: =S39/S$31 -> 0.22406894 | T40: =T39/T$31 -> 0.24415796 | U40: =U39/U$31 -> 0.24030148 | V40: =V39/V$31 -> 0.24371145 | W40: =W39/W$31 -> 0.2447248 | ... Y40: =Y39/Y$31 -> 0.24669296 | AA40: =AA39/AA$31 -> 0.20024729 | AB40: =AB39/AB$31 -> 0.26727134 | AC40: =AC39/AC$31 -> 0.25834437 | AD40: =AD39/AD$31 -> 0.20430833 | AE40: =AE39/AE$31 -> 0.30011046 | AF40: =AF39/AF$31 -> 0.30686984 | AG40: =AG39/AG$31 -> 0.23976394 | AH40: =AH39/AH$31 -> 0.29036264 | ... AM40: =AM39/AM$31 -> 0.2786132
C41: Amit | P41: =-SUMIFS('Rateio Folha'!$CH:$CH,'Rateio Folha'!$C:$C,MONTH('Breakdown Alocação de Despesas'!P$6)) -> -45000 | Q41: =-SUMIFS('Rateio Folha'!$CH:$CH,'Rateio Folha'!$C:$C,MONTH('Breakdown Alocação de Despesas'!Q$6)) -> -45000 | R41: =-SUMIFS('Rateio Folha'!$CH:$CH,'Rateio Folha'!$C:$C,MONTH('Breakdown Alocação de Despesas'!R$6)) -> -45000 | S41: =-SUMIFS('Rateio Folha'!$CH:$CH,'Rateio Folha'!$C:$C,MONTH('Breakdown Alocação de Despesas'!S$6)) -> -45000 | T41: =-SUMIFS('Rateio Folha'!$CH:$CH,'Rateio Folha'!$C:$C,MONTH('Breakdown Alocação de Despesas'!T$6)) -> -45000 | U41: =-SUMIFS('Rateio Folha'!$CH:$CH,'Rateio Folha'!$C:$C,MONTH('Breakdown Alocação de Despesas'!U$6)) -> -45000 | V41: =-SUMIFS('Rateio Folha'!$CH:$CH,'Rateio Folha'!$C:$C,MONTH('Breakdown Alocação de Despesas'!V$6)) -> -45000 | W41: =-SUMIFS('Rateio Folha'!$CH:$CH,'Rateio Folha'!$C:$C,MONTH('Breakdown Alocação de Despesas'!W$6)) -> -45000 | X41: =-SUMIFS('Rateio Folha'!$CH:$CH,'Rateio Folha'!$C:$C,MONTH('Breakdown Alocação de Despesas'!X$6)) -> 0 | Y41: =SUM(P41:X41) -> -360000 | AA41: =-SUMIFS('Rateio Folha'!$CH:$CH,'Rateio Folha'!$C:$C,MONTH('Breakdown Alocação de Despesas'!AA$6)) -> -45000 | AB41: =-SUMIFS('Rateio Folha'!$CH:$CH,'Rateio Folha'!$C:$C,MONTH('Breakdown Alocação de Despesas'!AB$6)) -> -45000 | AC41: =-SUMIFS('Rateio Folha'!$CH:$CH,'Rateio Folha'!$C:$C,MONTH('Breakdown Alocação de Despesas'!AC$6)) -> -45000 | AD41: =-SUMIFS('Rateio Folha'!$CH:$CH,'Rateio Folha'!$C:$C,MONTH('Breakdown Alocação de Despesas'!AD$6)) -> -45000 | AE41: =-SUMIFS('Rateio Folha'!$CH:$CH,'Rateio Folha'!$C:$C,MONTH('Breakdown Alocação de Despesas'!AE$6)) -> -45000 | AF41: =-SUMIFS('Rateio Folha'!$CH:$CH,'Rateio Folha'!$C:$C,MONTH('Breakdown Alocação de Despesas'!AF$6)) -> -45000 | AG41: =-SUMIFS('Rateio Folha'!$CH:$CH,'Rateio Folha'!$C:$C,MONTH('Breakdown Alocação de Despesas'!AG$6)) -> -45000 | AH41: =-SUMIFS('Rateio Folha'!$CH:$CH,'Rateio Folha'!$C:$C,MONTH('Breakdown Alocação de Despesas'!AH$6)) -> -45000 | ... AL41: =-SUMIFS('Rateio Folha'!$CH:$CH,'Rateio Folha'!$C:$C,MONTH('Breakdown Alocação de Despesas'!AL$6)) -> 0 | AM41: =SUM(AD41:AL41) -> -360000
P42: =P41/P37 -> -0.18685616 | Q42: =Q41/Q37 -> -0.16299633 | R42: =R41/R37 -> -0.16008022 | S42: =S41/S37 -> -0.17994689 | T42: =T41/T37 -> -0.15397103 | U42: =U41/U37 -> -0.15923147 | V42: =V41/V37 -> -0.1545749 | W42: =W41/W37 -> -0.15320636 | X42: =X41/X37 -> 0 | Y42: =Y41/Y31 -> -0.0323698 | AA42: =AA41/AA37 -> -0.26549138 | AB42: =AB41/AB37 -> -0.30454809 | AC42: =AC41/AC37 -> -0.28283873 | AD42: =AD41/AD37 -> -0.27319616 | AE42: =AE41/AE37 -> -0.26000808 | AF42: =AF41/AF37 -> -0.22182784 | AG42: =AG41/AG37 -> -0.22182784 | AH42: =AH41/AH37 -> -0.22182784 | ... AL42: =AL41/AL37 -> 0 | AM42: =AM41/AM31 -> -0.03607116
A44: Tech Academy | C44: Tech Academy | D44: =SUMIFS('Rateio Fopag'!$F:$F,'Rateio Fopag'!$H:$H,MONTH(D$6),'Rateio Fopag'!$J:$J,'Breakdown Alocação de Despesas'!$C44) -> 122660.74 | E44: =SUMIFS('Rateio Fopag'!$F:$F,'Rateio Fopag'!$H:$H,MONTH(E$6),'Rateio Fopag'!$J:$J,'Breakdown Alocação de Despesas'!$C44) -> 121893.01 | F44: =SUMIFS('Rateio Fopag'!$F:$F,'Rateio Fopag'!$H:$H,MONTH(F$6),'Rateio Fopag'!$J:$J,'Breakdown Alocação de Despesas'!$C44) -> 166899.7 | G44: =SUM(D44:F44) -> 411453.44 | I44: =SUMIFS('Rateio Folha'!$CI:$CI,'Rateio Folha'!$C:$C,MONTH('Breakdown Alocação de Despesas'!I$6)) -> 120609.24 | J44: =SUMIFS('Rateio Folha'!$CI:$CI,'Rateio Folha'!$C:$C,MONTH('Breakdown Alocação de Despesas'!J$6)) -> 120609.24 | K44: =SUMIFS('Rateio Folha'!$CI:$CI,'Rateio Folha'!$C:$C,MONTH('Breakdown Alocação de Despesas'!K$6)) -> 120609.24 | L44: =SUM(I44:K44) -> 361827.73 | N44: =G44/L44-1 -> 0.13715289 | P44: =SUMIFS('Rateio Folha'!$CI:$CI,'Rateio Folha'!$C:$C,MONTH('Breakdown Alocação de Despesas'!P$6)) -> 120609.24 | Q44: =SUMIFS('Rateio Folha'!$CI:$CI,'Rateio Folha'!$C:$C,MONTH('Breakdown Alocação de Despesas'!Q$6)) -> 143894.88 | R44: =SUMIFS('Rateio Folha'!$CI:$CI,'Rateio Folha'!$C:$C,MONTH('Breakdown Alocação de Despesas'!R$6)) -> 147406.53 | S44: =SUMIFS('Rateio Folha'!$CI:$CI,'Rateio Folha'!$C:$C,MONTH('Breakdown Alocação de Despesas'!S$6)) -> 125736.2 | T44: =SUMIFS('Rateio Folha'!$CI:$CI,'Rateio Folha'!$C:$C,MONTH('Breakdown Alocação de Despesas'!T$6)) -> 145511.37 | U44: =SUMIFS('Rateio Folha'!$CI:$CI,'Rateio Folha'!$C:$C,MONTH('Breakdown Alocação de Despesas'!U$6)) -> 139190.21 | V44: =SUMIFS('Rateio Folha'!$CI:$CI,'Rateio Folha'!$C:$C,MONTH('Breakdown Alocação de Despesas'!V$6)) -> 144763.87 | W44: =SUMIFS('Rateio Folha'!$CI:$CI,'Rateio Folha'!$C:$C,MONTH('Breakdown Alocação de Despesas'!W$6)) -> 146466.36 | X44: =SUMIFS('Rateio Folha'!$CI:$CI,'Rateio Folha'!$C:$C,MONTH('Breakdown Alocação de Despesas'!X$6)) -> 115775.21 | Y44: =SUM(I44:K44,P44:X44) -> 1591181.6 | AA44: =SUMIFS('Folha Forescast 3+9'!DL:DL,'Folha Forescast 3+9'!$I:$I,$C44) -> 115064.61 | AB44: =SUMIFS('Folha Forescast 3+9'!DM:DM,'Folha Forescast 3+9'!$I:$I,$C44) -> 115064.61 | AC44: =SUMIFS('Folha Forescast 3+9'!DN:DN,'Folha Forescast 3+9'!$I:$I,$C44) -> 115064.61 | AD44: =SUMIFS('Folha Forescast 3+9'!DO:DO,'Folha Forescast 3+9'!$I:$I,$C44) -> 128608.5 | AE44: =SUMIFS('Folha Forescast 3+9'!DP:DP,'Folha Forescast 3+9'!$I:$I,$C44) -> 133080.55 | AF44: =SUMIFS('Folha Forescast 3+9'!DQ:DQ,'Folha Forescast 3+9'!$I:$I,$C44) -> 133080.55 | AG44: =SUMIFS('Folha Forescast 3+9'!DR:DR,'Folha Forescast 3+9'!$I:$I,$C44) -> 133080.55 | AH44: =SUMIFS('Folha Forescast 3+9'!DS:DS,'Folha Forescast 3+9'!$I:$I,$C44) -> 133080.55 | AI44: =SUMIFS('Folha Forescast 3+9'!DT:DT,'Folha Forescast 3+9'!$I:$I,$C44) -> 133080.55 | AJ44: =SUMIFS('Folha Forescast 3+9'!DU:DU,'Folha Forescast 3+9'!$I:$I,$C44) -> 133080.55 | AK44: =SUMIFS('Folha Forescast 3+9'!DV:DV,'Folha Forescast 3+9'!$I:$I,$C44) -> 133080.55 | AL44: =SUMIFS('Folha Forescast 3+9'!DW:DW,'Folha Forescast 3+9'!$I:$I,$C44) -> 133080.55 | AM44: =SUM(AA44:AL44) -> 1538446.7
C45: % Alocada da Folha de Produtos | D45: =D44/D$31 -> 0.13576214 | E45: =E44/E$31 -> 0.14632038 | F45: =F44/F$31 -> 0.18816502 | G45: =G44/G$31 -> 0.15683147 | I45: =I44/I$31 -> 0.13834937 | J45: =J44/J$31 -> 0.13396442 | K45: =K44/K$31 -> 0.13155298 | L45: =L44/L$31 -> 0.13456386 | P45: =P44/P$31 -> 0.14084744 | Q45: =Q44/Q$31 -> 0.15007049 | R45: =R44/R$31 -> 0.15169456 | S45: =S44/S$31 -> 0.13738264 | T45: =T44/T$31 -> 0.14368422 | U45: =U44/U$31 -> 0.14076836 | V45: =V44/V$31 -> 0.14334662 | W45: =W44/W$31 -> 0.1441128 | ... Y45: =Y44/Y$31 -> 0.14307286 | AA45: =AA44/AA$31 -> 0.13773153 | AB45: =AB44/AB$31 -> 0.15704412 | AC45: =AC44/AC$31 -> 0.15179879 | AD45: =AD44/AD$31 -> 0.13417861 | AE45: =AE44/AE$31 -> 0.17283578 | AF45: =AF44/AF$31 -> 0.17296416 | AG45: =AG44/AG$31 -> 0.15559237 | AH45: =AH44/AH$31 -> 0.15627754 | ... AM45: =AM44/AM$31 -> 0.15414877
A47: =C47 -> Produtos Offline/Eventos | C47: Produtos Offline/Eventos | D47: =SUMIFS('Rateio Fopag'!$F:$F,'Rateio Fopag'!$H:$H,MONTH(D$6),'Rateio Fopag'!$J:$J,'Breakdown Alocação de Despesas'!$C47) -> 78055.314 | E47: =SUMIFS('Rateio Fopag'!$F:$F,'Rateio Fopag'!$H:$H,MONTH(E$6),'Rateio Fopag'!$J:$J,'Breakdown Alocação de Despesas'!$C47) -> 77566.762 | F47: =SUMIFS('Rateio Fopag'!$F:$F,'Rateio Fopag'!$H:$H,MONTH(F$6),'Rateio Fopag'!$J:$J,'Breakdown Alocação de Despesas'!$C47) -> 109303.46 | G47: =SUM(D47:F47) -> 264925.54 | I47: =SUMIFS('Rateio Folha'!$CJ:$CJ,'Rateio Folha'!$C:$C,MONTH('Breakdown Alocação de Despesas'!I$6)) -> 99525.514 | J47: =SUMIFS('Rateio Folha'!$CJ:$CJ,'Rateio Folha'!$C:$C,MONTH('Breakdown Alocação de Despesas'!J$6)) -> 99525.514 | K47: =SUMIFS('Rateio Folha'!$CJ:$CJ,'Rateio Folha'!$C:$C,MONTH('Breakdown Alocação de Despesas'!K$6)) -> 99525.514 | L47: =SUM(I47:K47) -> 298576.54 | N47: =G47/L47-1 -> -0.11270478 | P47: =SUMIFS('Rateio Folha'!$CJ:$CJ,'Rateio Folha'!$C:$C,MONTH('Breakdown Alocação de Despesas'!P$6)) -> 99525.514 | Q47: =SUMIFS('Rateio Folha'!$CJ:$CJ,'Rateio Folha'!$C:$C,MONTH('Breakdown Alocação de Despesas'!Q$6)) -> 118842.01 | R47: =SUMIFS('Rateio Folha'!$CJ:$CJ,'Rateio Folha'!$C:$C,MONTH('Breakdown Alocação de Despesas'!R$6)) -> 121742.26 | S47: =SUMIFS('Rateio Folha'!$CJ:$CJ,'Rateio Folha'!$C:$C,MONTH('Breakdown Alocação de Despesas'!S$6)) -> 103844.86 | T47: =SUMIFS('Rateio Folha'!$CJ:$CJ,'Rateio Folha'!$C:$C,MONTH('Breakdown Alocação de Despesas'!T$6)) -> 123246.3 | U47: =SUMIFS('Rateio Folha'!$CJ:$CJ,'Rateio Folha'!$C:$C,MONTH('Breakdown Alocação de Despesas'!U$6)) -> 117892.36 | V47: =SUMIFS('Rateio Folha'!$CJ:$CJ,'Rateio Folha'!$C:$C,MONTH('Breakdown Alocação de Despesas'!V$6)) -> 122613.19 | W47: =SUMIFS('Rateio Folha'!$CJ:$CJ,'Rateio Folha'!$C:$C,MONTH('Breakdown Alocação de Despesas'!W$6)) -> 124055.17 | X47: =SUMIFS('Rateio Folha'!$CJ:$CJ,'Rateio Folha'!$C:$C,MONTH('Breakdown Alocação de Despesas'!X$6)) -> 98060.155 | Y47: =SUM(I47:K47,P47:X47) -> 1328398.4 | AA47: =SUMIFS('Folha Forescast 3+9'!DL:DL,'Folha Forescast 3+9'!$I:$I,$C47) -> 74197.574 | AB47: =SUMIFS('Folha Forescast 3+9'!DM:DM,'Folha Forescast 3+9'!$I:$I,$C47) -> 74197.574 | AC47: =SUMIFS('Folha Forescast 3+9'!DN:DN,'Folha Forescast 3+9'!$I:$I,$C47) -> 76173.979 | AD47: =SUMIFS('Folha Forescast 3+9'!DO:DO,'Folha Forescast 3+9'!$I:$I,$C47) -> 80354.192 | AE47: =SUMIFS('Folha Forescast 3+9'!DP:DP,'Folha Forescast 3+9'!$I:$I,$C47) -> 97797.601 | AF47: =SUMIFS('Folha Forescast 3+9'!DQ:DQ,'Folha Forescast 3+9'!$I:$I,$C47) -> 97797.601 | AG47: =SUMIFS('Folha Forescast 3+9'!DR:DR,'Folha Forescast 3+9'!$I:$I,$C47) -> 98826.866 | AH47: =SUMIFS('Folha Forescast 3+9'!DS:DS,'Folha Forescast 3+9'!$I:$I,$C47) -> 98826.866 | AI47: =SUMIFS('Folha Forescast 3+9'!DT:DT,'Folha Forescast 3+9'!$I:$I,$C47) -> 98826.866 | AJ47: =SUMIFS('Folha Forescast 3+9'!DU:DU,'Folha Forescast 3+9'!$I:$I,$C47) -> 98826.866 | AK47: =SUMIFS('Folha Forescast 3+9'!DV:DV,'Folha Forescast 3+9'!$I:$I,$C47) -> 98826.866 | AL47: =SUMIFS('Folha Forescast 3+9'!DW:DW,'Folha Forescast 3+9'!$I:$I,$C47) -> 98826.866 | AM47: =SUM(AA47:AL47) -> 1093479.7
C48: % Alocada da Folha de Produtos | D48: =D47/D$31 -> 0.086392405 | E48: =E47/E$31 -> 0.093111151 | F48: =F47/F$31 -> 0.12323023 | G48: =G47/G$31 -> 0.10098023 | I48: =I47/I$31 -> 0.11416448 | J48: =J47/J$31 -> 0.11054607 | K48: =K47/K$31 -> 0.10855617 | L48: =L47/L$31 -> 0.11104073 | P48: =P47/P$31 -> 0.11622587 | Q48: =Q47/Q$31 -> 0.12394242 | R48: =R47/R$31 -> 0.12528373 | S48: =S47/S$31 -> 0.11346359 | T48: =T47/T$31 -> 0.12169873 | U48: =U47/U$31 -> 0.11922904 | V48: =V47/V$31 -> 0.12141279 | W48: =W47/W$31 -> 0.12206174 | ... Y48: =Y47/Y$31 -> 0.11944442 | AA48: =AA47/AA$31 -> 0.088813976 | AB48: =AB47/AB$31 -> 0.10126739 | AC48: =AC47/AC$31 -> 0.10049239 | AD48: =AD47/AD$31 -> 0.083834378 | AE48: =AE47/AE$31 -> 0.12701274 | AF48: =AF47/AF$31 -> 0.12710708 | AG48: =AG47/AG$31 -> 0.11554436 | AH48: =AH47/AH$31 -> 0.11605318 | ... AM48: =AM47/AM$31 -> 0.10956412
A50: Produtos Inter | C50: Produtos Inter | D50: =SUMIFS('Rateio Fopag'!$F:$F,'Rateio Fopag'!$H:$H,MONTH(D$6),'Rateio Fopag'!$J:$J,'Breakdown Alocação de Despesas'!$C50) -> 330046.6 | E50: =SUMIFS('Rateio Fopag'!$F:$F,'Rateio Fopag'!$H:$H,MONTH(E$6),'Rateio Fopag'!$J:$J,'Breakdown Alocação de Despesas'!$C50) -> 228653.12 | F50: =SUMIFS('Rateio Fopag'!$F:$F,'Rateio Fopag'!$H:$H,MONTH(F$6),'Rateio Fopag'!$J:$J,'Breakdown Alocação de Despesas'!$C50) -> 241196.11 | G50: =SUM(D50:F50) -> 799895.83 | I50: =SUMIFS('Rateio Folha'!$CK:$CK,'Rateio Folha'!$C:$C,MONTH('Breakdown Alocação de Despesas'!I$6)) -> 260846.3 | J50: =SUMIFS('Rateio Folha'!$CK:$CK,'Rateio Folha'!$C:$C,MONTH('Breakdown Alocação de Despesas'!J$6)) -> 260846.3 | K50: =SUMIFS('Rateio Folha'!$CK:$CK,'Rateio Folha'!$C:$C,MONTH('Breakdown Alocação de Despesas'!K$6)) -> 262349.5 | L50: =SUM(I50:K50) -> 784042.09 | N50: =G50/L50-1 -> 0.020220522 | P50: =SUMIFS('Rateio Folha'!$CK:$CK,'Rateio Folha'!$C:$C,MONTH('Breakdown Alocação de Despesas'!P$6)) -> 201849.5 | Q50: =SUMIFS('Rateio Folha'!$CK:$CK,'Rateio Folha'!$C:$C,MONTH('Breakdown Alocação de Despesas'!Q$6)) -> 211531.84 | R50: =SUMIFS('Rateio Folha'!$CK:$CK,'Rateio Folha'!$C:$C,MONTH('Breakdown Alocação de Despesas'!R$6)) -> 212974.58 | S50: =SUMIFS('Rateio Folha'!$CK:$CK,'Rateio Folha'!$C:$C,MONTH('Breakdown Alocação de Despesas'!S$6)) -> 204071.45 | T50: =SUMIFS('Rateio Folha'!$CK:$CK,'Rateio Folha'!$C:$C,MONTH('Breakdown Alocação de Despesas'!T$6)) -> 212195.97 | U50: =SUMIFS('Rateio Folha'!$CK:$CK,'Rateio Folha'!$C:$C,MONTH('Breakdown Alocação de Despesas'!U$6)) -> 209598.95 | V50: =SUMIFS('Rateio Folha'!$CK:$CK,'Rateio Folha'!$C:$C,MONTH('Breakdown Alocação de Despesas'!V$6)) -> 211888.86 | W50: =SUMIFS('Rateio Folha'!$CK:$CK,'Rateio Folha'!$C:$C,MONTH('Breakdown Alocação de Despesas'!W$6)) -> 212588.32 | X50: =SUMIFS('Rateio Folha'!$CK:$CK,'Rateio Folha'!$C:$C,MONTH('Breakdown Alocação de Despesas'!X$6)) -> 47565.6 | Y50: =SUM(I50:K50,P50:X50) -> 2508307.2 | AA50: =SUMIFS('Folha Forescast 3+9'!DL:DL,'Folha Forescast 3+9'!$I:$I,$C50) -> 298167.57 | AB50: =SUMIFS('Folha Forescast 3+9'!DM:DM,'Folha Forescast 3+9'!$I:$I,$C50) -> 232167.57 | AC50: =SUMIFS('Folha Forescast 3+9'!DN:DN,'Folha Forescast 3+9'!$I:$I,$C50) -> 232167.57 | AD50: =SUMIFS('Folha Forescast 3+9'!DO:DO,'Folha Forescast 3+9'!$I:$I,$C50) -> 389307.86 | AE50: =SUMIFS('Folha Forescast 3+9'!DP:DP,'Folha Forescast 3+9'!$I:$I,$C50) -> 170532.94 | AF50: =SUMIFS('Folha Forescast 3+9'!DQ:DQ,'Folha Forescast 3+9'!$I:$I,$C50) -> 109172.94 | AG50: =SUMIFS('Folha Forescast 3+9'!DR:DR,'Folha Forescast 3+9'!$I:$I,$C50) -> 171047.94 | AH50: =SUMIFS('Folha Forescast 3+9'!DS:DS,'Folha Forescast 3+9'!$I:$I,$C50) -> 167297.94 | AI50: =SUMIFS('Folha Forescast 3+9'!DT:DT,'Folha Forescast 3+9'!$I:$I,$C50) -> 202922.94 | AJ50: =SUMIFS('Folha Forescast 3+9'!DU:DU,'Folha Forescast 3+9'!$I:$I,$C50) -> 171047.94 | AK50: =SUMIFS('Folha Forescast 3+9'!DV:DV,'Folha Forescast 3+9'!$I:$I,$C50) -> 167297.94 | AL50: =SUMIFS('Folha Forescast 3+9'!DW:DW,'Folha Forescast 3+9'!$I:$I,$C50) -> 171047.94 | AM50: =SUM(AA50:AL50) -> 2482179.1
C51: % Alocada da Folha de Produtos | D51: =D50/D$31 -> 0.36529889 | E51: =E50/E$31 -> 0.27447524 | F51: =F50/F$31 -> 0.27192782 | G51: =G50/G$31 -> 0.30489195 | I51: =I50/I$31 -> 0.29921355 | J51: =J50/J$31 -> 0.28973006 | K51: =K50/K$31 -> 0.28615433 | L51: =L50/L$31 -> 0.29158554 | P51: =P50/P$31 -> 0.23571979 | Q51: =Q50/Q$31 -> 0.22061027 | R51: =R50/R$31 -> 0.21916998 | S51: =S50/S$31 -> 0.22297376 | T51: =T50/T$31 -> 0.20953148 | U51: =U50/U$31 -> 0.21197541 | V51: =V50/V$31 -> 0.20981444 | W51: =W50/W$31 -> 0.20917226 | ... Y51: =Y50/Y$31 -> 0.22553723 | AA51: =AA50/AA$31 -> 0.35690449 | AB51: =AB50/AB$31 -> 0.31687027 | AC51: =AC50/AC$31 -> 0.30628667 | AD51: =AD50/AD$31 -> 0.40616901 | AE51: =AE50/AE$31 -> 0.22147635 | AF51: =AF50/AF$31 -> 0.14189156 | AG51: =AG50/AG$31 -> 0.19998231 | AH51: =AH50/AH$31 -> 0.19645931 | ... AM51: =AM50/AM$31 -> 0.24870856
A53: Backoffice | C53: Backoffice | D53: =SUMIFS('Rateio Fopag'!$F:$F,'Rateio Fopag'!$H:$H,MONTH(D$6),'Rateio Fopag'!$K:$K,'Breakdown Alocação de Despesas'!$C53) -> 1707682 | E53: =SUMIFS('Rateio Fopag'!$F:$F,'Rateio Fopag'!$H:$H,MONTH(E$6),'Rateio Fopag'!$K:$K,'Breakdown Alocação de Despesas'!$C53) -> 1586255.6 | F53: =SUMIFS('Rateio Fopag'!$F:$F,'Rateio Fopag'!$H:$H,MONTH(F$6),'Rateio Fopag'!$K:$K,'Breakdown Alocação de Despesas'!$C53) -> 1794305 | G53: =SUM(D53:F53) -> 5088242.6 | I53: =SUMIFS('Rateio Folha'!$CL:$CL,'Rateio Folha'!$C:$C,MONTH('Breakdown Alocação de Despesas'!I$6)) -> 1673606.1 | J53: =SUMIFS('Rateio Folha'!$CL:$CL,'Rateio Folha'!$C:$C,MONTH('Breakdown Alocação de Despesas'!J$6)) -> 1694622.3 | K53: =SUMIFS('Rateio Folha'!$CL:$CL,'Rateio Folha'!$C:$C,MONTH('Breakdown Alocação de Despesas'!K$6)) -> 1751586.5 | L53: =SUM(I53:K53) -> 5119814.9 | N53: =G53/L53-1 -> -0.0061666986 | P53: =SUMIFS('Rateio Folha'!$CL:$CL,'Rateio Folha'!$C:$C,MONTH('Breakdown Alocação de Despesas'!P$6)) -> 1732792.3 | Q53: =SUMIFS('Rateio Folha'!$CL:$CL,'Rateio Folha'!$C:$C,MONTH('Breakdown Alocação de Despesas'!Q$6)) -> 1960504.3 | R53: =SUMIFS('Rateio Folha'!$CL:$CL,'Rateio Folha'!$C:$C,MONTH('Breakdown Alocação de Despesas'!R$6)) -> 2044544 | S53: =SUMIFS('Rateio Folha'!$CL:$CL,'Rateio Folha'!$C:$C,MONTH('Breakdown Alocação de Despesas'!S$6)) -> 1864400.1 | T53: =SUMIFS('Rateio Folha'!$CL:$CL,'Rateio Folha'!$C:$C,MONTH('Breakdown Alocação de Despesas'!T$6)) -> 2070256.6 | U53: =SUMIFS('Rateio Folha'!$CL:$CL,'Rateio Folha'!$C:$C,MONTH('Breakdown Alocação de Despesas'!U$6)) -> 2091648.3 | V53: =SUMIFS('Rateio Folha'!$CL:$CL,'Rateio Folha'!$C:$C,MONTH('Breakdown Alocação de Despesas'!V$6)) -> 2088195.2 | W53: =SUMIFS('Rateio Folha'!$CL:$CL,'Rateio Folha'!$C:$C,MONTH('Breakdown Alocação de Despesas'!W$6)) -> 2110909.2 | X53: =SUMIFS('Rateio Folha'!$CL:$CL,'Rateio Folha'!$C:$C,MONTH('Breakdown Alocação de Despesas'!X$6)) -> 1811996.9 | Y53: =SUM(I53:K53,P53:X53) -> 22895062 | AA53: =SUMIFS('Folha Forescast 3+9'!DL:DL,'Folha Forescast 3+9'!$H:$H,'Breakdown Alocação de Despesas'!$C53) -> 1924788 | AB53: =SUMIFS('Folha Forescast 3+9'!DM:DM,'Folha Forescast 3+9'!$H:$H,'Breakdown Alocação de Despesas'!$C53) -> 1558221.2 | AC53: =SUMIFS('Folha Forescast 3+9'!DN:DN,'Folha Forescast 3+9'!$H:$H,'Breakdown Alocação de Despesas'!$C53) -> 1563792.9 | AD53: =SUMIFS('Folha Forescast 3+9'!DO:DO,'Folha Forescast 3+9'!$H:$H,'Breakdown Alocação de Despesas'!$C53) -> 1579082.2 | AE53: =SUMIFS('Folha Forescast 3+9'!DP:DP,'Folha Forescast 3+9'!$H:$H,'Breakdown Alocação de Despesas'!$C53) -> 1621257.5 | AF53: =SUMIFS('Folha Forescast 3+9'!DQ:DQ,'Folha Forescast 3+9'!$H:$H,'Breakdown Alocação de Despesas'!$C53) -> 1651537.7 | AG53: =SUMIFS('Folha Forescast 3+9'!DR:DR,'Folha Forescast 3+9'!$H:$H,'Breakdown Alocação de Despesas'!$C53) -> 1547180.9 | AH53: =SUMIFS('Folha Forescast 3+9'!DS:DS,'Folha Forescast 3+9'!$H:$H,'Breakdown Alocação de Despesas'!$C53) -> 1523965.7 | AI53: =SUMIFS('Folha Forescast 3+9'!DT:DT,'Folha Forescast 3+9'!$H:$H,'Breakdown Alocação de Despesas'!$C53) -> 1496629.2 | AJ53: =SUMIFS('Folha Forescast 3+9'!DU:DU,'Folha Forescast 3+9'!$H:$H,'Breakdown Alocação de Despesas'!$C53) -> 1506792.8 | AK53: =SUMIFS('Folha Forescast 3+9'!DV:DV,'Folha Forescast 3+9'!$H:$H,'Breakdown Alocação de Despesas'!$C53) -> 1516956.3 | AL53: =SUMIFS('Folha Forescast 3+9'!DW:DW,'Folha Forescast 3+9'!$H:$H,'Breakdown Alocação de Despesas'!$C53) -> 1527119.8 | AM53: =SUM(AA53:AL53) -> 19017324
C54: % Alocada da Folha Total | D54: =D53/D$10 -> 0.47431491 | E54: =E53/E$10 -> 0.46407576 | F54: =F53/F$10 -> 0.46296232 | G54: =G53/G$10 -> 0.4670635 | I54: =I53/I$10 -> 0.48110609 | J54: =J53/J$10 -> 0.47845638 | K54: =K53/K$10 -> 0.47170995 | L54: =L53/L$10 -> 0.47698124 | P54: =P53/P$10 -> 0.47203841 | Q54: =Q53/Q$10 -> 0.46152667 | R54: =R53/R$10 -> 0.46686584 | S54: =S53/S$10 -> 0.46833997 | T54: =T53/T$10 -> 0.45838716 | U54: =U53/U$10 -> 0.46955634 | V54: =V53/V$10 -> 0.46153209 | W54: =W53/W$10 -> 0.46194363 | ... Y54: =Y53/Y$10 -> 0.46967369 | AA54: =AA53/AA$10 -> 0.47029222 | AB54: =AB53/AB$10 -> 0.42951438 | AC54: =AC53/AC$10 -> 0.42990094 | AD54: =AD53/AD$10 -> 0.40961649 | AE54: =AE53/AE$10 -> 0.42519077 | AF54: =AF53/AF$10 -> 0.42297836 | AG54: =AG53/AG$10 -> 0.39215975 | AH54: =AH53/AH$10 -> 0.38680899 | ... AM54: =AM53/AM$10 -> 0.40797663
A56: Consulting | C56: Contabilidade | D56: =SUMIFS('Rateio Fopag'!$F:$F,'Rateio Fopag'!$H:$H,MONTH(D$6),'Rateio Fopag'!$J:$J,'Breakdown Alocação de Despesas'!$C56) -> 77843.64 | E56: =SUMIFS('Rateio Fopag'!$F:$F,'Rateio Fopag'!$H:$H,MONTH(E$6),'Rateio Fopag'!$J:$J,'Breakdown Alocação de Despesas'!$C56) -> 77356.413 | F56: =SUMIFS('Rateio Fopag'!$F:$F,'Rateio Fopag'!$H:$H,MONTH(F$6),'Rateio Fopag'!$J:$J,'Breakdown Alocação de Despesas'!$C56) -> 105918.81 | G56: =SUM(D56:F56) -> 261118.86 | I56: =SUMIFS('Rateio Folha'!$CN:$CN,'Rateio Folha'!$C:$C,MONTH('Breakdown Alocação de Despesas'!I$6)) -> 62104.116 | J56: =SUMIFS('Rateio Folha'!$CN:$CN,'Rateio Folha'!$C:$C,MONTH('Breakdown Alocação de Despesas'!J$6)) -> 62104.116 | K56: =SUMIFS('Rateio Folha'!$CN:$CN,'Rateio Folha'!$C:$C,MONTH('Breakdown Alocação de Despesas'!K$6)) -> 62104.116 | L56: =SUM(I56:K56) -> 186312.35 | N56: =G56/L56-1 -> 0.40151129 | P56: =SUMIFS('Rateio Folha'!$CN:$CN,'Rateio Folha'!$C:$C,MONTH('Breakdown Alocação de Despesas'!P$6)) -> 62104.116 | Q56: =SUMIFS('Rateio Folha'!$CN:$CN,'Rateio Folha'!$C:$C,MONTH('Breakdown Alocação de Despesas'!Q$6)) -> 76025.065 | R56: =SUMIFS('Rateio Folha'!$CN:$CN,'Rateio Folha'!$C:$C,MONTH('Breakdown Alocação de Despesas'!R$6)) -> 77880.399 | S56: =SUMIFS('Rateio Folha'!$CN:$CN,'Rateio Folha'!$C:$C,MONTH('Breakdown Alocação de Despesas'!S$6)) -> 67463.715 | T56: =SUMIFS('Rateio Folha'!$CN:$CN,'Rateio Folha'!$C:$C,MONTH('Breakdown Alocação de Despesas'!T$6)) -> 78074.074 | U56: =SUMIFS('Rateio Folha'!$CN:$CN,'Rateio Folha'!$C:$C,MONTH('Breakdown Alocação de Despesas'!U$6)) -> 74682.458 | V56: =SUMIFS('Rateio Folha'!$CN:$CN,'Rateio Folha'!$C:$C,MONTH('Breakdown Alocação de Despesas'!V$6)) -> 77673.007 | W56: =SUMIFS('Rateio Folha'!$CN:$CN,'Rateio Folha'!$C:$C,MONTH('Breakdown Alocação de Despesas'!W$6)) -> 78586.473 | X56: =SUMIFS('Rateio Folha'!$CN:$CN,'Rateio Folha'!$C:$C,MONTH('Breakdown Alocação de Despesas'!X$6)) -> 62119.151 | Y56: =SUM(I56:K56,P56:X56) -> 840920.81 | AA56: =SUMIFS('Folha Forescast 3+9'!DL:DL,'Folha Forescast 3+9'!$I:$I,$C56) -> 74013.644 | AB56: =SUMIFS('Folha Forescast 3+9'!DM:DM,'Folha Forescast 3+9'!$I:$I,$C56) -> 74013.644 | AC56: =SUMIFS('Folha Forescast 3+9'!DN:DN,'Folha Forescast 3+9'!$I:$I,$C56) -> 74013.644 | AD56: =SUMIFS('Folha Forescast 3+9'!DO:DO,'Folha Forescast 3+9'!$I:$I,$C56) -> 74013.644 | AE56: =SUMIFS('Folha Forescast 3+9'!DP:DP,'Folha Forescast 3+9'!$I:$I,$C56) -> 76683.977 | AF56: =SUMIFS('Folha Forescast 3+9'!DQ:DQ,'Folha Forescast 3+9'!$I:$I,$C56) -> 76683.977 | AG56: =SUMIFS('Folha Forescast 3+9'!DR:DR,'Folha Forescast 3+9'!$I:$I,$C56) -> 76683.977 | AH56: =SUMIFS('Folha Forescast 3+9'!DS:DS,'Folha Forescast 3+9'!$I:$I,$C56) -> 76683.977 | AI56: =SUMIFS('Folha Forescast 3+9'!DT:DT,'Folha Forescast 3+9'!$I:$I,$C56) -> 76683.977 | AJ56: =SUMIFS('Folha Forescast 3+9'!DU:DU,'Folha Forescast 3+9'!$I:$I,$C56) -> 76683.977 | AK56: =SUMIFS('Folha Forescast 3+9'!DV:DV,'Folha Forescast 3+9'!$I:$I,$C56) -> 76683.977 | AL56: =SUMIFS('Folha Forescast 3+9'!DW:DW,'Folha Forescast 3+9'!$I:$I,$C56) -> 76683.977 | AM56: =SUM(AA56:AL56) -> 909526.39
C57: % Alocada da Folha de Backoffice | D57: =D56/D$31 -> 0.086158122 | E57: =E56/E$31 -> 0.092858647 | F57: =F56/F$31 -> 0.11941433 | G57: =G56/G$53 -> 0.051318084 | I57: =I56/I$31 -> 0.071238862 | J57: =J56/J$31 -> 0.068980967 | K57: =K56/K$31 -> 0.067739264 | L57: =L56/L$31 -> 0.069289631 | P57: =P56/P$53 -> 0.035840484 | Q57: =Q56/Q$53 -> 0.038778321 | R57: =R56/R$53 -> 0.038091819 | S57: =S56/S$53 -> 0.036185213 | T57: =T56/T$53 -> 0.03771227 | U57: =U56/U$53 -> 0.035705075 | V57: =V56/V$53 -> 0.037196238 | W57: =W56/W$53 -> 0.037228732 | ... Y57: =Y56/Y$53 -> 0.036729353 | AA57: =AA56/AA$53 -> 0.038452882 | AB57: =AB56/AB$53 -> 0.047498805 | AC57: =AC56/AC$53 -> 0.04732957 | AD57: =AD56/AD$53 -> 0.046871305 | AE57: =AE56/AE$53 -> 0.047299073 | AF57: =AF56/AF$53 -> 0.046431866 | AG57: =AG56/AG$53 -> 0.049563678 | AH57: =AH56/AH$53 -> 0.050318702 | ... AM57: =AM56/AM$53 -> 0.047826202
A59: =C59 -> Financeiro | C59: Financeiro | D59: =SUMIFS('Rateio Fopag'!$F:$F,'Rateio Fopag'!$H:$H,MONTH(D$6),'Rateio Fopag'!$J:$J,'Breakdown Alocação de Despesas'!$C59) -> 91831.314 | E59: =SUMIFS('Rateio Fopag'!$F:$F,'Rateio Fopag'!$H:$H,MONTH(E$6),'Rateio Fopag'!$J:$J,'Breakdown Alocação de Despesas'!$C59) -> 35988.591 | F59: =SUMIFS('Rateio Fopag'!$F:$F,'Rateio Fopag'!$H:$H,MONTH(F$6),'Rateio Fopag'!$J:$J,'Breakdown Alocação de Despesas'!$C59) -> 50973.295 | G59: =SUM(D59:F59) -> 178793.2 | I59: =SUMIFS('Rateio Folha'!$CP:$CP,'Rateio Folha'!$C:$C,MONTH('Breakdown Alocação de Despesas'!I$6)) -> 82980.263 | J59: =SUMIFS('Rateio Folha'!$CP:$CP,'Rateio Folha'!$C:$C,MONTH('Breakdown Alocação de Despesas'!J$6)) -> 82980.263 | K59: =SUMIFS('Rateio Folha'!$CP:$CP,'Rateio Folha'!$C:$C,MONTH('Breakdown Alocação de Despesas'!K$6)) -> 82980.263 | L59: =SUM(I59:K59) -> 248940.79 | N59: =G59/L59-1 -> -0.28178423 | P59: =SUMIFS('Rateio Folha'!$CP:$CP,'Rateio Folha'!$C:$C,MONTH('Breakdown Alocação de Despesas'!P$6)) -> 84652.348 | Q59: =SUMIFS('Rateio Folha'!$CP:$CP,'Rateio Folha'!$C:$C,MONTH('Breakdown Alocação de Despesas'!Q$6)) -> 102000.97 | R59: =SUMIFS('Rateio Folha'!$CP:$CP,'Rateio Folha'!$C:$C,MONTH('Breakdown Alocação de Despesas'!R$6)) -> 104490.22 | S59: =SUMIFS('Rateio Folha'!$CP:$CP,'Rateio Folha'!$C:$C,MONTH('Breakdown Alocação de Despesas'!S$6)) -> 92012.798 | T59: =SUMIFS('Rateio Folha'!$CP:$CP,'Rateio Folha'!$C:$C,MONTH('Breakdown Alocação de Despesas'!T$6)) -> 106484.11 | U59: =SUMIFS('Rateio Folha'!$CP:$CP,'Rateio Folha'!$C:$C,MONTH('Breakdown Alocação de Despesas'!U$6)) -> 101858.34 | V59: =SUMIFS('Rateio Folha'!$CP:$CP,'Rateio Folha'!$C:$C,MONTH('Breakdown Alocação de Despesas'!V$6)) -> 108990.58 | W59: =SUMIFS('Rateio Folha'!$CP:$CP,'Rateio Folha'!$C:$C,MONTH('Breakdown Alocação de Despesas'!W$6)) -> 110272.36 | X59: =SUMIFS('Rateio Folha'!$CP:$CP,'Rateio Folha'!$C:$C,MONTH('Breakdown Alocação de Despesas'!X$6)) -> 87165.448 | Y59: =SUM(I59:K59,P59:X59) -> 1146868 | AA59: =SUMIFS('Folha Forescast 3+9'!DL:DL,'Folha Forescast 3+9'!$I:$I,$C59) -> 89402.743 | AB59: =SUMIFS('Folha Forescast 3+9'!DM:DM,'Folha Forescast 3+9'!$I:$I,$C59) -> 37951.814 | AC59: =SUMIFS('Folha Forescast 3+9'!DN:DN,'Folha Forescast 3+9'!$I:$I,$C59) -> 37951.814 | AD59: =SUMIFS('Folha Forescast 3+9'!DO:DO,'Folha Forescast 3+9'!$I:$I,$C59) -> 40459.942 | AE59: =SUMIFS('Folha Forescast 3+9'!DP:DP,'Folha Forescast 3+9'!$I:$I,$C59) -> 41947.259 | AF59: =SUMIFS('Folha Forescast 3+9'!DQ:DQ,'Folha Forescast 3+9'!$I:$I,$C59) -> 41947.259 | AG59: =SUMIFS('Folha Forescast 3+9'!DR:DR,'Folha Forescast 3+9'!$I:$I,$C59) -> 41947.259 | AH59: =SUMIFS('Folha Forescast 3+9'!DS:DS,'Folha Forescast 3+9'!$I:$I,$C59) -> 41947.259 | AI59: =SUMIFS('Folha Forescast 3+9'!DT:DT,'Folha Forescast 3+9'!$I:$I,$C59) -> 41947.259 | AJ59: =SUMIFS('Folha Forescast 3+9'!DU:DU,'Folha Forescast 3+9'!$I:$I,$C59) -> 41947.259 | AK59: =SUMIFS('Folha Forescast 3+9'!DV:DV,'Folha Forescast 3+9'!$I:$I,$C59) -> 41947.259 | AL59: =SUMIFS('Folha Forescast 3+9'!DW:DW,'Folha Forescast 3+9'!$I:$I,$C59) -> 41947.259 | AM59: =SUM(AA59:AL59) -> 541344.38
C60: % Alocada da Folha de Backoffice | D60: =D59/D$31 -> 0.10163982 | E60: =E59/E$31 -> 0.043200709 | F60: =F59/F$31 -> 0.057467997 | G60: =G59/G$53 -> 0.035138498 | I60: =I59/I$31 -> 0.095185631 | J60: =J59/J$31 -> 0.09216875 | K60: =K59/K$31 -> 0.090509652 | L60: =L59/L$31 -> 0.092581171 | P60: =P59/P$53 -> 0.048853141 | Q60: =Q59/Q$53 -> 0.052027922 | R60: =R59/R$53 -> 0.05110686 | S60: =S59/S$53 -> 0.049352495 | T60: =T59/T$53 -> 0.051435226 | U60: =U59/U$53 -> 0.048697641 | V60: =V59/V$53 -> 0.052193675 | W60: =W59/W$53 -> 0.052239269 | ... Y60: =Y59/Y$53 -> 0.050092372 | AA60: =AA59/AA$53 -> 0.046448099 | AB60: =AB59/AB$53 -> 0.024355858 | AC60: =AC59/AC$53 -> 0.02426908 | AD60: =AD59/AD$53 -> 0.025622442 | AE60: =AE59/AE$53 -> 0.025873286 | AF60: =AF59/AF$53 -> 0.025398911 | AG60: =AG59/AG$53 -> 0.027112058 | AH60: =AH59/AH$53 -> 0.027525068 | ... AM60: =AM59/AM$53 -> 0.028465855
A62: Tech Academy | C62: People | D62: =SUMIFS('Rateio Fopag'!$F:$F,'Rateio Fopag'!$H:$H,MONTH(D$6),'Rateio Fopag'!$J:$J,'Breakdown Alocação de Despesas'!$C62) -> 63559.979 | E62: =SUMIFS('Rateio Fopag'!$F:$F,'Rateio Fopag'!$H:$H,MONTH(E$6),'Rateio Fopag'!$J:$J,'Breakdown Alocação de Despesas'!$C62) -> 63162.154 | F62: =SUMIFS('Rateio Fopag'!$F:$F,'Rateio Fopag'!$H:$H,MONTH(F$6),'Rateio Fopag'!$J:$J,'Breakdown Alocação de Despesas'!$C62) -> 86483.587 | G62: =SUM(D62:F62) -> 213205.72 | I62: =SUMIFS('Rateio Folha'!$CR:$CR,'Rateio Folha'!$C:$C,MONTH('Breakdown Alocação de Despesas'!I$6)) -> 53298.179 | J62: =SUMIFS('Rateio Folha'!$CR:$CR,'Rateio Folha'!$C:$C,MONTH('Breakdown Alocação de Despesas'!J$6)) -> 66311.615 | K62: =SUMIFS('Rateio Folha'!$CR:$CR,'Rateio Folha'!$C:$C,MONTH('Breakdown Alocação de Despesas'!K$6)) -> 66311.615 | L62: =SUM(I62:K62) -> 185921.41 | N62: =G62/L62-1 -> 0.14675186 | P62: =SUMIFS('Rateio Folha'!$CR:$CR,'Rateio Folha'!$C:$C,MONTH('Breakdown Alocação de Despesas'!P$6)) -> 67938.554 | Q62: =SUMIFS('Rateio Folha'!$CR:$CR,'Rateio Folha'!$C:$C,MONTH('Breakdown Alocação de Despesas'!Q$6)) -> 81703.743 | R62: =SUMIFS('Rateio Folha'!$CR:$CR,'Rateio Folha'!$C:$C,MONTH('Breakdown Alocação de Despesas'!R$6)) -> 83697.661 | S62: =SUMIFS('Rateio Folha'!$CR:$CR,'Rateio Folha'!$C:$C,MONTH('Breakdown Alocação de Despesas'!S$6)) -> 71393.215 | T62: =SUMIFS('Rateio Folha'!$CR:$CR,'Rateio Folha'!$C:$C,MONTH('Breakdown Alocação de Despesas'!T$6)) -> 82621.586 | U62: =SUMIFS('Rateio Folha'!$CR:$CR,'Rateio Folha'!$C:$C,MONTH('Breakdown Alocação de Despesas'!U$6)) -> 79032.421 | V62: =SUMIFS('Rateio Folha'!$CR:$CR,'Rateio Folha'!$C:$C,MONTH('Breakdown Alocação de Despesas'!V$6)) -> 82197.158 | W62: =SUMIFS('Rateio Folha'!$CR:$CR,'Rateio Folha'!$C:$C,MONTH('Breakdown Alocação de Despesas'!W$6)) -> 83163.83 | X62: =SUMIFS('Rateio Folha'!$CR:$CR,'Rateio Folha'!$C:$C,MONTH('Breakdown Alocação de Despesas'!X$6)) -> 65737.351 | Y62: =SUM(I62:K62,P62:X62) -> 883406.93 | AA62: =SUMIFS('Folha Forescast 3+9'!DL:DL,'Folha Forescast 3+9'!$I:$I,$C62) -> 61613.46 | AB62: =SUMIFS('Folha Forescast 3+9'!DM:DM,'Folha Forescast 3+9'!$I:$I,$C62) -> 61613.46 | AC62: =SUMIFS('Folha Forescast 3+9'!DN:DN,'Folha Forescast 3+9'!$I:$I,$C62) -> 61613.46 | AD62: =SUMIFS('Folha Forescast 3+9'!DO:DO,'Folha Forescast 3+9'!$I:$I,$C62) -> 64957.63 | AE62: =SUMIFS('Folha Forescast 3+9'!DP:DP,'Folha Forescast 3+9'!$I:$I,$C62) -> 43856.736 | AF62: =SUMIFS('Folha Forescast 3+9'!DQ:DQ,'Folha Forescast 3+9'!$I:$I,$C62) -> 43856.736 | AG62: =SUMIFS('Folha Forescast 3+9'!DR:DR,'Folha Forescast 3+9'!$I:$I,$C62) -> 43856.736 | AH62: =SUMIFS('Folha Forescast 3+9'!DS:DS,'Folha Forescast 3+9'!$I:$I,$C62) -> 43856.736 | AI62: =SUMIFS('Folha Forescast 3+9'!DT:DT,'Folha Forescast 3+9'!$I:$I,$C62) -> 43856.736 | AJ62: =SUMIFS('Folha Forescast 3+9'!DU:DU,'Folha Forescast 3+9'!$I:$I,$C62) -> 43856.736 | AK62: =SUMIFS('Folha Forescast 3+9'!DV:DV,'Folha Forescast 3+9'!$I:$I,$C62) -> 43856.736 | AL62: =SUMIFS('Folha Forescast 3+9'!DW:DW,'Folha Forescast 3+9'!$I:$I,$C62) -> 43856.736 | AM62: =SUM(AA62:AL62) -> 600651.89
C63: % Alocada da Folha de Backoffice | D63: =D62/D$31 -> 0.070348823 | E63: =E62/E$31 -> 0.075819858 | F63: =F62/F$31 -> 0.097502791 | G63: =G62/G$53 -> 0.041901642 | I63: =I62/I$31 -> 0.06113768 | J63: =J62/J$31 -> 0.073654366 | K63: =K62/K$31 -> 0.072328539 | L63: =L62/L$31 -> 0.06914424 | P63: =P62/P$53 -> 0.039207557 | Q63: =Q62/Q$53 -> 0.04167486 | R63: =R62/R$53 -> 0.040937081 | S63: =S62/S$53 -> 0.038292861 | T63: =T62/T$53 -> 0.039908863 | U63: =U62/U$53 -> 0.037784757 | V63: =V62/V$53 -> 0.039362775 | W63: =W62/W$53 -> 0.039397161 | ... Y63: =Y62/Y$53 -> 0.038585042 | AA63: =AA62/AA$53 -> 0.032010518 | AB63: =AB62/AB$53 -> 0.039540894 | AC63: =AC62/AC$53 -> 0.039400013 | AD63: =AD62/AD$53 -> 0.041136319 | AE63: =AE62/AE$53 -> 0.027051061 | AF63: =AF62/AF$53 -> 0.026555092 | AG63: =AG62/AG$53 -> 0.028346223 | AH63: =AH62/AH$53 -> 0.028778033 | ... AM63: =AM62/AM$53 -> 0.031584459
A65: =C65 -> Atendimento | C65: Atendimento | D65: =SUMIFS('Rateio Fopag'!$F:$F,'Rateio Fopag'!$H:$H,MONTH(D$6),'Rateio Fopag'!$J:$J,'Breakdown Alocação de Despesas'!$C65) -> 67813.22 | E65: =SUMIFS('Rateio Fopag'!$F:$F,'Rateio Fopag'!$H:$H,MONTH(E$6),'Rateio Fopag'!$J:$J,'Breakdown Alocação de Despesas'!$C65) -> 67388.774 | F65: =SUMIFS('Rateio Fopag'!$F:$F,'Rateio Fopag'!$H:$H,MONTH(F$6),'Rateio Fopag'!$J:$J,'Breakdown Alocação de Despesas'!$C65) -> 88022.628 | G65: =SUM(D65:F65) -> 223224.62 | I65: =SUMIFS('Rateio Folha'!$CM:$CM,'Rateio Folha'!$C:$C,MONTH('Breakdown Alocação de Despesas'!I$6)) -> 58514.583 | J65: =SUMIFS('Rateio Folha'!$CM:$CM,'Rateio Folha'!$C:$C,MONTH('Breakdown Alocação de Despesas'!J$6)) -> 58514.583 | K65: =SUMIFS('Rateio Folha'!$CM:$CM,'Rateio Folha'!$C:$C,MONTH('Breakdown Alocação de Despesas'!K$6)) -> 59770.319 | L65: =SUM(I65:K65) -> 176799.48 | N65: =G65/L65-1 -> 0.26258639 | P65: =SUMIFS('Rateio Folha'!$CM:$CM,'Rateio Folha'!$C:$C,MONTH('Breakdown Alocação de Despesas'!P$6)) -> 59770.319 | Q65: =SUMIFS('Rateio Folha'!$CM:$CM,'Rateio Folha'!$C:$C,MONTH('Breakdown Alocação de Despesas'!Q$6)) -> 71477.789 | R65: =SUMIFS('Rateio Folha'!$CM:$CM,'Rateio Folha'!$C:$C,MONTH('Breakdown Alocação de Despesas'!R$6)) -> 73222.15 | S65: =SUMIFS('Rateio Folha'!$CM:$CM,'Rateio Folha'!$C:$C,MONTH('Breakdown Alocação de Despesas'!S$6)) -> 62457.716 | T65: =SUMIFS('Rateio Folha'!$CM:$CM,'Rateio Folha'!$C:$C,MONTH('Breakdown Alocação de Despesas'!T$6)) -> 72280.756 | U65: =SUMIFS('Rateio Folha'!$CM:$CM,'Rateio Folha'!$C:$C,MONTH('Breakdown Alocação de Despesas'!U$6)) -> 69140.807 | V65: =SUMIFS('Rateio Folha'!$CM:$CM,'Rateio Folha'!$C:$C,MONTH('Breakdown Alocação de Despesas'!V$6)) -> 71909.449 | W65: =SUMIFS('Rateio Folha'!$CM:$CM,'Rateio Folha'!$C:$C,MONTH('Breakdown Alocação de Despesas'!W$6)) -> 72755.133 | X65: =SUMIFS('Rateio Folha'!$CM:$CM,'Rateio Folha'!$C:$C,MONTH('Breakdown Alocação de Despesas'!X$6)) -> 57509.734 | Y65: =SUM(I65:K65,P65:X65) -> 787323.34 | AA65: =SUMIFS('Folha Forescast 3+9'!DL:DL,'Folha Forescast 3+9'!$I:$I,$C65) -> 74763.099 | AB65: =SUMIFS('Folha Forescast 3+9'!DM:DM,'Folha Forescast 3+9'!$I:$I,$C65) -> 74636.021 | AC65: =SUMIFS('Folha Forescast 3+9'!DN:DN,'Folha Forescast 3+9'!$I:$I,$C65) -> 74636.021 | AD65: =SUMIFS('Folha Forescast 3+9'!DO:DO,'Folha Forescast 3+9'!$I:$I,$C65) -> 79707.355 | AE65: =SUMIFS('Folha Forescast 3+9'!DP:DP,'Folha Forescast 3+9'!$I:$I,$C65) -> 82718.47 | AF65: =SUMIFS('Folha Forescast 3+9'!DQ:DQ,'Folha Forescast 3+9'!$I:$I,$C65) -> 82718.47 | AG65: =SUMIFS('Folha Forescast 3+9'!DR:DR,'Folha Forescast 3+9'!$I:$I,$C65) -> 82718.47 | AH65: =SUMIFS('Folha Forescast 3+9'!DS:DS,'Folha Forescast 3+9'!$I:$I,$C65) -> 82718.47 | AI65: =SUMIFS('Folha Forescast 3+9'!DT:DT,'Folha Forescast 3+9'!$I:$I,$C65) -> 82718.47 | AJ65: =SUMIFS('Folha Forescast 3+9'!DU:DU,'Folha Forescast 3+9'!$I:$I,$C65) -> 82718.47 | AK65: =SUMIFS('Folha Forescast 3+9'!DV:DV,'Folha Forescast 3+9'!$I:$I,$C65) -> 82718.47 | AL65: =SUMIFS('Folha Forescast 3+9'!DW:DW,'Folha Forescast 3+9'!$I:$I,$C65) -> 82718.47 | AM65: =SUM(AA65:AL65) -> 965490.26
C66: % Alocada da Folha de Backoffice | D66: =D65/D$31 -> 0.075056353 | E66: =E65/E$31 -> 0.080893493 | F66: =F65/F$31 -> 0.099237927 | G66: =G65/G$53 -> 0.043870672 | I66: =I65/I$31 -> 0.067121352 | J66: =J65/J$31 -> 0.064993961 | K66: =K65/K$31 -> 0.065193705 | L66: =L65/L$31 -> 0.065751793 | P66: =P65/P$53 -> 0.034493642 | Q66: =Q65/Q$53 -> 0.036458879 | R66: =R65/R$53 -> 0.035813439 | S66: =S65/S$53 -> 0.033500167 | T66: =T65/T$53 -> 0.034913912 | U66: =U65/U$53 -> 0.033055656 | V66: =V65/V$53 -> 0.034436171 | W66: =W65/W$53 -> 0.034466254 | ... Y66: =Y65/Y$53 -> 0.034388347 | AA66: =AA65/AA$53 -> 0.038842252 | AB66: =AB65/AB$53 -> 0.047898219 | AC66: =AC65/AC$53 -> 0.047727562 | AD66: =AD65/AD$53 -> 0.050477014 | AE66: =AE65/AE$53 -> 0.05102118 | AF66: =AF65/AF$53 -> 0.05008573 | AG66: =AG65/AG$53 -> 0.053463994 | AH66: =AH65/AH$53 -> 0.054278433 | ... AM66: =AM65/AM$53 -> 0.050768986
A68: Produtos Inter | C68: Revops | D68: =SUMIFS('Rateio Fopag'!$F:$F,'Rateio Fopag'!$H:$H,MONTH(D$6),'Rateio Fopag'!$J:$J,'Breakdown Alocação de Despesas'!$C68) -> 99757.291 | E68: =SUMIFS('Rateio Fopag'!$F:$F,'Rateio Fopag'!$H:$H,MONTH(E$6),'Rateio Fopag'!$J:$J,'Breakdown Alocação de Despesas'!$C68) -> 98482.318 | F68: =SUMIFS('Rateio Fopag'!$F:$F,'Rateio Fopag'!$H:$H,MONTH(F$6),'Rateio Fopag'!$J:$J,'Breakdown Alocação de Despesas'!$C68) -> 132671.46 | G68: =SUM(D68:F68) -> 330911.07 | I68: =SUMIFS('Rateio Folha'!$CS:$CS,'Rateio Folha'!$C:$C,MONTH('Breakdown Alocação de Despesas'!I$6)) -> 91235.36 | J68: =SUMIFS('Rateio Folha'!$CS:$CS,'Rateio Folha'!$C:$C,MONTH('Breakdown Alocação de Despesas'!J$6)) -> 91235.36 | K68: =SUMIFS('Rateio Folha'!$CS:$CS,'Rateio Folha'!$C:$C,MONTH('Breakdown Alocação de Despesas'!K$6)) -> 91235.36 | L68: =SUM(I68:K68) -> 273706.08 | N68: =G68/L68-1 -> 0.20900152 | P68: =SUMIFS('Rateio Folha'!$CS:$CS,'Rateio Folha'!$C:$C,MONTH('Breakdown Alocação de Despesas'!P$6)) -> 91235.36 | Q68: =SUMIFS('Rateio Folha'!$CS:$CS,'Rateio Folha'!$C:$C,MONTH('Breakdown Alocação de Despesas'!Q$6)) -> 108765.93 | R68: =SUMIFS('Rateio Folha'!$CS:$CS,'Rateio Folha'!$C:$C,MONTH('Breakdown Alocação de Despesas'!R$6)) -> 111420.28 | S68: =SUMIFS('Rateio Folha'!$CS:$CS,'Rateio Folha'!$C:$C,MONTH('Breakdown Alocação de Despesas'!S$6)) -> 95040.311 | T68: =SUMIFS('Rateio Folha'!$CS:$CS,'Rateio Folha'!$C:$C,MONTH('Breakdown Alocação de Despesas'!T$6)) -> 116915.41 | U68: =SUMIFS('Rateio Folha'!$CS:$CS,'Rateio Folha'!$C:$C,MONTH('Breakdown Alocação de Despesas'!U$6)) -> 111836.49 | V68: =SUMIFS('Rateio Folha'!$CS:$CS,'Rateio Folha'!$C:$C,MONTH('Breakdown Alocação de Despesas'!V$6)) -> 116314.82 | W68: =SUMIFS('Rateio Folha'!$CS:$CS,'Rateio Folha'!$C:$C,MONTH('Breakdown Alocação de Despesas'!W$6)) -> 117682.73 | X68: =SUMIFS('Rateio Folha'!$CS:$CS,'Rateio Folha'!$C:$C,MONTH('Breakdown Alocação de Despesas'!X$6)) -> 93023.021 | Y68: =SUM(I68:K68,P68:X68) -> 1235940.4 | AA68: =SUMIFS('Folha Forescast 3+9'!DL:DL,'Folha Forescast 3+9'!$I:$I,$C68) -> 88459.108 | AB68: =SUMIFS('Folha Forescast 3+9'!DM:DM,'Folha Forescast 3+9'!$I:$I,$C68) -> 88459.108 | AC68: =SUMIFS('Folha Forescast 3+9'!DN:DN,'Folha Forescast 3+9'!$I:$I,$C68) -> 88459.108 | AD68: =SUMIFS('Folha Forescast 3+9'!DO:DO,'Folha Forescast 3+9'!$I:$I,$C68) -> 75817.552 | AE68: =SUMIFS('Folha Forescast 3+9'!DP:DP,'Folha Forescast 3+9'!$I:$I,$C68) -> 107049.94 | AF68: =SUMIFS('Folha Forescast 3+9'!DQ:DQ,'Folha Forescast 3+9'!$I:$I,$C68) -> 110858.27 | AG68: =SUMIFS('Folha Forescast 3+9'!DR:DR,'Folha Forescast 3+9'!$I:$I,$C68) -> 110858.27 | AH68: =SUMIFS('Folha Forescast 3+9'!DS:DS,'Folha Forescast 3+9'!$I:$I,$C68) -> 113024.94 | AI68: =SUMIFS('Folha Forescast 3+9'!DT:DT,'Folha Forescast 3+9'!$I:$I,$C68) -> 113024.94 | AJ68: =SUMIFS('Folha Forescast 3+9'!DU:DU,'Folha Forescast 3+9'!$I:$I,$C68) -> 113024.94 | AK68: =SUMIFS('Folha Forescast 3+9'!DV:DV,'Folha Forescast 3+9'!$I:$I,$C68) -> 113024.94 | AL68: =SUMIFS('Folha Forescast 3+9'!DW:DW,'Folha Forescast 3+9'!$I:$I,$C68) -> 113024.94 | AM68: =SUM(AA68:AL68) -> 1235086
C69: % Alocada da Folha de Backoffice | D69: =D68/D$31 -> 0.11041237 | E69: =E68/E$31 -> 0.11821819 | F69: =F68/F$31 -> 0.14957563 | G69: =G68/G$53 -> 0.065034452 | I69: =I68/I$31 -> 0.10465495 | J69: =J68/J$31 -> 0.10133794 | K69: =K68/K$31 -> 0.099513792 | L69: =L68/L$31 -> 0.10179139 | P69: =P68/P$53 -> 0.052652218 | Q69: =Q68/Q$53 -> 0.055478545 | R69: =R68/R$53 -> 0.054496395 | S69: =S68/S$53 -> 0.050976349 | T69: =T68/T$53 -> 0.056473876 | U69: =U68/U$53 -> 0.053468114 | V69: =V68/V$53 -> 0.055701122 | W69: =W68/W$53 -> 0.055749781 | ... Y69: =Y68/Y$53 -> 0.053982838 | AA69: =AA68/AA$53 -> 0.045957845 | AB69: =AB68/AB$53 -> 0.056769288 | AC69: =AC68/AC$53 -> 0.056567023 | AD69: =AD68/AD$53 -> 0.048013683 | AE69: =AE68/AE$53 -> 0.066028955 | AF69: =AF68/AF$53 -> 0.067124276 | AG69: =AG68/AG$53 -> 0.071651783 | AH69: =AH68/AH$53 -> 0.074165014 | ... AM69: =AM68/AM$53 -> 0.064945312
A71: =C71 -> Facilites | C71: Facilites | D71: =SUMIFS('Rateio Fopag'!$F:$F,'Rateio Fopag'!$H:$H,MONTH(D$6),'Rateio Fopag'!$J:$J,'Breakdown Alocação de Despesas'!$C71) -> 38521.199 | E71: =SUMIFS('Rateio Fopag'!$F:$F,'Rateio Fopag'!$H:$H,MONTH(E$6),'Rateio Fopag'!$J:$J,'Breakdown Alocação de Despesas'!$C71) -> 38280.094 | F71: =SUMIFS('Rateio Fopag'!$F:$F,'Rateio Fopag'!$H:$H,MONTH(F$6),'Rateio Fopag'!$J:$J,'Breakdown Alocação de Despesas'!$C71) -> 52414.295 | G71: =SUM(D71:F71) -> 129215.59 | I71: =SUMIFS('Rateio Folha'!$CO:$CO,'Rateio Folha'!$C:$C,MONTH('Breakdown Alocação de Despesas'!I$6)) -> 36030.554 | J71: =SUMIFS('Rateio Folha'!$CO:$CO,'Rateio Folha'!$C:$C,MONTH('Breakdown Alocação de Despesas'!J$6)) -> 36030.554 | K71: =SUMIFS('Rateio Folha'!$CO:$CO,'Rateio Folha'!$C:$C,MONTH('Breakdown Alocação de Despesas'!K$6)) -> 36030.554 | L71: =SUM(I71:K71) -> 108091.66 | N71: =G71/L71-1 -> 0.19542606 | P71: =SUMIFS('Rateio Folha'!$CO:$CO,'Rateio Folha'!$C:$C,MONTH('Breakdown Alocação de Despesas'!P$6)) -> 36030.554 | Q71: =SUMIFS('Rateio Folha'!$CO:$CO,'Rateio Folha'!$C:$C,MONTH('Breakdown Alocação de Despesas'!Q$6)) -> 43218.679 | R71: =SUMIFS('Rateio Folha'!$CO:$CO,'Rateio Folha'!$C:$C,MONTH('Breakdown Alocação de Despesas'!R$6)) -> 44273.398 | S71: =SUMIFS('Rateio Folha'!$CO:$CO,'Rateio Folha'!$C:$C,MONTH('Breakdown Alocação de Despesas'!S$6)) -> 38648.781 | T71: =SUMIFS('Rateio Folha'!$CO:$CO,'Rateio Folha'!$C:$C,MONTH('Breakdown Alocação de Despesas'!T$6)) -> 44727.27 | U71: =SUMIFS('Rateio Folha'!$CO:$CO,'Rateio Folha'!$C:$C,MONTH('Breakdown Alocação de Despesas'!U$6)) -> 42784.272 | V71: =SUMIFS('Rateio Folha'!$CO:$CO,'Rateio Folha'!$C:$C,MONTH('Breakdown Alocação de Despesas'!V$6)) -> 44497.506 | W71: =SUMIFS('Rateio Folha'!$CO:$CO,'Rateio Folha'!$C:$C,MONTH('Breakdown Alocação de Despesas'!W$6)) -> 45020.814 | X71: =SUMIFS('Rateio Folha'!$CO:$CO,'Rateio Folha'!$C:$C,MONTH('Breakdown Alocação de Despesas'!X$6)) -> 35586.974 | Y71: =SUM(I71:K71,P71:X71) -> 482879.91 | AA71: =SUMIFS('Folha Forescast 3+9'!DL:DL,'Folha Forescast 3+9'!$I:$I,$C71) -> 27698.957 | AB71: =SUMIFS('Folha Forescast 3+9'!DM:DM,'Folha Forescast 3+9'!$I:$I,$C71) -> 27698.957 | AC71: =SUMIFS('Folha Forescast 3+9'!DN:DN,'Folha Forescast 3+9'!$I:$I,$C71) -> 27698.957 | AD71: =SUMIFS('Folha Forescast 3+9'!DO:DO,'Folha Forescast 3+9'!$I:$I,$C71) -> 27698.957 | AE71: =SUMIFS('Folha Forescast 3+9'!DP:DP,'Folha Forescast 3+9'!$I:$I,$C71) -> 28909.212 | AF71: =SUMIFS('Folha Forescast 3+9'!DQ:DQ,'Folha Forescast 3+9'!$I:$I,$C71) -> 28909.212 | AG71: =SUMIFS('Folha Forescast 3+9'!DR:DR,'Folha Forescast 3+9'!$I:$I,$C71) -> 41605.286 | AH71: =SUMIFS('Folha Forescast 3+9'!DS:DS,'Folha Forescast 3+9'!$I:$I,$C71) -> 41605.286 | AI71: =SUMIFS('Folha Forescast 3+9'!DT:DT,'Folha Forescast 3+9'!$I:$I,$C71) -> 41605.286 | AJ71: =SUMIFS('Folha Forescast 3+9'!DU:DU,'Folha Forescast 3+9'!$I:$I,$C71) -> 41605.286 | AK71: =SUMIFS('Folha Forescast 3+9'!DV:DV,'Folha Forescast 3+9'!$I:$I,$C71) -> 41605.286 | AL71: =SUMIFS('Folha Forescast 3+9'!DW:DW,'Folha Forescast 3+9'!$I:$I,$C71) -> 41605.286 | AM71: =SUM(AA71:AL71) -> 418245.97
C72: % Alocada da Folha de Backoffice | D72: =D71/D$31 -> 0.04263565 | E72: =E71/E$31 -> 0.045951429 | F72: =F71/F$31 -> 0.0590926 | G72: =G71/G$53 -> 0.025394935 | I72: =I71/I$31 -> 0.041330201 | J72: =J71/J$31 -> 0.040020253 | K72: =K71/K$31 -> 0.039299862 | L72: =L71/L$31 -> 0.040199329 | P72: =P71/P$53 -> 0.020793348 | Q72: =Q71/Q$53 -> 0.022044674 | R72: =R71/R$53 -> 0.021654412 | S72: =S71/S$53 -> 0.020729875 | T72: =T71/T$53 -> 0.021604699 | U72: =U71/U$53 -> 0.020454812 | V72: =V71/V$53 -> 0.021309074 | W72: =W71/W$53 -> 0.021327689 | ... Y72: =Y71/Y$53 -> 0.021091007 | AA72: =AA71/AA$53 -> 0.014390654 | AB72: =AB71/AB$53 -> 0.017776011 | AC72: =AC71/AC$53 -> 0.017712676 | AD72: =AD71/AD$53 -> 0.017541175 | AE72: =AE71/AE$53 -> 0.017831352 | AF72: =AF71/AF$53 -> 0.017504422 | AG72: =AG71/AG$53 -> 0.026891029 | AH72: =AH71/AH$53 -> 0.027300671 | ... AM72: =AM71/AM$53 -> 0.021992893
A74: Tech Academy | C74: Ops | D74: =SUMIFS('Rateio Fopag'!$F:$F,'Rateio Fopag'!$H:$H,MONTH(D$6),'Rateio Fopag'!$J:$J,'Breakdown Alocação de Despesas'!$C74) -> 115169.22 | E74: =SUMIFS('Rateio Fopag'!$F:$F,'Rateio Fopag'!$H:$H,MONTH(E$6),'Rateio Fopag'!$J:$J,'Breakdown Alocação de Despesas'!$C74) -> 113797.78 | F74: =SUMIFS('Rateio Fopag'!$F:$F,'Rateio Fopag'!$H:$H,MONTH(F$6),'Rateio Fopag'!$J:$J,'Breakdown Alocação de Despesas'!$C74) -> 129631.27 | G74: =SUM(D74:F74) -> 358598.27 | I74: =SUMIFS('Rateio Folha'!$CQ:$CQ,'Rateio Folha'!$C:$C,MONTH('Breakdown Alocação de Despesas'!I$6)) -> 117359.08 | J74: =SUMIFS('Rateio Folha'!$CQ:$CQ,'Rateio Folha'!$C:$C,MONTH('Breakdown Alocação de Despesas'!J$6)) -> 117359.08 | K74: =SUMIFS('Rateio Folha'!$CQ:$CQ,'Rateio Folha'!$C:$C,MONTH('Breakdown Alocação de Despesas'!K$6)) -> 120432.37 | L74: =SUM(I74:K74) -> 355150.53 | N74: =G74/L74-1 -> 0.0097078192 | P74: =SUMIFS('Rateio Folha'!$CQ:$CQ,'Rateio Folha'!$C:$C,MONTH('Breakdown Alocação de Despesas'!P$6)) -> 120432.37 | Q74: =SUMIFS('Rateio Folha'!$CQ:$CQ,'Rateio Folha'!$C:$C,MONTH('Breakdown Alocação de Despesas'!Q$6)) -> 144013.06 | R74: =SUMIFS('Rateio Folha'!$CQ:$CQ,'Rateio Folha'!$C:$C,MONTH('Breakdown Alocação de Despesas'!R$6)) -> 147527.59 | S74: =SUMIFS('Rateio Folha'!$CQ:$CQ,'Rateio Folha'!$C:$C,MONTH('Breakdown Alocação de Despesas'!S$6)) -> 125839.47 | T74: =SUMIFS('Rateio Folha'!$CQ:$CQ,'Rateio Folha'!$C:$C,MONTH('Breakdown Alocação de Despesas'!T$6)) -> 145630.88 | U74: =SUMIFS('Rateio Folha'!$CQ:$CQ,'Rateio Folha'!$C:$C,MONTH('Breakdown Alocação de Despesas'!U$6)) -> 139304.52 | V74: =SUMIFS('Rateio Folha'!$CQ:$CQ,'Rateio Folha'!$C:$C,MONTH('Breakdown Alocação de Despesas'!V$6)) -> 144882.77 | W74: =SUMIFS('Rateio Folha'!$CQ:$CQ,'Rateio Folha'!$C:$C,MONTH('Breakdown Alocação de Despesas'!W$6)) -> 146586.65 | X74: =SUMIFS('Rateio Folha'!$CQ:$CQ,'Rateio Folha'!$C:$C,MONTH('Breakdown Alocação de Despesas'!X$6)) -> 115870.3 | Y74: =SUM(I74:K74,P74:X74) -> 1585238.1 | AA74: =SUMIFS('Folha Forescast 3+9'!DL:DL,'Folha Forescast 3+9'!$I:$I,$C74) -> 359113.9 | AB74: =SUMIFS('Folha Forescast 3+9'!DM:DM,'Folha Forescast 3+9'!$I:$I,$C74) -> 130675.66 | AC74: =SUMIFS('Folha Forescast 3+9'!DN:DN,'Folha Forescast 3+9'!$I:$I,$C74) -> 136247.32 | AD74: =SUMIFS('Folha Forescast 3+9'!DO:DO,'Folha Forescast 3+9'!$I:$I,$C74) -> 148071.13 | AE74: =SUMIFS('Folha Forescast 3+9'!DP:DP,'Folha Forescast 3+9'!$I:$I,$C74) -> 161512.36 | AF74: =SUMIFS('Folha Forescast 3+9'!DQ:DQ,'Folha Forescast 3+9'!$I:$I,$C74) -> 184175.89 | AG74: =SUMIFS('Folha Forescast 3+9'!DR:DR,'Folha Forescast 3+9'!$I:$I,$C74) -> 256839.42 | AH74: =SUMIFS('Folha Forescast 3+9'!DS:DS,'Folha Forescast 3+9'!$I:$I,$C74) -> 217002.95 | AI74: =SUMIFS('Folha Forescast 3+9'!DT:DT,'Folha Forescast 3+9'!$I:$I,$C74) -> 189666.47 | AJ74: =SUMIFS('Folha Forescast 3+9'!DU:DU,'Folha Forescast 3+9'!$I:$I,$C74) -> 199830 | AK74: =SUMIFS('Folha Forescast 3+9'!DV:DV,'Folha Forescast 3+9'!$I:$I,$C74) -> 209993.53 | AL74: =SUMIFS('Folha Forescast 3+9'!DW:DW,'Folha Forescast 3+9'!$I:$I,$C74) -> 220157.06 | AM74: =SUM(AA74:AL74) -> 2413285.7
C75: % Alocada da Folha de Backoffice | D75: =D74/D$31 -> 0.12747045 | E75: =E74/E$31 -> 0.13660287 | F75: =F74/F$31 -> 0.14614809 | G75: =G74/G$53 -> 0.07047586 | I75: =I74/I$31 -> 0.13462115 | J75: =J74/J$31 -> 0.13035437 | K75: =K74/K$31 -> 0.13136006 | L75: =L74/L$31 -> 0.13208061 | P75: =P74/P$53 -> 0.069501908 | Q75: =Q74/Q$53 -> 0.073457151 | R75: =R74/R$53 -> 0.072156723 | S75: =S74/S$53 -> 0.067495955 | T75: =T74/T$53 -> 0.070344361 | U75: =U74/U$53 -> 0.066600358 | V75: =V74/V$53 -> 0.069381812 | W75: =W74/W$53 -> 0.069442422 | ... Y75: =Y74/Y$53 -> 0.069239304 | AA75: =AA74/AA$53 -> 0.18657322 | AB75: =AB74/AB$53 -> 0.083862071 | AC75: =AC74/AC$53 -> 0.087126196 | AD75: =AD74/AD$53 -> 0.093770372 | AE75: =AE74/AE$53 -> 0.09962166 | AF75: =AF74/AF$53 -> 0.11151783 | AG75: =AG74/AG$53 -> 0.16600478 | AH75: =AH74/AH$53 -> 0.14239359 | ... AM75: =AM74/AM$53 -> 0.12689933
A77: =C77 -> Tech | C77: Tech | D77: =SUMIFS('Rateio Fopag'!$F:$F,'Rateio Fopag'!$H:$H,MONTH(D$6),'Rateio Fopag'!$J:$J,'Breakdown Alocação de Despesas'!$C77) -> 321517.51 | E77: =SUMIFS('Rateio Fopag'!$F:$F,'Rateio Fopag'!$H:$H,MONTH(E$6),'Rateio Fopag'!$J:$J,'Breakdown Alocação de Despesas'!$C77) -> 260130.87 | F77: =SUMIFS('Rateio Fopag'!$F:$F,'Rateio Fopag'!$H:$H,MONTH(F$6),'Rateio Fopag'!$J:$J,'Breakdown Alocação de Despesas'!$C77) -> 316520.99 | G77: =SUM(D77:F77) -> 898169.37 | I77: =SUMIFS('Rateio Folha'!$CT:$CT,'Rateio Folha'!$C:$C,MONTH('Breakdown Alocação de Despesas'!I$6)) -> 324442.84 | J77: =SUMIFS('Rateio Folha'!$CT:$CT,'Rateio Folha'!$C:$C,MONTH('Breakdown Alocação de Despesas'!J$6)) -> 324442.84 | K77: =SUMIFS('Rateio Folha'!$CT:$CT,'Rateio Folha'!$C:$C,MONTH('Breakdown Alocação de Despesas'!K$6)) -> 331575.28 | L77: =SUM(I77:K77) -> 980460.97 | N77: =G77/L77-1 -> -0.083931548 | P77: =SUMIFS('Rateio Folha'!$CT:$CT,'Rateio Folha'!$C:$C,MONTH('Breakdown Alocação de Despesas'!P$6)) -> 338979.28 | Q77: =SUMIFS('Rateio Folha'!$CT:$CT,'Rateio Folha'!$C:$C,MONTH('Breakdown Alocação de Despesas'!Q$6)) -> 410566.93 | R77: =SUMIFS('Rateio Folha'!$CT:$CT,'Rateio Folha'!$C:$C,MONTH('Breakdown Alocação de Despesas'!R$6)) -> 420586.5 | S77: =SUMIFS('Rateio Folha'!$CT:$CT,'Rateio Folha'!$C:$C,MONTH('Breakdown Alocação de Despesas'!S$6)) -> 372995.57 | T77: =SUMIFS('Rateio Folha'!$CT:$CT,'Rateio Folha'!$C:$C,MONTH('Breakdown Alocação de Despesas'!T$6)) -> 431658.46 | U77: =SUMIFS('Rateio Folha'!$CT:$CT,'Rateio Folha'!$C:$C,MONTH('Breakdown Alocação de Despesas'!U$6)) -> 412906.78 | V77: =SUMIFS('Rateio Folha'!$CT:$CT,'Rateio Folha'!$C:$C,MONTH('Breakdown Alocação de Despesas'!V$6)) -> 429441.03 | W77: =SUMIFS('Rateio Folha'!$CT:$CT,'Rateio Folha'!$C:$C,MONTH('Breakdown Alocação de Despesas'!W$6)) -> 434491.43 | X77: =SUMIFS('Rateio Folha'!$CT:$CT,'Rateio Folha'!$C:$C,MONTH('Breakdown Alocação de Despesas'!X$6)) -> 343446.37 | Y77: =SUM(I77:K77,P77:X77) -> 4575533.3 | AA77: =SUMIFS('Folha Forescast 3+9'!DL:DL,'Folha Forescast 3+9'!$I:$I,$C77) -> 318054.44 | AB77: =SUMIFS('Folha Forescast 3+9'!DM:DM,'Folha Forescast 3+9'!$I:$I,$C77) -> 231503.91 | AC77: =SUMIFS('Folha Forescast 3+9'!DN:DN,'Folha Forescast 3+9'!$I:$I,$C77) -> 231503.91 | AD77: =SUMIFS('Folha Forescast 3+9'!DO:DO,'Folha Forescast 3+9'!$I:$I,$C77) -> 236687.37 | AE77: =SUMIFS('Folha Forescast 3+9'!DP:DP,'Folha Forescast 3+9'!$I:$I,$C77) -> 246910.9 | AF77: =SUMIFS('Folha Forescast 3+9'!DQ:DQ,'Folha Forescast 3+9'!$I:$I,$C77) -> 250719.23 | AG77: =SUMIFS('Folha Forescast 3+9'!DR:DR,'Folha Forescast 3+9'!$I:$I,$C77) -> 284904.04 | AH77: =SUMIFS('Folha Forescast 3+9'!DS:DS,'Folha Forescast 3+9'!$I:$I,$C77) -> 299358.65 | AI77: =SUMIFS('Folha Forescast 3+9'!DT:DT,'Folha Forescast 3+9'!$I:$I,$C77) -> 299358.65 | AJ77: =SUMIFS('Folha Forescast 3+9'!DU:DU,'Folha Forescast 3+9'!$I:$I,$C77) -> 299358.65 | AK77: =SUMIFS('Folha Forescast 3+9'!DV:DV,'Folha Forescast 3+9'!$I:$I,$C77) -> 299358.65 | AL77: =SUMIFS('Folha Forescast 3+9'!DW:DW,'Folha Forescast 3+9'!$I:$I,$C77) -> 299358.65 | AM77: =SUM(AA77:AL77) -> 3297077.1
C78: % Alocada da Folha de Backoffice | D78: =D77/D$31 -> 0.35585881 | E78: =E77/E$31 -> 0.31226112 | F78: =F77/F$31 -> 0.35685014 | G78: =G77/G$53 -> 0.17651858 | I78: =I77/I$31 -> 0.37216436 | J78: =J77/J$31 -> 0.36036872 | K78: =K77/K$31 -> 0.36166147 | L78: =L77/L$31 -> 0.3646338 | P78: =P77/P$53 -> 0.19562602 | Q78: =Q77/Q$53 -> 0.20941904 | R78: =R77/R$53 -> 0.20571164 | S78: =S77/S$53 -> 0.20006197 | T78: =T77/T$53 -> 0.20850481 | U78: =U77/U$53 -> 0.19740737 | V78: =V77/V$53 -> 0.20565176 | W78: =W77/W$53 -> 0.20583141 | ... Y78: =Y77/Y$53 -> 0.19984804 | AA78: =AA77/AA$53 -> 0.16524129 | AB78: =AB77/AB$53 -> 0.14856935 | AC78: =AC77/AC$53 -> 0.14804001 | AD78: =AD77/AD$53 -> 0.1498892 | AE78: =AE77/AE$53 -> 0.15229592 | AF78: =AF77/AF$53 -> 0.15180958 | AG78: =AG77/AG$53 -> 0.18414398 | AH78: =AH77/AH$53 -> 0.19643398 | ... AM78: =AM77/AM$53 -> 0.17337229
A80: Produtos Inter | C80: Diretoria | D80: =SUMIFS('Rateio Fopag'!$F:$F,'Rateio Fopag'!$H:$H,MONTH(D$6),'Rateio Fopag'!$J:$J,'Breakdown Alocação de Despesas'!$C80) -> 831668.63 | E80: =SUMIFS('Rateio Fopag'!$F:$F,'Rateio Fopag'!$H:$H,MONTH(E$6),'Rateio Fopag'!$J:$J,'Breakdown Alocação de Despesas'!$C80) -> 831668.63 | F80: =SUMIFS('Rateio Fopag'!$F:$F,'Rateio Fopag'!$H:$H,MONTH(F$6),'Rateio Fopag'!$J:$J,'Breakdown Alocação de Despesas'!$C80) -> 831668.63 | G80: =SUM(D80:F80) -> 2495005.9 | I80: =SUMIFS('Rateio Folha'!$CU:$CU,'Rateio Folha'!$C:$C,MONTH('Breakdown Alocação de Despesas'!I$6)) -> 593666.67 | J80: =SUMIFS('Rateio Folha'!$CU:$CU,'Rateio Folha'!$C:$C,MONTH('Breakdown Alocação de Despesas'!J$6)) -> 593666.67 | K80: =SUMIFS('Rateio Folha'!$CU:$CU,'Rateio Folha'!$C:$C,MONTH('Breakdown Alocação de Despesas'!K$6)) -> 593666.67 | L80: =SUM(I80:K80) -> 1781000 | N80: =G80/L80-1 -> 0.40090168 | P80: =SUMIFS('Rateio Folha'!$CU:$CU,'Rateio Folha'!$C:$C,MONTH('Breakdown Alocação de Despesas'!P$6)) -> 593666.67 | Q80: =SUMIFS('Rateio Folha'!$CU:$CU,'Rateio Folha'!$C:$C,MONTH('Breakdown Alocação de Despesas'!Q$6)) -> 593666.67 | R80: =SUMIFS('Rateio Folha'!$CU:$CU,'Rateio Folha'!$C:$C,MONTH('Breakdown Alocação de Despesas'!R$6)) -> 593666.67 | S80: =SUMIFS('Rateio Folha'!$CU:$CU,'Rateio Folha'!$C:$C,MONTH('Breakdown Alocação de Despesas'!S$6)) -> 593666.67 | T80: =SUMIFS('Rateio Folha'!$CU:$CU,'Rateio Folha'!$C:$C,MONTH('Breakdown Alocação de Despesas'!T$6)) -> 593666.67 | U80: =SUMIFS('Rateio Folha'!$CU:$CU,'Rateio Folha'!$C:$C,MONTH('Breakdown Alocação de Despesas'!U$6)) -> 593666.67 | V80: =SUMIFS('Rateio Folha'!$CU:$CU,'Rateio Folha'!$C:$C,MONTH('Breakdown Alocação de Despesas'!V$6)) -> 593666.67 | W80: =SUMIFS('Rateio Folha'!$CU:$CU,'Rateio Folha'!$C:$C,MONTH('Breakdown Alocação de Despesas'!W$6)) -> 593666.67 | X80: =SUMIFS('Rateio Folha'!$CU:$CU,'Rateio Folha'!$C:$C,MONTH('Breakdown Alocação de Despesas'!X$6)) -> 593666.67 | Y80: =SUM(I80:K80,P80:X80) -> 7124000 | AA80: =SUMIFS('Folha Forescast 3+9'!DL:DL,'Folha Forescast 3+9'!$I:$I,$C80) -> 831668.63 | AB80: =SUMIFS('Folha Forescast 3+9'!DM:DM,'Folha Forescast 3+9'!$I:$I,$C80) -> 831668.63 | AC80: =SUMIFS('Folha Forescast 3+9'!DN:DN,'Folha Forescast 3+9'!$I:$I,$C80) -> 831668.63 | AD80: =SUMIFS('Folha Forescast 3+9'!DO:DO,'Folha Forescast 3+9'!$I:$I,$C80) -> 831668.63 | AE80: =SUMIFS('Folha Forescast 3+9'!DP:DP,'Folha Forescast 3+9'!$I:$I,$C80) -> 831668.63 | AF80: =SUMIFS('Folha Forescast 3+9'!DQ:DQ,'Folha Forescast 3+9'!$I:$I,$C80) -> 831668.63 | AG80: =SUMIFS('Folha Forescast 3+9'!DR:DR,'Folha Forescast 3+9'!$I:$I,$C80) -> 607767.44 | AH80: =SUMIFS('Folha Forescast 3+9'!DS:DS,'Folha Forescast 3+9'!$I:$I,$C80) -> 607767.44 | AI80: =SUMIFS('Folha Forescast 3+9'!DT:DT,'Folha Forescast 3+9'!$I:$I,$C80) -> 607767.44 | AJ80: =SUMIFS('Folha Forescast 3+9'!DU:DU,'Folha Forescast 3+9'!$I:$I,$C80) -> 607767.44 | AK80: =SUMIFS('Folha Forescast 3+9'!DV:DV,'Folha Forescast 3+9'!$I:$I,$C80) -> 607767.44 | AL80: =SUMIFS('Folha Forescast 3+9'!DW:DW,'Folha Forescast 3+9'!$I:$I,$C80) -> 607767.44 | AM80: =SUM(AA80:AL80) -> 8636616.4
C81: % Alocada da Folha de Backoffice | D81: =D80/D$31 -> 0.92049919 | E81: =E80/E$31 -> 0.99833512 | F81: =F80/F$31 -> 0.9376347 | G81: =G80/G$53 -> 0.49034728 | I81: =I80/I$31 -> 0.68098767 | J81: =J80/J$31 -> 0.65940397 | K81: =K80/K$31 -> 0.64753426 | L81: =L80/L$31 -> 0.66235455 | P81: =P80/P$53 -> 0.34260693 | Q81: =Q80/Q$53 -> 0.30281324 | R81: =R80/R$53 -> 0.2903663 | S81: =S80/S$53 -> 0.31842235 | T81: =T80/T$53 -> 0.28675995 | U81: =U80/U$53 -> 0.2838272 | V81: =V80/V$53 -> 0.28429653 | W81: =W80/W$53 -> 0.28123742 | ... Y81: =Y80/Y$53 -> 0.3111588 | AD81: =AD80/AD$53 -> 0.52667849 | AE81: =AE80/AE$53 -> 0.51297751 | AF81: =AF80/AF$53 -> 0.5035723 | AG81: =AG80/AG$53 -> 0.39282248 | AH81: =AH80/AH$53 -> 0.39880651 | AI81: =AI80/AI$53 -> 0.40609085 | AJ81: =AJ80/AJ$53 -> 0.40335172 | AK81: =AK80/AK$53 -> 0.40064928 | ... AM81: =AM80/AM$53 -> 0.45414467

Sheet Folha
K2: Salário Bruto Base | X2: Salário Bruto com Dissídio | AK2: IRRF | AX2: INSS Retido | BK2: 13º | BX2: Benefícios | CK2: Férias | CX2: Encargos s/ Salário Bruto | DK2: Custo Empresa | DX2: TOTAL ANO
K3: =$K$2 -> Salário Bruto Base | L3: =$K$2 -> Salário Bruto Base | M3: =$K$2 -> Salário Bruto Base | N3: =$K$2 -> Salário Bruto Base | O3: =$K$2 -> Salário Bruto Base | P3: =$K$2 -> Salário Bruto Base | Q3: =$K$2 -> Salário Bruto Base | R3: =$K$2 -> Salário Bruto Base | ... V3: =$K$2 -> Salário Bruto Base | X3: =$X$2 -> Salário Bruto com Dissídio | Y3: =$X$2 -> Salário Bruto com Dissídio | Z3: =$X$2 -> Salário Bruto com Dissídio | AA3: =$X$2 -> Salário Bruto com Dissídio | AB3: =$X$2 -> Salário Bruto com Dissídio | AC3: =$X$2 -> Salário Bruto com Dissídio | AD3: =$X$2 -> Salário Bruto com Dissídio | AE3: =$X$2 -> Salário Bruto com Dissídio | ... AI3: =$X$2 -> Salário Bruto com Dissídio | AK3: =$BK$2 -> 13º | AL3: =$BK$2 -> 13º | AM3: =$BK$2 -> 13º | AN3: =$BK$2 -> 13º | AO3: =$BK$2 -> 13º | AP3: =$BK$2 -> 13º | AQ3: =$BK$2 -> 13º | AR3: =$BK$2 -> 13º | ... AV3: =$BK$2 -> 13º | AX3: =$BK$2 -> 13º | AY3: =$BK$2 -> 13º | AZ3: =$BK$2 -> 13º | BA3: =$BK$2 -> 13º | BB3: =$BK$2 -> 13º | BC3: =$BK$2 -> 13º | BD3: =$BK$2 -> 13º | BE3: =$BK$2 -> 13º | ... BI3: =$BK$2 -> 13º | BK3: =$BK$2 -> 13º | BL3: =$BK$2 -> 13º | BM3: =$BK$2 -> 13º | BN3: =$BK$2 -> 13º | BO3: =$BK$2 -> 13º | BP3: =$BK$2 -> 13º | BQ3: =$BK$2 -> 13º | BR3: =$BK$2 -> 13º | ... BV3: =$BK$2 -> 13º | BX3: =$BX$2 -> Benefícios | BY3: =$BX$2 -> Benefícios | BZ3: =$BX$2 -> Benefícios | CA3: =$BX$2 -> Benefícios | CB3: =$BX$2 -> Benefícios | CC3: =$BX$2 -> Benefícios | CD3: =$BX$2 -> Benefícios | CE3: =$BX$2 -> Benefícios | ... CI3: =$BX$2 -> Benefícios | CK3: =$CK$2 -> Férias | CL3: =$CK$2 -> Férias | CM3: =$CK$2 -> Férias | CN3: =$CK$2 -> Férias | CO3: =$CK$2 -> Férias | CP3: =$CK$2 -> Férias | CQ3: =$CK$2 -> Férias | CR3: =$CK$2 -> Férias | ... CV3: =$CK$2 -> Férias | CX3: =$CX$2 -> Encargos s/ Salário Bruto | CY3: =$CX$2 -> Encargos s/ Salário Bruto | CZ3: =$CX$2 -> Encargos s/ Salário Bruto | DA3: =$CX$2 -> Encargos s/ Salário Bruto | DB3: =$CX$2 -> Encargos s/ Salário Bruto | DC3: =$CX$2 -> Encargos s/ Salário Bruto | DD3: =$CX$2 -> Encargos s/ Salário Bruto | DE3: =$CX$2 -> Encargos s/ Salário Bruto | ... DI3: =$CX$2 -> Encargos s/ Salário Bruto | DK3: =$DK$2 -> Custo Empresa | DL3: =$DK$2 -> Custo Empresa | DM3: =$DK$2 -> Custo Empresa | DN3: =$DK$2 -> Custo Empresa | DO3: =$DK$2 -> Custo Empresa | DP3: =$DK$2 -> Custo Empresa | DQ3: =$DK$2 -> Custo Empresa | DR3: =$DK$2 -> Custo Empresa | ... DV3: =$DK$2 -> Custo Empresa | DX3: =$DK$2 -> Custo Empresa | EE3: Fall Back Arrojado | EF3: Fall Back Agressivo
B4: Despesas com Pessoal (R$ mil) | K4: =SUM(K9,K11,K13,K15) -> 2538.6486 | L4: =SUM(L9,L11,L13,L15) -> 2571.5226 | M4: =SUM(M9,M11,M13,M15) -> 2649.0986 | N4: =SUM(N9,N11,N13,N15) -> 2619.4996 | O4: =SUM(O9,O11,O13,O15) -> 2664.0297 | P4: =SUM(P9,P11,P13,P15) -> 2670.8297 | Q4: =SUM(Q9,Q11,Q13,Q15) -> 2726.0847 | R4: =SUM(R9,R11,R13,R15) -> 2778.3547 | ... V4: =SUM(V9,V11,V13,V15) -> 2799.8547 | X4: =SUM(X9,X11,X13,X15) -> 2538.6486 | Y4: =SUM(Y9,Y11,Y13,Y15) -> 2571.5226 | Z4: =SUM(Z9,Z11,Z13,Z15) -> 2649.0986 | AA4: =SUM(AA9,AA11,AA13,AA15) -> 2619.4996 | AB4: =SUM(AB9,AB11,AB13,AB15) -> 2721.3929 | AC4: =SUM(AC9,AC11,AC13,AC15) -> 2728.286 | AD4: =SUM(AD9,AD11,AD13,AD15) -> 2784.6657 | AE4: =SUM(AE9,AE11,AE13,AE15) -> 2838.1826 | ... AI4: =SUM(AI9,AI11,AI13,AI15) -> 2859.7602 | AK4: =SUM(AK9,AK11,AK13,AK15) -> 355.58666 | AL4: =SUM(AL9,AL11,AL13,AL15) -> 358.73761 | AM4: =SUM(AM9,AM11,AM13,AM15) -> 366.05743 | AN4: =SUM(AN9,AN11,AN13,AN15) -> 370.931 | AO4: =SUM(AO9,AO11,AO13,AO15) -> 389.24147 | AP4: =SUM(AP9,AP11,AP13,AP15) -> 389.68917 | AQ4: =SUM(AQ9,AQ11,AQ13,AQ15) -> 394.6208 | AR4: =SUM(AR9,AR11,AR13,AR15) -> 404.80672 | ... AV4: =SUM(AV9,AV11,AV13,AV15) -> 405.17981 | AX4: =SUM(AX9,AX11,AX13,AX15) -> 95.548061 | AY4: =SUM(AY9,AY11,AY13,AY15) -> 98.636449 | AZ4: =SUM(AZ9,AZ11,AZ13,AZ15) -> 103.70783 | BA4: =SUM(BA9,BA11,BA13,BA15) -> 105.59069 | BB4: =SUM(BB9,BB11,BB13,BB15) -> 110.46051 | BC4: =SUM(BC9,BC11,BC13,BC15) -> 110.72554 | BD4: =SUM(BD9,BD11,BD13,BD15) -> 112.15732 | BE4: =SUM(BE9,BE11,BE13,BE15) -> 113.41841 | ... BI4: =SUM(BI9,BI11,BI13,BI15) -> 113.63927 | BK4: =SUM(BK9,BK11,BK13,BK15) -> 159.874 | BL4: =SUM(BL9,BL11,BL13,BL15) -> 163.54493 | BM4: =SUM(BM9,BM11,BM13,BM15) -> 170.25342 | BN4: =SUM(BN9,BN11,BN13,BN15) -> 173.70403 | BO4: =SUM(BO9,BO11,BO13,BO15) -> 183.12795 | BP4: =SUM(BP9,BP11,BP13,BP15) -> 183.89767 | BQ4: =SUM(BQ9,BQ11,BQ13,BQ15) -> 187.01091 | BR4: =SUM(BR9,BR11,BR13,BR15) -> 191.91496 | ... BV4: =SUM(BV9,BV11,BV13,BV15) -> 194.32445 | BX4: =SUM(BX9,BX11,BX13,BX15) -> 396.01538 | BY4: =SUM(BY9,BY11,BY13,BY15) -> 406.58873 | BZ4: =SUM(BZ9,BZ11,BZ13,BZ15) -> 426.64247 | CA4: =SUM(CA9,CA11,CA13,CA15) -> 432.78493 | CB4: =SUM(CB9,CB11,CB13,CB15) -> 443.85367 | CC4: =SUM(CC9,CC11,CC13,CC15) -> 443.98908 | CD4: =SUM(CD9,CD11,CD13,CD15) -> 448.87055 | CE4: =SUM(CE9,CE11,CE13,CE15) -> 451.65426 | ... CI4: =SUM(CI9,CI11,CI13,CI15) -> 451.76711 | CK4: =SUM(CK9,CK11,CK13,CK15) -> 216.52034 | CL4: =SUM(CL9,CL11,CL13,CL15) -> 221.41491 | CM4: =SUM(CM9,CM11,CM13,CM15) -> 230.56789 | CN4: =SUM(CN9,CN11,CN13,CN15) -> 235.16871 | CO4: =SUM(CO9,CO11,CO13,CO15) -> 247.94226 | CP4: =SUM(CP9,CP11,CP13,CP15) -> 248.96856 | CQ4: =SUM(CQ9,CQ11,CQ13,CQ15) -> 253.57788 | CR4: =SUM(CR9,CR11,CR13,CR15) -> 260.24995 | ... CV4: =SUM(CV9,CV11,CV13,CV15) -> 263.46261 | CX4: =SUM(CX9,CX11,CX13,CX15) -> 562.30115 | CY4: =SUM(CY9,CY11,CY13,CY15) -> 573.47831 | CZ4: =SUM(CZ9,CZ11,CZ13,CZ15) -> 593.90415 | DA4: =SUM(DA9,DA11,DA13,DA15) -> 604.41049 | DB4: =SUM(DB9,DB11,DB13,DB15) -> 633.10421 | DC4: =SUM(DC9,DC11,DC13,DC15) -> 635.44785 | DD4: =SUM(DD9,DD11,DD13,DD15) -> 644.92696 | DE4: =SUM(DE9,DE11,DE13,DE15) -> 659.8587 | ... DI4: =SUM(DI9,DI11,DI13,DI15) -> 667.19506 | DK4: =SUM(DK9,DK11,DK13,DK15) -> 3515.3299 | DL4: =SUM(DL9,DL11,DL13,DL15) -> 3578.5199 | DM4: =SUM(DM9,DM11,DM13,DM15) -> 3712.437 | DN4: =SUM(DN9,DN11,DN13,DN15) -> 3707.5382 | DO4: =SUM(DO9,DO11,DO13,DO15) -> 3871.3914 | DP4: =SUM(DP9,DP11,DP13,DP15) -> 3882.5595 | DQ4: =SUM(DQ9,DQ11,DQ13,DQ15) -> 3961.0224 | DR4: =SUM(DR9,DR11,DR13,DR15) -> 4043.8309 | ... DV4: =SUM(DV9,DV11,DV13,DV15) -> 4078.4798 | ED4: Tecnologia | EE4: =+SUMIFS($DX:$DX,$C:$C,EE$3,$H:$H,"TECH") -> 970172.88 | EF4: =+SUMIFS($DX:$DX,$C:$C,EF$3,$H:$H,"TECH") -> 1421920.3
B5: HC | K5: =SUM(K10,K12,K14) -> 157 | L5: =SUM(L10,L12,L14) -> 168 | M5: =SUM(M10,M12,M14) -> 178 | N5: =SUM(N10,N12,N14) -> 177 | O5: =SUM(O10,O12,O14) -> 177 | P5: =SUM(P10,P12,P14) -> 177 | Q5: =SUM(Q10,Q12,Q14) -> 178 | R5: =SUM(R10,R12,R14) -> 178 | ... V5: =SUM(V10,V12,V14) -> 178 | X5: =SUM(X10,X12,X14) -> 157 | Y5: =SUM(Y10,Y12,Y14) -> 161 | Z5: =SUM(Z10,Z12,Z14) -> 170 | AA5: =SUM(AA10,AA12,AA14) -> 171 | AB5: =SUM(AB10,AB12,AB14) -> 175 | AC5: =SUM(AC10,AC12,AC14) -> 175 | AD5: =SUM(AD10,AD12,AD14) -> 178 | AE5: =SUM(AE10,AE12,AE14) -> 178 | ... AI5: =SUM(AI10,AI12,AI14) -> 178 | AK5: =SUM(AK10,AK12,AK14) -> 122 | AL5: =SUM(AL10,AL12,AL14) -> 126 | AM5: =SUM(AM10,AM12,AM14) -> 133 | AN5: =SUM(AN10,AN12,AN14) -> 135 | AO5: =SUM(AO10,AO12,AO14) -> 137 | AP5: =SUM(AP10,AP12,AP14) -> 137 | AQ5: =SUM(AQ10,AQ12,AQ14) -> 138 | AR5: =SUM(AR10,AR12,AR14) -> 138 | ... AV5: =SUM(AV10,AV12,AV14) -> 138 | AX5: =SUM(AX10,AX12,AX14) -> 124 | AY5: =SUM(AY10,AY12,AY14) -> 128 | AZ5: =SUM(AZ10,AZ12,AZ14) -> 135 | BA5: =SUM(BA10,BA12,BA14) -> 137 | BB5: =SUM(BB10,BB12,BB14) -> 139 | BC5: =SUM(BC10,BC12,BC14) -> 139 | BD5: =SUM(BD10,BD12,BD14) -> 140 | BE5: =SUM(BE10,BE12,BE14) -> 140 | ... BI5: =SUM(BI10,BI12,BI14) -> 140 | BK5: =SUM(BK10,BK12,BK14) -> 120 | BL5: =SUM(BL10,BL12,BL14) -> 124 | BM5: =SUM(BM10,BM12,BM14) -> 131 | BN5: =SUM(BN10,BN12,BN14) -> 133 | BO5: =SUM(BO10,BO12,BO14) -> 135 | BP5: =SUM(BP10,BP12,BP14) -> 135 | BQ5: =SUM(BQ10,BQ12,BQ14) -> 136 | BR5: =SUM(BR10,BR12,BR14) -> 136 | ... BV5: =SUM(BV10,BV12,BV14) -> 136 | BX5: =SUM(BX10,BX12,BX14) -> 139 | BY5: =SUM(BY10,BY12,BY14) -> 143 | BZ5: =SUM(BZ10,BZ12,BZ14) -> 151 | CA5: =SUM(CA10,CA12,CA14) -> 153 | CB5: =SUM(CB10,CB12,CB14) -> 156 | CC5: =SUM(CC10,CC12,CC14) -> 156 | CD5: =SUM(CD10,CD12,CD14) -> 158 | CE5: =SUM(CE10,CE12,CE14) -> 158 | ... CI5: =SUM(CI10,CI12,CI14) -> 158 | CK5: =SUM(CK10,CK12,CK14) -> 135 | CL5: =SUM(CL10,CL12,CL14) -> 139 | CM5: =SUM(CM10,CM12,CM14) -> 147 | CN5: =SUM(CN10,CN12,CN14) -> 149 | CO5: =SUM(CO10,CO12,CO14) -> 152 | CP5: =SUM(CP10,CP12,CP14) -> 152 | CQ5: =SUM(CQ10,CQ12,CQ14) -> 154 | CR5: =SUM(CR10,CR12,CR14) -> 154 | ... CV5: =SUM(CV10,CV12,CV14) -> 154 | CX5: =SUM(CX10,CX12,CX14) -> 124 | CY5: =SUM(CY10,CY12,CY14) -> 128 | CZ5: =SUM(CZ10,CZ12,CZ14) -> 135 | DA5: =SUM(DA10,DA12,DA14) -> 137 | DB5: =SUM(DB10,DB12,DB14) -> 139 | DC5: =SUM(DC10,DC12,DC14) -> 139 | DD5: =SUM(DD10,DD12,DD14) -> 140 | DE5: =SUM(DE10,DE12,DE14) -> 140 | ... DI5: =SUM(DI10,DI12,DI14) -> 140 | DK5: =SUM(DK10,DK12,DK14) -> 157 | DL5: =SUM(DL10,DL12,DL14) -> 161 | DM5: =SUM(DM10,DM12,DM14) -> 170 | DN5: =SUM(DN10,DN12,DN14) -> 171 | DO5: =SUM(DO10,DO12,DO14) -> 175 | DP5: =SUM(DP10,DP12,DP14) -> 175 | DQ5: =SUM(DQ10,DQ12,DQ14) -> 178 | DR5: =SUM(DR10,DR12,DR14) -> 178 | ... DV5: =SUM(DV10,DV12,DV14) -> 178 | ED5: Maurício (EUA) | EE5: =+SUMIFS($DX:$DX,$C:$C,EE$3,$D:$D,"Maurício (mensal + semestral)") -> 1828961.2 | EF5: =+SUMIFS($DX:$DX,$C:$C,EF$3,$D:$D,"Maurício (mensal + semestral)") -> 1828961.2
B6: Receit a Bruta LTM/HC | K6: =K8/K5 -> 987.66846 | L6: =L8/L5 -> 912.75439 | M6: =M8/M5 -> 916.64968 | N6: =N8/N5 -> 935.70039 | O6: =O8/O5 -> 974.66057 | P6: =P8/P5 -> 963.77634 | Q6: =Q8/Q5 -> 980.6066 | R6: =R8/R5 -> 1010.5213 | ... V6: =V8/V5 -> 1021.0497 | ED6: Produtos | EE6: =+SUMIFS($DX:$DX,$C:$C,EE$3,$D:$D,"Amit") -> 0 | EF6: =+SUMIFS($DX:$DX,$C:$C,EF$3,$D:$D,"Amit") -> 540000
B7: Custo Empresa/HC | K7: =DK4/K5 -> 22.390636 | L7: =DL4/L5 -> 21.300714 | M7: =DM4/M5 -> 20.856387 | N7: =DN4/N5 -> 20.946543 | O7: =DO4/O5 -> 21.872268 | P7: =DP4/P5 -> 21.935365 | Q7: =DQ4/Q5 -> 22.252935 | R7: =DR4/R5 -> 22.718151 | ... V7: =DV4/V5 -> 22.912808 | AK7: =AK4/AK5 -> 2.9146448 | AL7: =AL4/AL5 -> 2.8471239 | AM7: =AM4/AM5 -> 2.7523115 | AN7: =AN4/AN5 -> 2.747637 | AO7: =AO4/AO5 -> 2.8411786 | AP7: =AP4/AP5 -> 2.8444465 | AQ7: =AQ4/AQ5 -> 2.859571 | AR7: =AR4/AR5 -> 2.933382 | ... AV7: =AV4/AV5 -> 2.9360856 | AX7: =AX4/AX5 -> 0.77054888 | AY7: =AY4/AY5 -> 0.77059726 | AZ7: =AZ4/AZ5 -> 0.76820612 | BA7: =BA4/BA5 -> 0.770735 | BB7: =BB4/BB5 -> 0.79467995 | BC7: =BC4/BC5 -> 0.79658663 | BD7: =BD4/BD5 -> 0.80112368 | BE7: =BE4/BE5 -> 0.81013149 | ... BI7: =BI4/BI5 -> 0.81170904 | BK7: =BK4/BK5 -> 1.3322833 | BL7: =BL4/BL5 -> 1.3189107 | BM7: =BM4/BM5 -> 1.2996444 | BN7: =BN4/BN5 -> 1.3060453 | BO7: =BO4/BO5 -> 1.3565033 | BP7: =BP4/BP5 -> 1.362205 | BQ7: =BQ4/BQ5 -> 1.3750802 | BR7: =BR4/BR5 -> 1.4111394 | ... BV7: =BV4/BV5 -> 1.4288563 | BX7: =BX4/BX5 -> 2.8490315 | BY7: =BY4/BY5 -> 2.8432778 | BZ7: =BZ4/BZ5 -> 2.8254468 | CA7: =CA4/CA5 -> 2.8286597 | CB7: =CB4/CB5 -> 2.8452159 | CC7: =CC4/CC5 -> 2.8460839 | CD7: =CD4/CD5 -> 2.8409528 | CE7: =CE4/CE5 -> 2.8585713 | ... CI7: =CI4/CI5 -> 2.8592855 | CK7: =CK4/CK5 -> 1.6038543 | CL7: =CL4/CL5 -> 1.592913 | CM7: =CM4/CM5 -> 1.5684891 | CN7: =CN4/CN5 -> 1.5783135 | CO7: =CO4/CO5 -> 1.6311991 | CP7: =CP4/CP5 -> 1.6379511 | CQ7: =CQ4/CQ5 -> 1.6466096 | CR7: =CR4/CR5 -> 1.6899347 | ... CV7: =CV4/CV5 -> 1.7107961 | CX7: =CX4/CX5 -> 4.5346867 | CY7: =CY4/CY5 -> 4.4802993 | CZ7: =CZ4/CZ5 -> 4.39929 | DA7: =DA4/DA5 -> 4.4117554 | DB7: =DB4/DB5 -> 4.5547065 | DC7: =DC4/DC5 -> 4.5715672 | DD7: =DD4/DD5 -> 4.6066211 | DE7: =DE4/DE5 -> 4.7132764 | ... DI7: =DI4/DI5 -> 4.765679 | DK7: =DK4/DK5 -> 22.390636 | DL7: =DL4/DL5 -> 22.226832 | DM7: =DM4/DM5 -> 21.837865 | DN7: =DN4/DN5 -> 21.68151 | DO7: =DO4/DO5 -> 22.122237 | DP7: =DP4/DP5 -> 22.186055 | DQ7: =DQ4/DQ5 -> 22.252935 | DR7: =DR4/DR5 -> 22.718151 | ... DV7: =DV4/DV5 -> 22.912808 | ED7: Patrocínio | EE7: =+SUMIFS($DX:$DX,$C:$C,EE$3,$D:$D,518) -> 540232.55 | EF7: =+SUMIFS($DX:$DX,$C:$C,EF$3,$D:$D,518) -> 540232.55
B8: Receita LTM | K8: 155063.95 | L8: 153342.74 | M8: 163163.64 | N8: 165618.97 | O8: 172514.92 | P8: 170588.41 | Q8: 174547.97 | R8: 179872.8 | S8: 178868.38 | T8: 177699.53 | U8: 181824.04 | V8: 181746.85 | ED8: Eventos | EE8: =+SUMIFS($DX:$DX,$C:$C,EE$3,$H:$H,"PRODUTOS EVENTOS") -> 721645.61 | EF8: =+SUMIFS($DX:$DX,$C:$C,EF$3,$H:$H,"PRODUTOS EVENTOS") -> 882302.07
B9: Fopag | K9: =(SUMIFS(K$19:K$211,$F$19:$F$211,$B9))/1000 -> 1503.0685 | L9: =(SUMIFS(L$19:L$211,$F$19:$F$211,$B9))/1000 -> 1535.9425 | M9: =(SUMIFS(M$19:M$211,$F$19:$F$211,$B9))/1000 -> 1598.5185 | N9: =(SUMIFS(N$19:N$211,$F$19:$F$211,$B9))/1000 -> 1629.4195 | O9: =(SUMIFS(O$19:O$211,$F$19:$F$211,$B9))/1000 -> 1658.9496 | P9: =(SUMIFS(P$19:P$211,$F$19:$F$211,$B9))/1000 -> 1665.7496 | Q9: =(SUMIFS(Q$19:Q$211,$F$19:$F$211,$B9))/1000 -> 1698.0046 | R9: =(SUMIFS(R$19:R$211,$F$19:$F$211,$B9))/1000 -> 1742.2746 | ... V9: =(SUMIFS(V$19:V$211,$F$19:$F$211,$B9))/1000 -> 1763.7746 | X9: =(SUMIFS(X$19:X$211,$F$19:$F$211,$B9))/1000 -> 1503.0685 | Y9: =(SUMIFS(Y$19:Y$211,$F$19:$F$211,$B9))/1000 -> 1535.9425 | Z9: =(SUMIFS(Z$19:Z$211,$F$19:$F$211,$B9))/1000 -> 1598.5185 | AA9: =(SUMIFS(AA$19:AA$211,$F$19:$F$211,$B9))/1000 -> 1629.4195 | AB9: =(SUMIFS(AB$19:AB$211,$F$19:$F$211,$B9))/1000 -> 1716.3128 | AC9: =(SUMIFS(AC$19:AC$211,$F$19:$F$211,$B9))/1000 -> 1723.2059 | AD9: =(SUMIFS(AD$19:AD$211,$F$19:$F$211,$B9))/1000 -> 1756.5856 | AE9: =(SUMIFS(AE$19:AE$211,$F$19:$F$211,$B9))/1000 -> 1802.1025 | ... AI9: =(SUMIFS(AI$19:AI$211,$F$19:$F$211,$B9))/1000 -> 1823.6801 | AK9: =(SUMIFS(AK$19:AK$211,$F$19:$F$211,$B9))/1000 -> 260.90837 | AL9: =(SUMIFS(AL$19:AL$211,$F$19:$F$211,$B9))/1000 -> 264.05931 | AM9: =(SUMIFS(AM$19:AM$211,$F$19:$F$211,$B9))/1000 -> 271.37913 | AN9: =(SUMIFS(AN$19:AN$211,$F$19:$F$211,$B9))/1000 -> 276.2527 | AO9: =(SUMIFS(AO$19:AO$211,$F$19:$F$211,$B9))/1000 -> 294.56317 | AP9: =(SUMIFS(AP$19:AP$211,$F$19:$F$211,$B9))/1000 -> 295.01087 | AQ9: =(SUMIFS(AQ$19:AQ$211,$F$19:$F$211,$B9))/1000 -> 299.9425 | AR9: =(SUMIFS(AR$19:AR$211,$F$19:$F$211,$B9))/1000 -> 310.12842 | ... AV9: =(SUMIFS(AV$19:AV$211,$F$19:$F$211,$B9))/1000 -> 310.50151 | AX9: =(SUMIFS(AX$19:AX$211,$F$19:$F$211,$B9))/1000 -> 87.934986 | AY9: =(SUMIFS(AY$19:AY$211,$F$19:$F$211,$B9))/1000 -> 91.023374 | AZ9: =(SUMIFS(AZ$19:AZ$211,$F$19:$F$211,$B9))/1000 -> 96.094751 | BA9: =(SUMIFS(BA$19:BA$211,$F$19:$F$211,$B9))/1000 -> 97.977619 | BB9: =(SUMIFS(BB$19:BB$211,$F$19:$F$211,$B9))/1000 -> 102.84744 | BC9: =(SUMIFS(BC$19:BC$211,$F$19:$F$211,$B9))/1000 -> 103.11247 | BD9: =(SUMIFS(BD$19:BD$211,$F$19:$F$211,$B9))/1000 -> 104.54424 | BE9: =(SUMIFS(BE$19:BE$211,$F$19:$F$211,$B9))/1000 -> 105.80533 | ... BI9: =(SUMIFS(BI$19:BI$211,$F$19:$F$211,$B9))/1000 -> 106.02619 | BK9: =(SUMIFS(BK$19:BK$211,$F$19:$F$211,$B9))/1000 -> 159.874 | BL9: =(SUMIFS(BL$19:BL$211,$F$19:$F$211,$B9))/1000 -> 163.54493 | BM9: =(SUMIFS(BM$19:BM$211,$F$19:$F$211,$B9))/1000 -> 170.25342 | BN9: =(SUMIFS(BN$19:BN$211,$F$19:$F$211,$B9))/1000 -> 173.70403 | BO9: =(SUMIFS(BO$19:BO$211,$F$19:$F$211,$B9))/1000 -> 183.12795 | BP9: =(SUMIFS(BP$19:BP$211,$F$19:$F$211,$B9))/1000 -> 183.89767 | BQ9: =(SUMIFS(BQ$19:BQ$211,$F$19:$F$211,$B9))/1000 -> 187.01091 | BR9: =(SUMIFS(BR$19:BR$211,$F$19:$F$211,$B9))/1000 -> 191.91496 | ... BV9: =(SUMIFS(BV$19:BV$211,$F$19:$F$211,$B9))/1000 -> 194.32445 | BX9: =(SUMIFS(BX$19:BX$211,$F$19:$F$211,$B9))/1000 -> 348.01538 | BY9: =(SUMIFS(BY$19:BY$211,$F$19:$F$211,$B9))/1000 -> 358.58873 | BZ9: =(SUMIFS(BZ$19:BZ$211,$F$19:$F$211,$B9))/1000 -> 378.64247 | CA9: =(SUMIFS(CA$19:CA$211,$F$19:$F$211,$B9))/1000 -> 384.78493 | CB9: =(SUMIFS(CB$19:CB$211,$F$19:$F$211,$B9))/1000 -> 395.85367 | CC9: =(SUMIFS(CC$19:CC$211,$F$19:$F$211,$B9))/1000 -> 395.98908 | CD9: =(SUMIFS(CD$19:CD$211,$F$19:$F$211,$B9))/1000 -> 400.87055 | CE9: =(SUMIFS(CE$19:CE$211,$F$19:$F$211,$B9))/1000 -> 403.65426 | ... CI9: =(SUMIFS(CI$19:CI$211,$F$19:$F$211,$B9))/1000 -> 403.76711 | CK9: =(SUMIFS(CK$19:CK$211,$F$19:$F$211,$B9))/1000 -> 216.52034 | CL9: =(SUMIFS(CL$19:CL$211,$F$19:$F$211,$B9))/1000 -> 221.41491 | CM9: =(SUMIFS(CM$19:CM$211,$F$19:$F$211,$B9))/1000 -> 230.56789 | CN9: =(SUMIFS(CN$19:CN$211,$F$19:$F$211,$B9))/1000 -> 235.16871 | CO9: =(SUMIFS(CO$19:CO$211,$F$19:$F$211,$B9))/1000 -> 247.94226 | CP9: =(SUMIFS(CP$19:CP$211,$F$19:$F$211,$B9))/1000 -> 248.96856 | CQ9: =(SUMIFS(CQ$19:CQ$211,$F$19:$F$211,$B9))/1000 -> 253.57788 | CR9: =(SUMIFS(CR$19:CR$211,$F$19:$F$211,$B9))/1000 -> 260.24995 | ... CV9: =(SUMIFS(CV$19:CV$211,$F$19:$F$211,$B9))/1000 -> 263.46261 | CX9: =(SUMIFS(CX$19:CX$211,$F$19:$F$211,$B9))/1000 -> 486.63448 | CY9: =(SUMIFS(CY$19:CY$211,$F$19:$F$211,$B9))/1000 -> 497.81164 | CZ9: =(SUMIFS(CZ$19:CZ$211,$F$19:$F$211,$B9))/1000 -> 518.23748 | DA9: =(SUMIFS(DA$19:DA$211,$F$19:$F$211,$B9))/1000 -> 528.74382 | DB9: =(SUMIFS(DB$19:DB$211,$F$19:$F$211,$B9))/1000 -> 557.43754 | DC9: =(SUMIFS(DC$19:DC$211,$F$19:$F$211,$B9))/1000 -> 559.78118 | DD9: =(SUMIFS(DD$19:DD$211,$F$19:$F$211,$B9))/1000 -> 569.26029 | DE9: =(SUMIFS(DE$19:DE$211,$F$19:$F$211,$B9))/1000 -> 584.19203 | ... DI9: =(SUMIFS(DI$19:DI$211,$F$19:$F$211,$B9))/1000 -> 591.5284 | DK9: =(SUMIFS(DK$19:DK$211,$F$19:$F$211,$B9))/1000 -> 2356.0831 | DL9: =(SUMIFS(DL$19:DL$211,$F$19:$F$211,$B9))/1000 -> 2419.2732 | DM9: =(SUMIFS(DM$19:DM$211,$F$19:$F$211,$B9))/1000 -> 2538.1902 | DN9: =(SUMIFS(DN$19:DN$211,$F$19:$F$211,$B9))/1000 -> 2593.7914 | DO9: =(SUMIFS(DO$19:DO$211,$F$19:$F$211,$B9))/1000 -> 2742.6446 | DP9: =(SUMIFS(DP$19:DP$211,$F$19:$F$211,$B9))/1000 -> 2753.8128 | DQ9: =(SUMIFS(DQ$19:DQ$211,$F$19:$F$211,$B9))/1000 -> 2809.2756 | DR9: =(SUMIFS(DR$19:DR$211,$F$19:$F$211,$B9))/1000 -> 2884.0841 | ... DV9: =(SUMIFS(DV$19:DV$211,$F$19:$F$211,$B9))/1000 -> 2918.733 | ED9: Consulting | EE9: =+SUMIFS($DX:$DX,$C:$C,EE$3,$H:$H,"PRODUTOS CONSULTING") -> 269836.56 | EF9: =+SUMIFS($DX:$DX,$C:$C,EF$3,$H:$H,"PRODUTOS CONSULTING") -> 404754.84
B10: HC | K10: =COUNTIFS(K$19:K$211,"<>0",$E$19:$E$211,"CLT")+COUNTIFS(K$19:K$211,"<>0",$E$19:$E$211,"Estágio")+COUNTIFS(K$19:K$211,"<>0",$E$19:$E$211,"Jovem Aprendiz") -> 135 | L10: =COUNTIFS(L$19:L$211,"<>0",$E$19:$E$211,"CLT")+COUNTIFS(L$19:L$211,"<>0",$E$19:$E$211,"Estágio")+COUNTIFS(L$19:L$211,"<>0",$E$19:$E$211,"Jovem Aprendiz") -> 143 | M10: =COUNTIFS(M$19:M$211,"<>0",$E$19:$E$211,"CLT")+COUNTIFS(M$19:M$211,"<>0",$E$19:$E$211,"Estágio")+COUNTIFS(M$19:M$211,"<>0",$E$19:$E$211,"Jovem Aprendiz") -> 153 | N10: =COUNTIFS(N$19:N$211,"<>0",$E$19:$E$211,"CLT")+COUNTIFS(N$19:N$211,"<>0",$E$19:$E$211,"Estágio")+COUNTIFS(N$19:N$211,"<>0",$E$19:$E$211,"Jovem Aprendiz") -> 153 | O10: =COUNTIFS(O$19:O$211,"<>0",$E$19:$E$211,"CLT")+COUNTIFS(O$19:O$211,"<>0",$E$19:$E$211,"Estágio")+COUNTIFS(O$19:O$211,"<>0",$E$19:$E$211,"Jovem Aprendiz") -> 153 | P10: =COUNTIFS(P$19:P$211,"<>0",$E$19:$E$211,"CLT")+COUNTIFS(P$19:P$211,"<>0",$E$19:$E$211,"Estágio")+COUNTIFS(P$19:P$211,"<>0",$E$19:$E$211,"Jovem Aprendiz") -> 153 | Q10: =COUNTIFS(Q$19:Q$211,"<>0",$E$19:$E$211,"CLT")+COUNTIFS(Q$19:Q$211,"<>0",$E$19:$E$211,"Estágio")+COUNTIFS(Q$19:Q$211,"<>0",$E$19:$E$211,"Jovem Aprendiz") -> 154 | R10: =COUNTIFS(R$19:R$211,"<>0",$E$19:$E$211,"CLT")+COUNTIFS(R$19:R$211,"<>0",$E$19:$E$211,"Estágio")+COUNTIFS(R$19:R$211,"<>0",$E$19:$E$211,"Jovem Aprendiz") -> 154 | ... V10: =COUNTIFS(V$19:V$211,"<>0",$E$19:$E$211,"CLT")+COUNTIFS(V$19:V$211,"<>0",$E$19:$E$211,"Estágio")+COUNTIFS(V$19:V$211,"<>0",$E$19:$E$211,"Jovem Aprendiz") -> 154 | X10: =COUNTIFS(X$19:X$211,"<>0",$E$19:$E$211,"CLT")+COUNTIFS(X$19:X$211,"<>0",$E$19:$E$211,"Estágio")+COUNTIFS(X$19:X$211,"<>0",$E$19:$E$211,"Jovem Aprendiz") -> 135 | Y10: =COUNTIFS(Y$19:Y$211,"<>0",$E$19:$E$211,"CLT")+COUNTIFS(Y$19:Y$211,"<>0",$E$19:$E$211,"Estágio")+COUNTIFS(Y$19:Y$211,"<>0",$E$19:$E$211,"Jovem Aprendiz") -> 139 | Z10: =COUNTIFS(Z$19:Z$211,"<>0",$E$19:$E$211,"CLT")+COUNTIFS(Z$19:Z$211,"<>0",$E$19:$E$211,"Estágio")+COUNTIFS(Z$19:Z$211,"<>0",$E$19:$E$211,"Jovem Aprendiz") -> 147 | AA10: =COUNTIFS(AA$19:AA$211,"<>0",$E$19:$E$211,"CLT")+COUNTIFS(AA$19:AA$211,"<>0",$E$19:$E$211,"Estágio")+COUNTIFS(AA$19:AA$211,"<>0",$E$19:$E$211,"Jovem Aprendiz") -> 149 | AB10: =COUNTIFS(AB$19:AB$211,"<>0",$E$19:$E$211,"CLT")+COUNTIFS(AB$19:AB$211,"<>0",$E$19:$E$211,"Estágio")+COUNTIFS(AB$19:AB$211,"<>0",$E$19:$E$211,"Jovem Aprendiz") -> 152 | AC10: =COUNTIFS(AC$19:AC$211,"<>0",$E$19:$E$211,"CLT")+COUNTIFS(AC$19:AC$211,"<>0",$E$19:$E$211,"Estágio")+COUNTIFS(AC$19:AC$211,"<>0",$E$19:$E$211,"Jovem Aprendiz") -> 152 | AD10: =COUNTIFS(AD$19:AD$211,"<>0",$E$19:$E$211,"CLT")+COUNTIFS(AD$19:AD$211,"<>0",$E$19:$E$211,"Estágio")+COUNTIFS(AD$19:AD$211,"<>0",$E$19:$E$211,"Jovem Aprendiz") -> 154 | AE10: =COUNTIFS(AE$19:AE$211,"<>0",$E$19:$E$211,"CLT")+COUNTIFS(AE$19:AE$211,"<>0",$E$19:$E$211,"Estágio")+COUNTIFS(AE$19:AE$211,"<>0",$E$19:$E$211,"Jovem Aprendiz") -> 154 | ... AI10: =COUNTIFS(AI$19:AI$211,"<>0",$E$19:$E$211,"CLT")+COUNTIFS(AI$19:AI$211,"<>0",$E$19:$E$211,"Estágio")+COUNTIFS(AI$19:AI$211,"<>0",$E$19:$E$211,"Jovem Aprendiz") -> 154 | AK10: =COUNTIFS(AK$19:AK$211,"<>0",$E$19:$E$211,"CLT")+COUNTIFS(AK$19:AK$211,"<>0",$E$19:$E$211,"Estágio")+COUNTIFS(AK$19:AK$211,"<>0",$E$19:$E$211,"Jovem Aprendiz") -> 118 | AL10: =COUNTIFS(AL$19:AL$211,"<>0",$E$19:$E$211,"CLT")+COUNTIFS(AL$19:AL$211,"<>0",$E$19:$E$211,"Estágio")+COUNTIFS(AL$19:AL$211,"<>0",$E$19:$E$211,"Jovem Aprendiz") -> 122 | AM10: =COUNTIFS(AM$19:AM$211,"<>0",$E$19:$E$211,"CLT")+COUNTIFS(AM$19:AM$211,"<>0",$E$19:$E$211,"Estágio")+COUNTIFS(AM$19:AM$211,"<>0",$E$19:$E$211,"Jovem Aprendiz") -> 129 | AN10: =COUNTIFS(AN$19:AN$211,"<>0",$E$19:$E$211,"CLT")+COUNTIFS(AN$19:AN$211,"<>0",$E$19:$E$211,"Estágio")+COUNTIFS(AN$19:AN$211,"<>0",$E$19:$E$211,"Jovem Aprendiz") -> 131 | AO10: =COUNTIFS(AO$19:AO$211,"<>0",$E$19:$E$211,"CLT")+COUNTIFS(AO$19:AO$211,"<>0",$E$19:$E$211,"Estágio")+COUNTIFS(AO$19:AO$211,"<>0",$E$19:$E$211,"Jovem Aprendiz") -> 133 | AP10: =COUNTIFS(AP$19:AP$211,"<>0",$E$19:$E$211,"CLT")+COUNTIFS(AP$19:AP$211,"<>0",$E$19:$E$211,"Estágio")+COUNTIFS(AP$19:AP$211,"<>0",$E$19:$E$211,"Jovem Aprendiz") -> 133 | AQ10: =COUNTIFS(AQ$19:AQ$211,"<>0",$E$19:$E$211,"CLT")+COUNTIFS(AQ$19:AQ$211,"<>0",$E$19:$E$211,"Estágio")+COUNTIFS(AQ$19:AQ$211,"<>0",$E$19:$E$211,"Jovem Aprendiz") -> 134 | AR10: =COUNTIFS(AR$19:AR$211,"<>0",$E$19:$E$211,"CLT")+COUNTIFS(AR$19:AR$211,"<>0",$E$19:$E$211,"Estágio")+COUNTIFS(AR$19:AR$211,"<>0",$E$19:$E$211,"Jovem Aprendiz") -> 134 | ... AV10: =COUNTIFS(AV$19:AV$211,"<>0",$E$19:$E$211,"CLT")+COUNTIFS(AV$19:AV$211,"<>0",$E$19:$E$211,"Estágio")+COUNTIFS(AV$19:AV$211,"<>0",$E$19:$E$211,"Jovem Aprendiz") -> 134 | AX10: =COUNTIFS(AX$19:AX$211,"<>0",$E$19:$E$211,"CLT")+COUNTIFS(AX$19:AX$211,"<>0",$E$19:$E$211,"Estágio")+COUNTIFS(AX$19:AX$211,"<>0",$E$19:$E$211,"Jovem Aprendiz") -> 120 | AY10: =COUNTIFS(AY$19:AY$211,"<>0",$E$19:$E$211,"CLT")+COUNTIFS(AY$19:AY$211,"<>0",$E$19:$E$211,"Estágio")+COUNTIFS(AY$19:AY$211,"<>0",$E$19:$E$211,"Jovem Aprendiz") -> 124 | AZ10: =COUNTIFS(AZ$19:AZ$211,"<>0",$E$19:$E$211,"CLT")+COUNTIFS(AZ$19:AZ$211,"<>0",$E$19:$E$211,"Estágio")+COUNTIFS(AZ$19:AZ$211,"<>0",$E$19:$E$211,"Jovem Aprendiz") -> 131 | BA10: =COUNTIFS(BA$19:BA$211,"<>0",$E$19:$E$211,"CLT")+COUNTIFS(BA$19:BA$211,"<>0",$E$19:$E$211,"Estágio")+COUNTIFS(BA$19:BA$211,"<>0",$E$19:$E$211,"Jovem Aprendiz") -> 133 | BB10: =COUNTIFS(BB$19:BB$211,"<>0",$E$19:$E$211,"CLT")+COUNTIFS(BB$19:BB$211,"<>0",$E$19:$E$211,"Estágio")+COUNTIFS(BB$19:BB$211,"<>0",$E$19:$E$211,"Jovem Aprendiz") -> 135 | BC10: =COUNTIFS(BC$19:BC$211,"<>0",$E$19:$E$211,"CLT")+COUNTIFS(BC$19:BC$211,"<>0",$E$19:$E$211,"Estágio")+COUNTIFS(BC$19:BC$211,"<>0",$E$19:$E$211,"Jovem Aprendiz") -> 135 | BD10: =COUNTIFS(BD$19:BD$211,"<>0",$E$19:$E$211,"CLT")+COUNTIFS(BD$19:BD$211,"<>0",$E$19:$E$211,"Estágio")+COUNTIFS(BD$19:BD$211,"<>0",$E$19:$E$211,"Jovem Aprendiz") -> 136 | BE10: =COUNTIFS(BE$19:BE$211,"<>0",$E$19:$E$211,"CLT")+COUNTIFS(BE$19:BE$211,"<>0",$E$19:$E$211,"Estágio")+COUNTIFS(BE$19:BE$211,"<>0",$E$19:$E$211,"Jovem Aprendiz") -> 136 | ... BI10: =COUNTIFS(BI$19:BI$211,"<>0",$E$19:$E$211,"CLT")+COUNTIFS(BI$19:BI$211,"<>0",$E$19:$E$211,"Estágio")+COUNTIFS(BI$19:BI$211,"<>0",$E$19:$E$211,"Jovem Aprendiz") -> 136 | BK10: =COUNTIFS(BK$19:BK$211,"<>0",$E$19:$E$211,"CLT")+COUNTIFS(BK$19:BK$211,"<>0",$E$19:$E$211,"Estágio")+COUNTIFS(BK$19:BK$211,"<>0",$E$19:$E$211,"Jovem Aprendiz") -> 120 | BL10: =COUNTIFS(BL$19:BL$211,"<>0",$E$19:$E$211,"CLT")+COUNTIFS(BL$19:BL$211,"<>0",$E$19:$E$211,"Estágio")+COUNTIFS(BL$19:BL$211,"<>0",$E$19:$E$211,"Jovem Aprendiz") -> 124 | BM10: =COUNTIFS(BM$19:BM$211,"<>0",$E$19:$E$211,"CLT")+COUNTIFS(BM$19:BM$211,"<>0",$E$19:$E$211,"Estágio")+COUNTIFS(BM$19:BM$211,"<>0",$E$19:$E$211,"Jovem Aprendiz") -> 131 | BN10: =COUNTIFS(BN$19:BN$211,"<>0",$E$19:$E$211,"CLT")+COUNTIFS(BN$19:BN$211,"<>0",$E$19:$E$211,"Estágio")+COUNTIFS(BN$19:BN$211,"<>0",$E$19:$E$211,"Jovem Aprendiz") -> 133 | BO10: =COUNTIFS(BO$19:BO$211,"<>0",$E$19:$E$211,"CLT")+COUNTIFS(BO$19:BO$211,"<>0",$E$19:$E$211,"Estágio")+COUNTIFS(BO$19:BO$211,"<>0",$E$19:$E$211,"Jovem Aprendiz") -> 135 | BP10: =COUNTIFS(BP$19:BP$211,"<>0",$E$19:$E$211,"CLT")+COUNTIFS(BP$19:BP$211,"<>0",$E$19:$E$211,"Estágio")+COUNTIFS(BP$19:BP$211,"<>0",$E$19:$E$211,"Jovem Aprendiz") -> 135 | BQ10: =COUNTIFS(BQ$19:BQ$211,"<>0",$E$19:$E$211,"CLT")+COUNTIFS(BQ$19:BQ$211,"<>0",$E$19:$E$211,"Estágio")+COUNTIFS(BQ$19:BQ$211,"<>0",$E$19:$E$211,"Jovem Aprendiz") -> 136 | BR10: =COUNTIFS(BR$19:BR$211,"<>0",$E$19:$E$211,"CLT")+COUNTIFS(BR$19:BR$211,"<>0",$E$19:$E$211,"Estágio")+COUNTIFS(BR$19:BR$211,"<>0",$E$19:$E$211,"Jovem Aprendiz") -> 136 | ... BV10: =COUNTIFS(BV$19:BV$211,"<>0",$E$19:$E$211,"CLT")+COUNTIFS(BV$19:BV$211,"<>0",$E$19:$E$211,"Estágio")+COUNTIFS(BV$19:BV$211,"<>0",$E$19:$E$211,"Jovem Aprendiz") -> 136 | BX10: =COUNTIFS(BX$19:BX$211,"<>0",$E$19:$E$211,"CLT")+COUNTIFS(BX$19:BX$211,"<>0",$E$19:$E$211,"Estágio")+COUNTIFS(BX$19:BX$211,"<>0",$E$19:$E$211,"Jovem Aprendiz") -> 135 | BY10: =COUNTIFS(BY$19:BY$211,"<>0",$E$19:$E$211,"CLT")+COUNTIFS(BY$19:BY$211,"<>0",$E$19:$E$211,"Estágio")+COUNTIFS(BY$19:BY$211,"<>0",$E$19:$E$211,"Jovem Aprendiz") -> 139 | BZ10: =COUNTIFS(BZ$19:BZ$211,"<>0",$E$19:$E$211,"CLT")+COUNTIFS(BZ$19:BZ$211,"<>0",$E$19:$E$211,"Estágio")+COUNTIFS(BZ$19:BZ$211,"<>0",$E$19:$E$211,"Jovem Aprendiz") -> 147 | CA10: =COUNTIFS(CA$19:CA$211,"<>0",$E$19:$E$211,"CLT")+COUNTIFS(CA$19:CA$211,"<>0",$E$19:$E$211,"Estágio")+COUNTIFS(CA$19:CA$211,"<>0",$E$19:$E$211,"Jovem Aprendiz") -> 149 | CB10: =COUNTIFS(CB$19:CB$211,"<>0",$E$19:$E$211,"CLT")+COUNTIFS(CB$19:CB$211,"<>0",$E$19:$E$211,"Estágio")+COUNTIFS(CB$19:CB$211,"<>0",$E$19:$E$211,"Jovem Aprendiz") -> 152 | CC10: =COUNTIFS(CC$19:CC$211,"<>0",$E$19:$E$211,"CLT")+COUNTIFS(CC$19:CC$211,"<>0",$E$19:$E$211,"Estágio")+COUNTIFS(CC$19:CC$211,"<>0",$E$19:$E$211,"Jovem Aprendiz") -> 152 | CD10: =COUNTIFS(CD$19:CD$211,"<>0",$E$19:$E$211,"CLT")+COUNTIFS(CD$19:CD$211,"<>0",$E$19:$E$211,"Estágio")+COUNTIFS(CD$19:CD$211,"<>0",$E$19:$E$211,"Jovem Aprendiz") -> 154 | CE10: =COUNTIFS(CE$19:CE$211,"<>0",$E$19:$E$211,"CLT")+COUNTIFS(CE$19:CE$211,"<>0",$E$19:$E$211,"Estágio")+COUNTIFS(CE$19:CE$211,"<>0",$E$19:$E$211,"Jovem Aprendiz") -> 154 | ... CI10: =COUNTIFS(CI$19:CI$211,"<>0",$E$19:$E$211,"CLT")+COUNTIFS(CI$19:CI$211,"<>0",$E$19:$E$211,"Estágio")+COUNTIFS(CI$19:CI$211,"<>0",$E$19:$E$211,"Jovem Aprendiz") -> 154 | CK10: =COUNTIFS(CK$19:CK$211,"<>0",$E$19:$E$211,"CLT")+COUNTIFS(CK$19:CK$211,"<>0",$E$19:$E$211,"Estágio")+COUNTIFS(CK$19:CK$211,"<>0",$E$19:$E$211,"Jovem Aprendiz") -> 135 | CL10: =COUNTIFS(CL$19:CL$211,"<>0",$E$19:$E$211,"CLT")+COUNTIFS(CL$19:CL$211,"<>0",$E$19:$E$211,"Estágio")+COUNTIFS(CL$19:CL$211,"<>0",$E$19:$E$211,"Jovem Aprendiz") -> 139 | CM10: =COUNTIFS(CM$19:CM$211,"<>0",$E$19:$E$211,"CLT")+COUNTIFS(CM$19:CM$211,"<>0",$E$19:$E$211,"Estágio")+COUNTIFS(CM$19:CM$211,"<>0",$E$19:$E$211,"Jovem Aprendiz") -> 147 | CN10: =COUNTIFS(CN$19:CN$211,"<>0",$E$19:$E$211,"CLT")+COUNTIFS(CN$19:CN$211,"<>0",$E$19:$E$211,"Estágio")+COUNTIFS(CN$19:CN$211,"<>0",$E$19:$E$211,"Jovem Aprendiz") -> 149 | CO10: =COUNTIFS(CO$19:CO$211,"<>0",$E$19:$E$211,"CLT")+COUNTIFS(CO$19:CO$211,"<>0",$E$19:$E$211,"Estágio")+COUNTIFS(CO$19:CO$211,"<>0",$E$19:$E$211,"Jovem Aprendiz") -> 152 | CP10: =COUNTIFS(CP$19:CP$211,"<>0",$E$19:$E$211,"CLT")+COUNTIFS(CP$19:CP$211,"<>0",$E$19:$E$211,"Estágio")+COUNTIFS(CP$19:CP$211,"<>0",$E$19:$E$211,"Jovem Aprendiz") -> 152 | CQ10: =COUNTIFS(CQ$19:CQ$211,"<>0",$E$19:$E$211,"CLT")+COUNTIFS(CQ$19:CQ$211,"<>0",$E$19:$E$211,"Estágio")+COUNTIFS(CQ$19:CQ$211,"<>0",$E$19:$E$211,"Jovem Aprendiz") -> 154 | CR10: =COUNTIFS(CR$19:CR$211,"<>0",$E$19:$E$211,"CLT")+COUNTIFS(CR$19:CR$211,"<>0",$E$19:$E$211,"Estágio")+COUNTIFS(CR$19:CR$211,"<>0",$E$19:$E$211,"Jovem Aprendiz") -> 154 | ... CV10: =COUNTIFS(CV$19:CV$211,"<>0",$E$19:$E$211,"CLT")+COUNTIFS(CV$19:CV$211,"<>0",$E$19:$E$211,"Estágio")+COUNTIFS(CV$19:CV$211,"<>0",$E$19:$E$211,"Jovem Aprendiz") -> 154 | CX10: =COUNTIFS(CX$19:CX$211,"<>0",$E$19:$E$211,"CLT")+COUNTIFS(CX$19:CX$211,"<>0",$E$19:$E$211,"Estágio")+COUNTIFS(CX$19:CX$211,"<>0",$E$19:$E$211,"Jovem Aprendiz") -> 120 | CY10: =COUNTIFS(CY$19:CY$211,"<>0",$E$19:$E$211,"CLT")+COUNTIFS(CY$19:CY$211,"<>0",$E$19:$E$211,"Estágio")+COUNTIFS(CY$19:CY$211,"<>0",$E$19:$E$211,"Jovem Aprendiz") -> 124 | CZ10: =COUNTIFS(CZ$19:CZ$211,"<>0",$E$19:$E$211,"CLT")+COUNTIFS(CZ$19:CZ$211,"<>0",$E$19:$E$211,"Estágio")+COUNTIFS(CZ$19:CZ$211,"<>0",$E$19:$E$211,"Jovem Aprendiz") -> 131 | DA10: =COUNTIFS(DA$19:DA$211,"<>0",$E$19:$E$211,"CLT")+COUNTIFS(DA$19:DA$211,"<>0",$E$19:$E$211,"Estágio")+COUNTIFS(DA$19:DA$211,"<>0",$E$19:$E$211,"Jovem Aprendiz") -> 133 | DB10: =COUNTIFS(DB$19:DB$211,"<>0",$E$19:$E$211,"CLT")+COUNTIFS(DB$19:DB$211,"<>0",$E$19:$E$211,"Estágio")+COUNTIFS(DB$19:DB$211,"<>0",$E$19:$E$211,"Jovem Aprendiz") -> 135 | DC10: =COUNTIFS(DC$19:DC$211,"<>0",$E$19:$E$211,"CLT")+COUNTIFS(DC$19:DC$211,"<>0",$E$19:$E$211,"Estágio")+COUNTIFS(DC$19:DC$211,"<>0",$E$19:$E$211,"Jovem Aprendiz") -> 135 | DD10: =COUNTIFS(DD$19:DD$211,"<>0",$E$19:$E$211,"CLT")+COUNTIFS(DD$19:DD$211,"<>0",$E$19:$E$211,"Estágio")+COUNTIFS(DD$19:DD$211,"<>0",$E$19:$E$211,"Jovem Aprendiz") -> 136 | DE10: =COUNTIFS(DE$19:DE$211,"<>0",$E$19:$E$211,"CLT")+COUNTIFS(DE$19:DE$211,"<>0",$E$19:$E$211,"Estágio")+COUNTIFS(DE$19:DE$211,"<>0",$E$19:$E$211,"Jovem Aprendiz") -> 136 | ... DI10: =COUNTIFS(DI$19:DI$211,"<>0",$E$19:$E$211,"CLT")+COUNTIFS(DI$19:DI$211,"<>0",$E$19:$E$211,"Estágio")+COUNTIFS(DI$19:DI$211,"<>0",$E$19:$E$211,"Jovem Aprendiz") -> 136 | DK10: =COUNTIFS(DK$19:DK$211,"<>0",$E$19:$E$211,"CLT")+COUNTIFS(DK$19:DK$211,"<>0",$E$19:$E$211,"Estágio")+COUNTIFS(DK$19:DK$211,"<>0",$E$19:$E$211,"Jovem Aprendiz") -> 135 | DL10: =COUNTIFS(DL$19:DL$211,"<>0",$E$19:$E$211,"CLT")+COUNTIFS(DL$19:DL$211,"<>0",$E$19:$E$211,"Estágio")+COUNTIFS(DL$19:DL$211,"<>0",$E$19:$E$211,"Jovem Aprendiz") -> 139 | DM10: =COUNTIFS(DM$19:DM$211,"<>0",$E$19:$E$211,"CLT")+COUNTIFS(DM$19:DM$211,"<>0",$E$19:$E$211,"Estágio")+COUNTIFS(DM$19:DM$211,"<>0",$E$19:$E$211,"Jovem Aprendiz") -> 147 | DN10: =COUNTIFS(DN$19:DN$211,"<>0",$E$19:$E$211,"CLT")+COUNTIFS(DN$19:DN$211,"<>0",$E$19:$E$211,"Estágio")+COUNTIFS(DN$19:DN$211,"<>0",$E$19:$E$211,"Jovem Aprendiz") -> 149 | DO10: =COUNTIFS(DO$19:DO$211,"<>0",$E$19:$E$211,"CLT")+COUNTIFS(DO$19:DO$211,"<>0",$E$19:$E$211,"Estágio")+COUNTIFS(DO$19:DO$211,"<>0",$E$19:$E$211,"Jovem Aprendiz") -> 152 | DP10: =COUNTIFS(DP$19:DP$211,"<>0",$E$19:$E$211,"CLT")+COUNTIFS(DP$19:DP$211,"<>0",$E$19:$E$211,"Estágio")+COUNTIFS(DP$19:DP$211,"<>0",$E$19:$E$211,"Jovem Aprendiz") -> 152 | DQ10: =COUNTIFS(DQ$19:DQ$211,"<>0",$E$19:$E$211,"CLT")+COUNTIFS(DQ$19:DQ$211,"<>0",$E$19:$E$211,"Estágio")+COUNTIFS(DQ$19:DQ$211,"<>0",$E$19:$E$211,"Jovem Aprendiz") -> 154 | DR10: =COUNTIFS(DR$19:DR$211,"<>0",$E$19:$E$211,"CLT")+COUNTIFS(DR$19:DR$211,"<>0",$E$19:$E$211,"Estágio")+COUNTIFS(DR$19:DR$211,"<>0",$E$19:$E$211,"Jovem Aprendiz") -> 154 | ... DV10: =COUNTIFS(DV$19:DV$211,"<>0",$E$19:$E$211,"CLT")+COUNTIFS(DV$19:DV$211,"<>0",$E$19:$E$211,"Estágio")+COUNTIFS(DV$19:DV$211,"<>0",$E$19:$E$211,"Jovem Aprendiz") -> 154 | ED10: Total | EE10: =+SUM(EE4:EE9) -> 4330848.8 | EF10: =+SUM(EF4:EF9) -> 5618170.9
B11: PJ | K11: =(SUMIFS(K$19:K$211,$E$19:$E$211,$B11))/1000 -> 620.5801 | L11: =(SUMIFS(L$19:L$211,$E$19:$E$211,$B11))/1000 -> 620.5801 | M11: =(SUMIFS(M$19:M$211,$E$19:$E$211,$B11))/1000 -> 635.5801 | N11: =(SUMIFS(N$19:N$211,$E$19:$E$211,$B11))/1000 -> 575.0801 | O11: =(SUMIFS(O$19:O$211,$E$19:$E$211,$B11))/1000 -> 590.0801 | P11: =(SUMIFS(P$19:P$211,$E$19:$E$211,$B11))/1000 -> 590.0801 | Q11: =(SUMIFS(Q$19:Q$211,$E$19:$E$211,$B11))/1000 -> 613.0801 | R11: =(SUMIFS(R$19:R$211,$E$19:$E$211,$B11))/1000 -> 621.0801 | ... V11: =(SUMIFS(V$19:V$211,$E$19:$E$211,$B11))/1000 -> 621.0801 | X11: =(SUMIFS(X$19:X$211,$E$19:$E$211,$B11))/1000 -> 620.5801 | Y11: =(SUMIFS(Y$19:Y$211,$E$19:$E$211,$B11))/1000 -> 620.5801 | Z11: =(SUMIFS(Z$19:Z$211,$E$19:$E$211,$B11))/1000 -> 635.5801 | AA11: =(SUMIFS(AA$19:AA$211,$E$19:$E$211,$B11))/1000 -> 575.0801 | AB11: =(SUMIFS(AB$19:AB$211,$E$19:$E$211,$B11))/1000 -> 590.0801 | AC11: =(SUMIFS(AC$19:AC$211,$E$19:$E$211,$B11))/1000 -> 590.0801 | AD11: =(SUMIFS(AD$19:AD$211,$E$19:$E$211,$B11))/1000 -> 613.0801 | AE11: =(SUMIFS(AE$19:AE$211,$E$19:$E$211,$B11))/1000 -> 621.0801 | ... AI11: =(SUMIFS(AI$19:AI$211,$E$19:$E$211,$B11))/1000 -> 621.0801 | AK11: =(SUMIFS(AK$19:AK$211,$E$19:$E$211,$B11))/1000 -> 0 | AL11: =(SUMIFS(AL$19:AL$211,$E$19:$E$211,$B11))/1000 -> 0 | AM11: =(SUMIFS(AM$19:AM$211,$E$19:$E$211,$B11))/1000 -> 0 | AN11: =(SUMIFS(AN$19:AN$211,$E$19:$E$211,$B11))/1000 -> 0 | AO11: =(SUMIFS(AO$19:AO$211,$E$19:$E$211,$B11))/1000 -> 0 | AP11: =(SUMIFS(AP$19:AP$211,$E$19:$E$211,$B11))/1000 -> 0 | AQ11: =(SUMIFS(AQ$19:AQ$211,$E$19:$E$211,$B11))/1000 -> 0 | AR11: =(SUMIFS(AR$19:AR$211,$E$19:$E$211,$B11))/1000 -> 0 | ... AV11: =(SUMIFS(AV$19:AV$211,$E$19:$E$211,$B11))/1000 -> 0 | AX11: =(SUMIFS(AX$19:AX$211,$E$19:$E$211,$B11))/1000 -> 0 | AY11: =(SUMIFS(AY$19:AY$211,$E$19:$E$211,$B11))/1000 -> 0 | AZ11: =(SUMIFS(AZ$19:AZ$211,$E$19:$E$211,$B11))/1000 -> 0 | BA11: =(SUMIFS(BA$19:BA$211,$E$19:$E$211,$B11))/1000 -> 0 | BB11: =(SUMIFS(BB$19:BB$211,$E$19:$E$211,$B11))/1000 -> 0 | BC11: =(SUMIFS(BC$19:BC$211,$E$19:$E$211,$B11))/1000 -> 0 | BD11: =(SUMIFS(BD$19:BD$211,$E$19:$E$211,$B11))/1000 -> 0 | BE11: =(SUMIFS(BE$19:BE$211,$E$19:$E$211,$B11))/1000 -> 0 | ... BI11: =(SUMIFS(BI$19:BI$211,$E$19:$E$211,$B11))/1000 -> 0 | BK11: =(SUMIFS(BK$19:BK$211,$E$19:$E$211,$B11))/1000 -> 0 | BL11: =(SUMIFS(BL$19:BL$211,$E$19:$E$211,$B11))/1000 -> 0 | BM11: =(SUMIFS(BM$19:BM$211,$E$19:$E$211,$B11))/1000 -> 0 | BN11: =(SUMIFS(BN$19:BN$211,$E$19:$E$211,$B11))/1000 -> 0 | BO11: =(SUMIFS(BO$19:BO$211,$E$19:$E$211,$B11))/1000 -> 0 | BP11: =(SUMIFS(BP$19:BP$211,$E$19:$E$211,$B11))/1000 -> 0 | BQ11: =(SUMIFS(BQ$19:BQ$211,$E$19:$E$211,$B11))/1000 -> 0 | BR11: =(SUMIFS(BR$19:BR$211,$E$19:$E$211,$B11))/1000 -> 0 | ... BV11: =(SUMIFS(BV$19:BV$211,$E$19:$E$211,$B11))/1000 -> 0 | BX11: =(SUMIFS(BX$19:BX$211,$E$19:$E$211,$B11))/1000 -> 0 | BY11: =(SUMIFS(BY$19:BY$211,$E$19:$E$211,$B11))/1000 -> 0 | BZ11: =(SUMIFS(BZ$19:BZ$211,$E$19:$E$211,$B11))/1000 -> 0 | CA11: =(SUMIFS(CA$19:CA$211,$E$19:$E$211,$B11))/1000 -> 0 | CB11: =(SUMIFS(CB$19:CB$211,$E$19:$E$211,$B11))/1000 -> 0 | CC11: =(SUMIFS(CC$19:CC$211,$E$19:$E$211,$B11))/1000 -> 0 | CD11: =(SUMIFS(CD$19:CD$211,$E$19:$E$211,$B11))/1000 -> 0 | CE11: =(SUMIFS(CE$19:CE$211,$E$19:$E$211,$B11))/1000 -> 0 | ... CI11: =(SUMIFS(CI$19:CI$211,$E$19:$E$211,$B11))/1000 -> 0 | CK11: =(SUMIFS(CK$19:CK$211,$E$19:$E$211,$B11))/1000 -> 0 | CL11: =(SUMIFS(CL$19:CL$211,$E$19:$E$211,$B11))/1000 -> 0 | CM11: =(SUMIFS(CM$19:CM$211,$E$19:$E$211,$B11))/1000 -> 0 | CN11: =(SUMIFS(CN$19:CN$211,$E$19:$E$211,$B11))/1000 -> 0 | CO11: =(SUMIFS(CO$19:CO$211,$E$19:$E$211,$B11))/1000 -> 0 | CP11: =(SUMIFS(CP$19:CP$211,$E$19:$E$211,$B11))/1000 -> 0 | CQ11: =(SUMIFS(CQ$19:CQ$211,$E$19:$E$211,$B11))/1000 -> 0 | CR11: =(SUMIFS(CR$19:CR$211,$E$19:$E$211,$B11))/1000 -> 0 | ... CV11: =(SUMIFS(CV$19:CV$211,$E$19:$E$211,$B11))/1000 -> 0 | CX11: =(SUMIFS(CX$19:CX$211,$E$19:$E$211,$B11))/1000 -> 0 | CY11: =(SUMIFS(CY$19:CY$211,$E$19:$E$211,$B11))/1000 -> 0 | CZ11: =(SUMIFS(CZ$19:CZ$211,$E$19:$E$211,$B11))/1000 -> 0 | DA11: =(SUMIFS(DA$19:DA$211,$E$19:$E$211,$B11))/1000 -> 0 | DB11: =(SUMIFS(DB$19:DB$211,$E$19:$E$211,$B11))/1000 -> 0 | DC11: =(SUMIFS(DC$19:DC$211,$E$19:$E$211,$B11))/1000 -> 0 | DD11: =(SUMIFS(DD$19:DD$211,$E$19:$E$211,$B11))/1000 -> 0 | DE11: =(SUMIFS(DE$19:DE$211,$E$19:$E$211,$B11))/1000 -> 0 | ... DI11: =(SUMIFS(DI$19:DI$211,$E$19:$E$211,$B11))/1000 -> 0 | DK11: =(SUMIFS(DK$19:DK$211,$E$19:$E$211,$B11))/1000 -> 620.5801 | DL11: =(SUMIFS(DL$19:DL$211,$E$19:$E$211,$B11))/1000 -> 620.5801 | DM11: =(SUMIFS(DM$19:DM$211,$E$19:$E$211,$B11))/1000 -> 635.5801 | DN11: =(SUMIFS(DN$19:DN$211,$E$19:$E$211,$B11))/1000 -> 575.0801 | DO11: =(SUMIFS(DO$19:DO$211,$E$19:$E$211,$B11))/1000 -> 590.0801 | DP11: =(SUMIFS(DP$19:DP$211,$E$19:$E$211,$B11))/1000 -> 590.0801 | DQ11: =(SUMIFS(DQ$19:DQ$211,$E$19:$E$211,$B11))/1000 -> 613.0801 | DR11: =(SUMIFS(DR$19:DR$211,$E$19:$E$211,$B11))/1000 -> 621.0801 | ... DV11: =(SUMIFS(DV$19:DV$211,$E$19:$E$211,$B11))/1000 -> 621.0801
B12: HC | K12: =COUNTIFS(K$19:K$211,"<>0",$E$19:$E$211,$B11) -> 18 | L12: =COUNTIFS(L$19:L$211,"<>0",$E$19:$E$211,$B11) -> 21 | M12: =COUNTIFS(M$19:M$211,"<>0",$E$19:$E$211,$B11) -> 21 | N12: =COUNTIFS(N$19:N$211,"<>0",$E$19:$E$211,$B11) -> 20 | O12: =COUNTIFS(O$19:O$211,"<>0",$E$19:$E$211,$B11) -> 20 | P12: =COUNTIFS(P$19:P$211,"<>0",$E$19:$E$211,$B11) -> 20 | Q12: =COUNTIFS(Q$19:Q$211,"<>0",$E$19:$E$211,$B11) -> 20 | R12: =COUNTIFS(R$19:R$211,"<>0",$E$19:$E$211,$B11) -> 20 | ... V12: =COUNTIFS(V$19:V$211,"<>0",$E$19:$E$211,$B11) -> 20 | X12: =COUNTIFS(X$19:X$211,"<>0",$E$19:$E$211,$B11) -> 18 | Y12: =COUNTIFS(Y$19:Y$211,"<>0",$E$19:$E$211,$B11) -> 18 | Z12: =COUNTIFS(Z$19:Z$211,"<>0",$E$19:$E$211,$B11) -> 19 | AA12: =COUNTIFS(AA$19:AA$211,"<>0",$E$19:$E$211,$B11) -> 18 | AB12: =COUNTIFS(AB$19:AB$211,"<>0",$E$19:$E$211,$B11) -> 19 | AC12: =COUNTIFS(AC$19:AC$211,"<>0",$E$19:$E$211,$B11) -> 19 | AD12: =COUNTIFS(AD$19:AD$211,"<>0",$E$19:$E$211,$B11) -> 20 | AE12: =COUNTIFS(AE$19:AE$211,"<>0",$E$19:$E$211,$B11) -> 20 | ... AI12: =COUNTIFS(AI$19:AI$211,"<>0",$E$19:$E$211,$B11) -> 20 | AK12: =COUNTIFS(AK$19:AK$211,"<>0",$E$19:$E$211,$B11) -> 0 | AL12: =COUNTIFS(AL$19:AL$211,"<>0",$E$19:$E$211,$B11) -> 0 | AM12: =COUNTIFS(AM$19:AM$211,"<>0",$E$19:$E$211,$B11) -> 0 | AN12: =COUNTIFS(AN$19:AN$211,"<>0",$E$19:$E$211,$B11) -> 0 | AO12: =COUNTIFS(AO$19:AO$211,"<>0",$E$19:$E$211,$B11) -> 0 | AP12: =COUNTIFS(AP$19:AP$211,"<>0",$E$19:$E$211,$B11) -> 0 | AQ12: =COUNTIFS(AQ$19:AQ$211,"<>0",$E$19:$E$211,$B11) -> 0 | AR12: =COUNTIFS(AR$19:AR$211,"<>0",$E$19:$E$211,$B11) -> 0 | ... AV12: =COUNTIFS(AV$19:AV$211,"<>0",$E$19:$E$211,$B11) -> 0 | AX12: =COUNTIFS(AX$19:AX$211,"<>0",$E$19:$E$211,$B11) -> 0 | AY12: =COUNTIFS(AY$19:AY$211,"<>0",$E$19:$E$211,$B11) -> 0 | AZ12: =COUNTIFS(AZ$19:AZ$211,"<>0",$E$19:$E$211,$B11) -> 0 | BA12: =COUNTIFS(BA$19:BA$211,"<>0",$E$19:$E$211,$B11) -> 0 | BB12: =COUNTIFS(BB$19:BB$211,"<>0",$E$19:$E$211,$B11) -> 0 | BC12: =COUNTIFS(BC$19:BC$211,"<>0",$E$19:$E$211,$B11) -> 0 | BD12: =COUNTIFS(BD$19:BD$211,"<>0",$E$19:$E$211,$B11) -> 0 | BE12: =COUNTIFS(BE$19:BE$211,"<>0",$E$19:$E$211,$B11) -> 0 | ... BI12: =COUNTIFS(BI$19:BI$211,"<>0",$E$19:$E$211,$B11) -> 0 | BK12: =COUNTIFS(BK$19:BK$211,"<>0",$E$19:$E$211,$B11) -> 0 | BL12: =COUNTIFS(BL$19:BL$211,"<>0",$E$19:$E$211,$B11) -> 0 | BM12: =COUNTIFS(BM$19:BM$211,"<>0",$E$19:$E$211,$B11) -> 0 | BN12: =COUNTIFS(BN$19:BN$211,"<>0",$E$19:$E$211,$B11) -> 0 | BO12: =COUNTIFS(BO$19:BO$211,"<>0",$E$19:$E$211,$B11) -> 0 | BP12: =COUNTIFS(BP$19:BP$211,"<>0",$E$19:$E$211,$B11) -> 0 | BQ12: =COUNTIFS(BQ$19:BQ$211,"<>0",$E$19:$E$211,$B11) -> 0 | BR12: =COUNTIFS(BR$19:BR$211,"<>0",$E$19:$E$211,$B11) -> 0 | ... BV12: =COUNTIFS(BV$19:BV$211,"<>0",$E$19:$E$211,$B11) -> 0 | BX12: =COUNTIFS(BX$19:BX$211,"<>0",$E$19:$E$211,$B11) -> 0 | BY12: =COUNTIFS(BY$19:BY$211,"<>0",$E$19:$E$211,$B11) -> 0 | BZ12: =COUNTIFS(BZ$19:BZ$211,"<>0",$E$19:$E$211,$B11) -> 0 | CA12: =COUNTIFS(CA$19:CA$211,"<>0",$E$19:$E$211,$B11) -> 0 | CB12: =COUNTIFS(CB$19:CB$211,"<>0",$E$19:$E$211,$B11) -> 0 | CC12: =COUNTIFS(CC$19:CC$211,"<>0",$E$19:$E$211,$B11) -> 0 | CD12: =COUNTIFS(CD$19:CD$211,"<>0",$E$19:$E$211,$B11) -> 0 | CE12: =COUNTIFS(CE$19:CE$211,"<>0",$E$19:$E$211,$B11) -> 0 | ... CI12: =COUNTIFS(CI$19:CI$211,"<>0",$E$19:$E$211,$B11) -> 0 | CK12: =COUNTIFS(CK$19:CK$211,"<>0",$E$19:$E$211,$B11) -> 0 | CL12: =COUNTIFS(CL$19:CL$211,"<>0",$E$19:$E$211,$B11) -> 0 | CM12: =COUNTIFS(CM$19:CM$211,"<>0",$E$19:$E$211,$B11) -> 0 | CN12: =COUNTIFS(CN$19:CN$211,"<>0",$E$19:$E$211,$B11) -> 0 | CO12: =COUNTIFS(CO$19:CO$211,"<>0",$E$19:$E$211,$B11) -> 0 | CP12: =COUNTIFS(CP$19:CP$211,"<>0",$E$19:$E$211,$B11) -> 0 | CQ12: =COUNTIFS(CQ$19:CQ$211,"<>0",$E$19:$E$211,$B11) -> 0 | CR12: =COUNTIFS(CR$19:CR$211,"<>0",$E$19:$E$211,$B11) -> 0 | ... CV12: =COUNTIFS(CV$19:CV$211,"<>0",$E$19:$E$211,$B11) -> 0 | CX12: =COUNTIFS(CX$19:CX$211,"<>0",$E$19:$E$211,$B11) -> 0 | CY12: =COUNTIFS(CY$19:CY$211,"<>0",$E$19:$E$211,$B11) -> 0 | CZ12: =COUNTIFS(CZ$19:CZ$211,"<>0",$E$19:$E$211,$B11) -> 0 | DA12: =COUNTIFS(DA$19:DA$211,"<>0",$E$19:$E$211,$B11) -> 0 | DB12: =COUNTIFS(DB$19:DB$211,"<>0",$E$19:$E$211,$B11) -> 0 | DC12: =COUNTIFS(DC$19:DC$211,"<>0",$E$19:$E$211,$B11) -> 0 | DD12: =COUNTIFS(DD$19:DD$211,"<>0",$E$19:$E$211,$B11) -> 0 | DE12: =COUNTIFS(DE$19:DE$211,"<>0",$E$19:$E$211,$B11) -> 0 | ... DI12: =COUNTIFS(DI$19:DI$211,"<>0",$E$19:$E$211,$B11) -> 0 | DK12: =COUNTIFS(DK$19:DK$211,"<>0",$E$19:$E$211,$B11) -> 18 | DL12: =COUNTIFS(DL$19:DL$211,"<>0",$E$19:$E$211,$B11) -> 18 | DM12: =COUNTIFS(DM$19:DM$211,"<>0",$E$19:$E$211,$B11) -> 19 | DN12: =COUNTIFS(DN$19:DN$211,"<>0",$E$19:$E$211,$B11) -> 18 | DO12: =COUNTIFS(DO$19:DO$211,"<>0",$E$19:$E$211,$B11) -> 19 | DP12: =COUNTIFS(DP$19:DP$211,"<>0",$E$19:$E$211,$B11) -> 19 | DQ12: =COUNTIFS(DQ$19:DQ$211,"<>0",$E$19:$E$211,$B11) -> 20 | DR12: =COUNTIFS(DR$19:DR$211,"<>0",$E$19:$E$211,$B11) -> 20 | ... DV12: =COUNTIFS(DV$19:DV$211,"<>0",$E$19:$E$211,$B11) -> 20
B13: Pró-labore | K13: =(SUMIFS(K$19:K$211,$F$19:$F$211,$B13))/1000 -> 227 | L13: =(SUMIFS(L$19:L$211,$F$19:$F$211,$B13))/1000 -> 227 | M13: =(SUMIFS(M$19:M$211,$F$19:$F$211,$B13))/1000 -> 227 | N13: =(SUMIFS(N$19:N$211,$F$19:$F$211,$B13))/1000 -> 227 | O13: =(SUMIFS(O$19:O$211,$F$19:$F$211,$B13))/1000 -> 227 | P13: =(SUMIFS(P$19:P$211,$F$19:$F$211,$B13))/1000 -> 227 | Q13: =(SUMIFS(Q$19:Q$211,$F$19:$F$211,$B13))/1000 -> 227 | R13: =(SUMIFS(R$19:R$211,$F$19:$F$211,$B13))/1000 -> 227 | ... V13: =(SUMIFS(V$19:V$211,$F$19:$F$211,$B13))/1000 -> 227 | X13: =(SUMIFS(X$19:X$211,$F$19:$F$211,$B13))/1000 -> 227 | Y13: =(SUMIFS(Y$19:Y$211,$F$19:$F$211,$B13))/1000 -> 227 | Z13: =(SUMIFS(Z$19:Z$211,$F$19:$F$211,$B13))/1000 -> 227 | AA13: =(SUMIFS(AA$19:AA$211,$F$19:$F$211,$B13))/1000 -> 227 | AB13: =(SUMIFS(AB$19:AB$211,$F$19:$F$211,$B13))/1000 -> 227 | AC13: =(SUMIFS(AC$19:AC$211,$F$19:$F$211,$B13))/1000 -> 227 | AD13: =(SUMIFS(AD$19:AD$211,$F$19:$F$211,$B13))/1000 -> 227 | AE13: =(SUMIFS(AE$19:AE$211,$F$19:$F$211,$B13))/1000 -> 227 | ... AI13: =(SUMIFS(AI$19:AI$211,$F$19:$F$211,$B13))/1000 -> 227 | AK13: =(SUMIFS(AK$19:AK$211,$F$19:$F$211,$B13))/1000 -> 57.743316 | AL13: =(SUMIFS(AL$19:AL$211,$F$19:$F$211,$B13))/1000 -> 57.743316 | AM13: =(SUMIFS(AM$19:AM$211,$F$19:$F$211,$B13))/1000 -> 57.743316 | AN13: =(SUMIFS(AN$19:AN$211,$F$19:$F$211,$B13))/1000 -> 57.743316 | AO13: =(SUMIFS(AO$19:AO$211,$F$19:$F$211,$B13))/1000 -> 57.743316 | AP13: =(SUMIFS(AP$19:AP$211,$F$19:$F$211,$B13))/1000 -> 57.743316 | AQ13: =(SUMIFS(AQ$19:AQ$211,$F$19:$F$211,$B13))/1000 -> 57.743316 | AR13: =(SUMIFS(AR$19:AR$211,$F$19:$F$211,$B13))/1000 -> 57.743316 | ... AV13: =(SUMIFS(AV$19:AV$211,$F$19:$F$211,$B13))/1000 -> 57.743316 | AX13: =(SUMIFS(AX$19:AX$211,$F$19:$F$211,$B13))/1000 -> 3.8065376 | AY13: =(SUMIFS(AY$19:AY$211,$F$19:$F$211,$B13))/1000 -> 3.8065376 | AZ13: =(SUMIFS(AZ$19:AZ$211,$F$19:$F$211,$B13))/1000 -> 3.8065376 | BA13: =(SUMIFS(BA$19:BA$211,$F$19:$F$211,$B13))/1000 -> 3.8065376 | BB13: =(SUMIFS(BB$19:BB$211,$F$19:$F$211,$B13))/1000 -> 3.8065376 | BC13: =(SUMIFS(BC$19:BC$211,$F$19:$F$211,$B13))/1000 -> 3.8065376 | BD13: =(SUMIFS(BD$19:BD$211,$F$19:$F$211,$B13))/1000 -> 3.8065376 | BE13: =(SUMIFS(BE$19:BE$211,$F$19:$F$211,$B13))/1000 -> 3.8065376 | ... BI13: =(SUMIFS(BI$19:BI$211,$F$19:$F$211,$B13))/1000 -> 3.8065376 | BK13: =(SUMIFS(BK$19:BK$211,$F$19:$F$211,$B13))/1000 -> 0 | BL13: =(SUMIFS(BL$19:BL$211,$F$19:$F$211,$B13))/1000 -> 0 | BM13: =(SUMIFS(BM$19:BM$211,$F$19:$F$211,$B13))/1000 -> 0 | BN13: =(SUMIFS(BN$19:BN$211,$F$19:$F$211,$B13))/1000 -> 0 | BO13: =(SUMIFS(BO$19:BO$211,$F$19:$F$211,$B13))/1000 -> 0 | BP13: =(SUMIFS(BP$19:BP$211,$F$19:$F$211,$B13))/1000 -> 0 | BQ13: =(SUMIFS(BQ$19:BQ$211,$F$19:$F$211,$B13))/1000 -> 0 | BR13: =(SUMIFS(BR$19:BR$211,$F$19:$F$211,$B13))/1000 -> 0 | ... BV13: =(SUMIFS(BV$19:BV$211,$F$19:$F$211,$B13))/1000 -> 0 | BX13: =(SUMIFS(BX$19:BX$211,$F$19:$F$211,$B13))/1000 -> 48 | BY13: =(SUMIFS(BY$19:BY$211,$F$19:$F$211,$B13))/1000 -> 48 | BZ13: =(SUMIFS(BZ$19:BZ$211,$F$19:$F$211,$B13))/1000 -> 48 | CA13: =(SUMIFS(CA$19:CA$211,$F$19:$F$211,$B13))/1000 -> 48 | CB13: =(SUMIFS(CB$19:CB$211,$F$19:$F$211,$B13))/1000 -> 48 | CC13: =(SUMIFS(CC$19:CC$211,$F$19:$F$211,$B13))/1000 -> 48 | CD13: =(SUMIFS(CD$19:CD$211,$F$19:$F$211,$B13))/1000 -> 48 | CE13: =(SUMIFS(CE$19:CE$211,$F$19:$F$211,$B13))/1000 -> 48 | ... CI13: =(SUMIFS(CI$19:CI$211,$F$19:$F$211,$B13))/1000 -> 48 | CK13: =(SUMIFS(CK$19:CK$211,$F$19:$F$211,$B13))/1000 -> 0 | CL13: =(SUMIFS(CL$19:CL$211,$F$19:$F$211,$B13))/1000 -> 0 | CM13: =(SUMIFS(CM$19:CM$211,$F$19:$F$211,$B13))/1000 -> 0 | CN13: =(SUMIFS(CN$19:CN$211,$F$19:$F$211,$B13))/1000 -> 0 | CO13: =(SUMIFS(CO$19:CO$211,$F$19:$F$211,$B13))/1000 -> 0 | CP13: =(SUMIFS(CP$19:CP$211,$F$19:$F$211,$B13))/1000 -> 0 | CQ13: =(SUMIFS(CQ$19:CQ$211,$F$19:$F$211,$B13))/1000 -> 0 | CR13: =(SUMIFS(CR$19:CR$211,$F$19:$F$211,$B13))/1000 -> 0 | ... CV13: =(SUMIFS(CV$19:CV$211,$F$19:$F$211,$B13))/1000 -> 0 | CX13: =(SUMIFS(CX$19:CX$211,$F$19:$F$211,$B13))/1000 -> 45.4 | CY13: =(SUMIFS(CY$19:CY$211,$F$19:$F$211,$B13))/1000 -> 45.4 | CZ13: =(SUMIFS(CZ$19:CZ$211,$F$19:$F$211,$B13))/1000 -> 45.4 | DA13: =(SUMIFS(DA$19:DA$211,$F$19:$F$211,$B13))/1000 -> 45.4 | DB13: =(SUMIFS(DB$19:DB$211,$F$19:$F$211,$B13))/1000 -> 45.4 | DC13: =(SUMIFS(DC$19:DC$211,$F$19:$F$211,$B13))/1000 -> 45.4 | DD13: =(SUMIFS(DD$19:DD$211,$F$19:$F$211,$B13))/1000 -> 45.4 | DE13: =(SUMIFS(DE$19:DE$211,$F$19:$F$211,$B13))/1000 -> 45.4 | ... DI13: =(SUMIFS(DI$19:DI$211,$F$19:$F$211,$B13))/1000 -> 45.4 | DK13: =(SUMIFS(DK$19:DK$211,$F$19:$F$211,$B13))/1000 -> 320.4 | DL13: =(SUMIFS(DL$19:DL$211,$F$19:$F$211,$B13))/1000 -> 320.4 | DM13: =(SUMIFS(DM$19:DM$211,$F$19:$F$211,$B13))/1000 -> 320.4 | DN13: =(SUMIFS(DN$19:DN$211,$F$19:$F$211,$B13))/1000 -> 320.4 | DO13: =(SUMIFS(DO$19:DO$211,$F$19:$F$211,$B13))/1000 -> 320.4 | DP13: =(SUMIFS(DP$19:DP$211,$F$19:$F$211,$B13))/1000 -> 320.4 | DQ13: =(SUMIFS(DQ$19:DQ$211,$F$19:$F$211,$B13))/1000 -> 320.4 | DR13: =(SUMIFS(DR$19:DR$211,$F$19:$F$211,$B13))/1000 -> 320.4 | ... DV13: =(SUMIFS(DV$19:DV$211,$F$19:$F$211,$B13))/1000 -> 320.4
B14: HC | K14: =COUNTIFS(K$19:K$211,"<>0",$F$19:$F$211,$B13) -> 4 | L14: =COUNTIFS(L$19:L$211,"<>0",$F$19:$F$211,$B13) -> 4 | M14: =COUNTIFS(M$19:M$211,"<>0",$F$19:$F$211,$B13) -> 4 | N14: =COUNTIFS(N$19:N$211,"<>0",$F$19:$F$211,$B13) -> 4 | O14: =COUNTIFS(O$19:O$211,"<>0",$F$19:$F$211,$B13) -> 4 | P14: =COUNTIFS(P$19:P$211,"<>0",$F$19:$F$211,$B13) -> 4 | Q14: =COUNTIFS(Q$19:Q$211,"<>0",$F$19:$F$211,$B13) -> 4 | R14: =COUNTIFS(R$19:R$211,"<>0",$F$19:$F$211,$B13) -> 4 | ... V14: =COUNTIFS(V$19:V$211,"<>0",$F$19:$F$211,$B13) -> 4 | X14: =COUNTIFS(X$19:X$211,"<>0",$F$19:$F$211,$B13) -> 4 | Y14: =COUNTIFS(Y$19:Y$211,"<>0",$F$19:$F$211,$B13) -> 4 | Z14: =COUNTIFS(Z$19:Z$211,"<>0",$F$19:$F$211,$B13) -> 4 | AA14: =COUNTIFS(AA$19:AA$211,"<>0",$F$19:$F$211,$B13) -> 4 | AB14: =COUNTIFS(AB$19:AB$211,"<>0",$F$19:$F$211,$B13) -> 4 | AC14: =COUNTIFS(AC$19:AC$211,"<>0",$F$19:$F$211,$B13) -> 4 | AD14: =COUNTIFS(AD$19:AD$211,"<>0",$F$19:$F$211,$B13) -> 4 | AE14: =COUNTIFS(AE$19:AE$211,"<>0",$F$19:$F$211,$B13) -> 4 | ... AI14: =COUNTIFS(AI$19:AI$211,"<>0",$F$19:$F$211,$B13) -> 4 | AK14: =COUNTIFS(AK$19:AK$211,"<>0",$F$19:$F$211,$B13) -> 4 | AL14: =COUNTIFS(AL$19:AL$211,"<>0",$F$19:$F$211,$B13) -> 4 | AM14: =COUNTIFS(AM$19:AM$211,"<>0",$F$19:$F$211,$B13) -> 4 | AN14: =COUNTIFS(AN$19:AN$211,"<>0",$F$19:$F$211,$B13) -> 4 | AO14: =COUNTIFS(AO$19:AO$211,"<>0",$F$19:$F$211,$B13) -> 4 | AP14: =COUNTIFS(AP$19:AP$211,"<>0",$F$19:$F$211,$B13) -> 4 | AQ14: =COUNTIFS(AQ$19:AQ$211,"<>0",$F$19:$F$211,$B13) -> 4 | AR14: =COUNTIFS(AR$19:AR$211,"<>0",$F$19:$F$211,$B13) -> 4 | ... AV14: =COUNTIFS(AV$19:AV$211,"<>0",$F$19:$F$211,$B13) -> 4 | AX14: =COUNTIFS(AX$19:AX$211,"<>0",$F$19:$F$211,$B13) -> 4 | AY14: =COUNTIFS(AY$19:AY$211,"<>0",$F$19:$F$211,$B13) -> 4 | AZ14: =COUNTIFS(AZ$19:AZ$211,"<>0",$F$19:$F$211,$B13) -> 4 | BA14: =COUNTIFS(BA$19:BA$211,"<>0",$F$19:$F$211,$B13) -> 4 | BB14: =COUNTIFS(BB$19:BB$211,"<>0",$F$19:$F$211,$B13) -> 4 | BC14: =COUNTIFS(BC$19:BC$211,"<>0",$F$19:$F$211,$B13) -> 4 | BD14: =COUNTIFS(BD$19:BD$211,"<>0",$F$19:$F$211,$B13) -> 4 | BE14: =COUNTIFS(BE$19:BE$211,"<>0",$F$19:$F$211,$B13) -> 4 | ... BI14: =COUNTIFS(BI$19:BI$211,"<>0",$F$19:$F$211,$B13) -> 4 | BK14: =COUNTIFS(BK$19:BK$211,"<>0",$F$19:$F$211,$B13) -> 0 | BL14: =COUNTIFS(BL$19:BL$211,"<>0",$F$19:$F$211,$B13) -> 0 | BM14: =COUNTIFS(BM$19:BM$211,"<>0",$F$19:$F$211,$B13) -> 0 | BN14: =COUNTIFS(BN$19:BN$211,"<>0",$F$19:$F$211,$B13) -> 0 | BO14: =COUNTIFS(BO$19:BO$211,"<>0",$F$19:$F$211,$B13) -> 0 | BP14: =COUNTIFS(BP$19:BP$211,"<>0",$F$19:$F$211,$B13) -> 0 | BQ14: =COUNTIFS(BQ$19:BQ$211,"<>0",$F$19:$F$211,$B13) -> 0 | BR14: =COUNTIFS(BR$19:BR$211,"<>0",$F$19:$F$211,$B13) -> 0 | ... BV14: =COUNTIFS(BV$19:BV$211,"<>0",$F$19:$F$211,$B13) -> 0 | BX14: =COUNTIFS(BX$19:BX$211,"<>0",$F$19:$F$211,$B13) -> 4 | BY14: =COUNTIFS(BY$19:BY$211,"<>0",$F$19:$F$211,$B13) -> 4 | BZ14: =COUNTIFS(BZ$19:BZ$211,"<>0",$F$19:$F$211,$B13) -> 4 | CA14: =COUNTIFS(CA$19:CA$211,"<>0",$F$19:$F$211,$B13) -> 4 | CB14: =COUNTIFS(CB$19:CB$211,"<>0",$F$19:$F$211,$B13) -> 4 | CC14: =COUNTIFS(CC$19:CC$211,"<>0",$F$19:$F$211,$B13) -> 4 | CD14: =COUNTIFS(CD$19:CD$211,"<>0",$F$19:$F$211,$B13) -> 4 | CE14: =COUNTIFS(CE$19:CE$211,"<>0",$F$19:$F$211,$B13) -> 4 | ... CI14: =COUNTIFS(CI$19:CI$211,"<>0",$F$19:$F$211,$B13) -> 4 | CK14: =COUNTIFS(CK$19:CK$211,"<>0",$F$19:$F$211,$B13) -> 0 | CL14: =COUNTIFS(CL$19:CL$211,"<>0",$F$19:$F$211,$B13) -> 0 | CM14: =COUNTIFS(CM$19:CM$211,"<>0",$F$19:$F$211,$B13) -> 0 | CN14: =COUNTIFS(CN$19:CN$211,"<>0",$F$19:$F$211,$B13) -> 0 | CO14: =COUNTIFS(CO$19:CO$211,"<>0",$F$19:$F$211,$B13) -> 0 | CP14: =COUNTIFS(CP$19:CP$211,"<>0",$F$19:$F$211,$B13) -> 0 | CQ14: =COUNTIFS(CQ$19:CQ$211,"<>0",$F$19:$F$211,$B13) -> 0 | CR14: =COUNTIFS(CR$19:CR$211,"<>0",$F$19:$F$211,$B13) -> 0 | ... CV14: =COUNTIFS(CV$19:CV$211,"<>0",$F$19:$F$211,$B13) -> 0 | CX14: =COUNTIFS(CX$19:CX$211,"<>0",$F$19:$F$211,$B13) -> 4 | CY14: =COUNTIFS(CY$19:CY$211,"<>0",$F$19:$F$211,$B13) -> 4 | CZ14: =COUNTIFS(CZ$19:CZ$211,"<>0",$F$19:$F$211,$B13) -> 4 | DA14: =COUNTIFS(DA$19:DA$211,"<>0",$F$19:$F$211,$B13) -> 4 | DB14: =COUNTIFS(DB$19:DB$211,"<>0",$F$19:$F$211,$B13) -> 4 | DC14: =COUNTIFS(DC$19:DC$211,"<>0",$F$19:$F$211,$B13) -> 4 | DD14: =COUNTIFS(DD$19:DD$211,"<>0",$F$19:$F$211,$B13) -> 4 | DE14: =COUNTIFS(DE$19:DE$211,"<>0",$F$19:$F$211,$B13) -> 4 | ... DI14: =COUNTIFS(DI$19:DI$211,"<>0",$F$19:$F$211,$B13) -> 4 | DK14: =COUNTIFS(DK$19:DK$211,"<>0",$F$19:$F$211,$B13) -> 4 | DL14: =COUNTIFS(DL$19:DL$211,"<>0",$F$19:$F$211,$B13) -> 4 | DM14: =COUNTIFS(DM$19:DM$211,"<>0",$F$19:$F$211,$B13) -> 4 | DN14: =COUNTIFS(DN$19:DN$211,"<>0",$F$19:$F$211,$B13) -> 4 | DO14: =COUNTIFS(DO$19:DO$211,"<>0",$F$19:$F$211,$B13) -> 4 | DP14: =COUNTIFS(DP$19:DP$211,"<>0",$F$19:$F$211,$B13) -> 4 | DQ14: =COUNTIFS(DQ$19:DQ$211,"<>0",$F$19:$F$211,$B13) -> 4 | DR14: =COUNTIFS(DR$19:DR$211,"<>0",$F$19:$F$211,$B13) -> 4 | ... DV14: =COUNTIFS(DV$19:DV$211,"<>0",$F$19:$F$211,$B13) -> 4
B15: ICP Sócios | K15: =(SUMIFS(K$19:K$211,$F$19:$F$211,$B15))/1000 -> 188 | L15: =(SUMIFS(L$19:L$211,$F$19:$F$211,$B15))/1000 -> 188 | M15: =(SUMIFS(M$19:M$211,$F$19:$F$211,$B15))/1000 -> 188 | N15: =(SUMIFS(N$19:N$211,$F$19:$F$211,$B15))/1000 -> 188 | O15: =(SUMIFS(O$19:O$211,$F$19:$F$211,$B15))/1000 -> 188 | P15: =(SUMIFS(P$19:P$211,$F$19:$F$211,$B15))/1000 -> 188 | Q15: =(SUMIFS(Q$19:Q$211,$F$19:$F$211,$B15))/1000 -> 188 | R15: =(SUMIFS(R$19:R$211,$F$19:$F$211,$B15))/1000 -> 188 | ... V15: =(SUMIFS(V$19:V$211,$F$19:$F$211,$B15))/1000 -> 188 | X15: =(SUMIFS(X$19:X$211,$F$19:$F$211,$B15))/1000 -> 188 | Y15: =(SUMIFS(Y$19:Y$211,$F$19:$F$211,$B15))/1000 -> 188 | Z15: =(SUMIFS(Z$19:Z$211,$F$19:$F$211,$B15))/1000 -> 188 | AA15: =(SUMIFS(AA$19:AA$211,$F$19:$F$211,$B15))/1000 -> 188 | AB15: =(SUMIFS(AB$19:AB$211,$F$19:$F$211,$B15))/1000 -> 188 | AC15: =(SUMIFS(AC$19:AC$211,$F$19:$F$211,$B15))/1000 -> 188 | AD15: =(SUMIFS(AD$19:AD$211,$F$19:$F$211,$B15))/1000 -> 188 | AE15: =(SUMIFS(AE$19:AE$211,$F$19:$F$211,$B15))/1000 -> 188 | ... AI15: =(SUMIFS(AI$19:AI$211,$F$19:$F$211,$B15))/1000 -> 188 | AK15: =(SUMIFS(AK$19:AK$211,$F$19:$F$211,$B15))/1000 -> 36.934983 | AL15: =(SUMIFS(AL$19:AL$211,$F$19:$F$211,$B15))/1000 -> 36.934983 | AM15: =(SUMIFS(AM$19:AM$211,$F$19:$F$211,$B15))/1000 -> 36.934983 | AN15: =(SUMIFS(AN$19:AN$211,$F$19:$F$211,$B15))/1000 -> 36.934983 | AO15: =(SUMIFS(AO$19:AO$211,$F$19:$F$211,$B15))/1000 -> 36.934983 | AP15: =(SUMIFS(AP$19:AP$211,$F$19:$F$211,$B15))/1000 -> 36.934983 | AQ15: =(SUMIFS(AQ$19:AQ$211,$F$19:$F$211,$B15))/1000 -> 36.934983 | AR15: =(SUMIFS(AR$19:AR$211,$F$19:$F$211,$B15))/1000 -> 36.934983 | ... AV15: =(SUMIFS(AV$19:AV$211,$F$19:$F$211,$B15))/1000 -> 36.934983 | AX15: =(SUMIFS(AX$19:AX$211,$F$19:$F$211,$B15))/1000 -> 3.8065376 | AY15: =(SUMIFS(AY$19:AY$211,$F$19:$F$211,$B15))/1000 -> 3.8065376 | AZ15: =(SUMIFS(AZ$19:AZ$211,$F$19:$F$211,$B15))/1000 -> 3.8065376 | BA15: =(SUMIFS(BA$19:BA$211,$F$19:$F$211,$B15))/1000 -> 3.8065376 | BB15: =(SUMIFS(BB$19:BB$211,$F$19:$F$211,$B15))/1000 -> 3.8065376 | BC15: =(SUMIFS(BC$19:BC$211,$F$19:$F$211,$B15))/1000 -> 3.8065376 | BD15: =(SUMIFS(BD$19:BD$211,$F$19:$F$211,$B15))/1000 -> 3.8065376 | BE15: =(SUMIFS(BE$19:BE$211,$F$19:$F$211,$B15))/1000 -> 3.8065376 | ... BI15: =(SUMIFS(BI$19:BI$211,$F$19:$F$211,$B15))/1000 -> 3.8065376 | BK15: =(SUMIFS(BK$19:BK$211,$F$19:$F$211,$B15))/1000 -> 0 | BL15: =(SUMIFS(BL$19:BL$211,$F$19:$F$211,$B15))/1000 -> 0 | BM15: =(SUMIFS(BM$19:BM$211,$F$19:$F$211,$B15))/1000 -> 0 | BN15: =(SUMIFS(BN$19:BN$211,$F$19:$F$211,$B15))/1000 -> 0 | BO15: =(SUMIFS(BO$19:BO$211,$F$19:$F$211,$B15))/1000 -> 0 | BP15: =(SUMIFS(BP$19:BP$211,$F$19:$F$211,$B15))/1000 -> 0 | BQ15: =(SUMIFS(BQ$19:BQ$211,$F$19:$F$211,$B15))/1000 -> 0 | BR15: =(SUMIFS(BR$19:BR$211,$F$19:$F$211,$B15))/1000 -> 0 | ... BV15: =(SUMIFS(BV$19:BV$211,$F$19:$F$211,$B15))/1000 -> 0 | BX15: =(SUMIFS(BX$19:BX$211,$F$19:$F$211,$B15))/1000 -> 0 | BY15: =(SUMIFS(BY$19:BY$211,$F$19:$F$211,$B15))/1000 -> 0 | BZ15: =(SUMIFS(BZ$19:BZ$211,$F$19:$F$211,$B15))/1000 -> 0 | CA15: =(SUMIFS(CA$19:CA$211,$F$19:$F$211,$B15))/1000 -> 0 | CB15: =(SUMIFS(CB$19:CB$211,$F$19:$F$211,$B15))/1000 -> 0 | CC15: =(SUMIFS(CC$19:CC$211,$F$19:$F$211,$B15))/1000 -> 0 | CD15: =(SUMIFS(CD$19:CD$211,$F$19:$F$211,$B15))/1000 -> 0 | CE15: =(SUMIFS(CE$19:CE$211,$F$19:$F$211,$B15))/1000 -> 0 | ... CI15: =(SUMIFS(CI$19:CI$211,$F$19:$F$211,$B15))/1000 -> 0 | CK15: =(SUMIFS(CK$19:CK$211,$F$19:$F$211,$B15))/1000 -> 0 | CL15: =(SUMIFS(CL$19:CL$211,$F$19:$F$211,$B15))/1000 -> 0 | CM15: =(SUMIFS(CM$19:CM$211,$F$19:$F$211,$B15))/1000 -> 0 | CN15: =(SUMIFS(CN$19:CN$211,$F$19:$F$211,$B15))/1000 -> 0 | CO15: =(SUMIFS(CO$19:CO$211,$F$19:$F$211,$B15))/1000 -> 0 | CP15: =(SUMIFS(CP$19:CP$211,$F$19:$F$211,$B15))/1000 -> 0 | CQ15: =(SUMIFS(CQ$19:CQ$211,$F$19:$F$211,$B15))/1000 -> 0 | CR15: =(SUMIFS(CR$19:CR$211,$F$19:$F$211,$B15))/1000 -> 0 | ... CV15: =(SUMIFS(CV$19:CV$211,$F$19:$F$211,$B15))/1000 -> 0 | CX15: =(SUMIFS(CX$19:CX$211,$F$19:$F$211,$B15))/1000 -> 30.266667 | CY15: =(SUMIFS(CY$19:CY$211,$F$19:$F$211,$B15))/1000 -> 30.266667 | CZ15: =(SUMIFS(CZ$19:CZ$211,$F$19:$F$211,$B15))/1000 -> 30.266667 | DA15: =(SUMIFS(DA$19:DA$211,$F$19:$F$211,$B15))/1000 -> 30.266667 | DB15: =(SUMIFS(DB$19:DB$211,$F$19:$F$211,$B15))/1000 -> 30.266667 | DC15: =(SUMIFS(DC$19:DC$211,$F$19:$F$211,$B15))/1000 -> 30.266667 | DD15: =(SUMIFS(DD$19:DD$211,$F$19:$F$211,$B15))/1000 -> 30.266667 | DE15: =(SUMIFS(DE$19:DE$211,$F$19:$F$211,$B15))/1000 -> 30.266667 | ... DI15: =(SUMIFS(DI$19:DI$211,$F$19:$F$211,$B15))/1000 -> 30.266667 | DK15: =(SUMIFS(DK$19:DK$211,$F$19:$F$211,$B15))/1000 -> 218.26667 | DL15: =(SUMIFS(DL$19:DL$211,$F$19:$F$211,$B15))/1000 -> 218.26667 | DM15: =(SUMIFS(DM$19:DM$211,$F$19:$F$211,$B15))/1000 -> 218.26667 | DN15: =(SUMIFS(DN$19:DN$211,$F$19:$F$211,$B15))/1000 -> 218.26667 | DO15: =(SUMIFS(DO$19:DO$211,$F$19:$F$211,$B15))/1000 -> 218.26667 | DP15: =(SUMIFS(DP$19:DP$211,$F$19:$F$211,$B15))/1000 -> 218.26667 | DQ15: =(SUMIFS(DQ$19:DQ$211,$F$19:$F$211,$B15))/1000 -> 218.26667 | DR15: =(SUMIFS(DR$19:DR$211,$F$19:$F$211,$B15))/1000 -> 218.26667 | ... DV15: =(SUMIFS(DV$19:DV$211,$F$19:$F$211,$B15))/1000 -> 218.26667
B16: HC | K16: =COUNTIFS(K$19:K$211,"<>0",$F$19:$F$211,$B15) -> 5 | L16: =COUNTIFS(L$19:L$211,"<>0",$F$19:$F$211,$B15) -> 5 | M16: =COUNTIFS(M$19:M$211,"<>0",$F$19:$F$211,$B15) -> 5 | N16: =COUNTIFS(N$19:N$211,"<>0",$F$19:$F$211,$B15) -> 5 | O16: =COUNTIFS(O$19:O$211,"<>0",$F$19:$F$211,$B15) -> 5 | P16: =COUNTIFS(P$19:P$211,"<>0",$F$19:$F$211,$B15) -> 5 | Q16: =COUNTIFS(Q$19:Q$211,"<>0",$F$19:$F$211,$B15) -> 5 | R16: =COUNTIFS(R$19:R$211,"<>0",$F$19:$F$211,$B15) -> 5 | ... V16: =COUNTIFS(V$19:V$211,"<>0",$F$19:$F$211,$B15) -> 5 | X16: =COUNTIFS(X$19:X$211,"<>0",$F$19:$F$211,$B15) -> 5 | Y16: =COUNTIFS(Y$19:Y$211,"<>0",$F$19:$F$211,$B15) -> 5 | Z16: =COUNTIFS(Z$19:Z$211,"<>0",$F$19:$F$211,$B15) -> 5 | AA16: =COUNTIFS(AA$19:AA$211,"<>0",$F$19:$F$211,$B15) -> 5 | AB16: =COUNTIFS(AB$19:AB$211,"<>0",$F$19:$F$211,$B15) -> 5 | AC16: =COUNTIFS(AC$19:AC$211,"<>0",$F$19:$F$211,$B15) -> 5 | AD16: =COUNTIFS(AD$19:AD$211,"<>0",$F$19:$F$211,$B15) -> 5 | AE16: =COUNTIFS(AE$19:AE$211,"<>0",$F$19:$F$211,$B15) -> 5 | ... AI16: =COUNTIFS(AI$19:AI$211,"<>0",$F$19:$F$211,$B15) -> 5 | AK16: =COUNTIFS(AK$19:AK$211,"<>0",$F$19:$F$211,$B15) -> 4 | AL16: =COUNTIFS(AL$19:AL$211,"<>0",$F$19:$F$211,$B15) -> 4 | AM16: =COUNTIFS(AM$19:AM$211,"<>0",$F$19:$F$211,$B15) -> 4 | AN16: =COUNTIFS(AN$19:AN$211,"<>0",$F$19:$F$211,$B15) -> 4 | AO16: =COUNTIFS(AO$19:AO$211,"<>0",$F$19:$F$211,$B15) -> 4 | AP16: =COUNTIFS(AP$19:AP$211,"<>0",$F$19:$F$211,$B15) -> 4 | AQ16: =COUNTIFS(AQ$19:AQ$211,"<>0",$F$19:$F$211,$B15) -> 4 | AR16: =COUNTIFS(AR$19:AR$211,"<>0",$F$19:$F$211,$B15) -> 4 | ... AV16: =COUNTIFS(AV$19:AV$211,"<>0",$F$19:$F$211,$B15) -> 4 | AX16: =COUNTIFS(AX$19:AX$211,"<>0",$F$19:$F$211,$B15) -> 4 | AY16: =COUNTIFS(AY$19:AY$211,"<>0",$F$19:$F$211,$B15) -> 4 | AZ16: =COUNTIFS(AZ$19:AZ$211,"<>0",$F$19:$F$211,$B15) -> 4 | BA16: =COUNTIFS(BA$19:BA$211,"<>0",$F$19:$F$211,$B15) -> 4 | BB16: =COUNTIFS(BB$19:BB$211,"<>0",$F$19:$F$211,$B15) -> 4 | BC16: =COUNTIFS(BC$19:BC$211,"<>0",$F$19:$F$211,$B15) -> 4 | BD16: =COUNTIFS(BD$19:BD$211,"<>0",$F$19:$F$211,$B15) -> 4 | BE16: =COUNTIFS(BE$19:BE$211,"<>0",$F$19:$F$211,$B15) -> 4 | ... BI16: =COUNTIFS(BI$19:BI$211,"<>0",$F$19:$F$211,$B15) -> 4 | BK16: =COUNTIFS(BK$19:BK$211,"<>0",$F$19:$F$211,$B15) -> 0 | BL16: =COUNTIFS(BL$19:BL$211,"<>0",$F$19:$F$211,$B15) -> 0 | BM16: =COUNTIFS(BM$19:BM$211,"<>0",$F$19:$F$211,$B15) -> 0 | BN16: =COUNTIFS(BN$19:BN$211,"<>0",$F$19:$F$211,$B15) -> 0 | BO16: =COUNTIFS(BO$19:BO$211,"<>0",$F$19:$F$211,$B15) -> 0 | BP16: =COUNTIFS(BP$19:BP$211,"<>0",$F$19:$F$211,$B15) -> 0 | BQ16: =COUNTIFS(BQ$19:BQ$211,"<>0",$F$19:$F$211,$B15) -> 0 | BR16: =COUNTIFS(BR$19:BR$211,"<>0",$F$19:$F$211,$B15) -> 0 | ... BV16: =COUNTIFS(BV$19:BV$211,"<>0",$F$19:$F$211,$B15) -> 0 | BX16: =COUNTIFS(BX$19:BX$211,"<>0",$F$19:$F$211,$B15) -> 0 | BY16: =COUNTIFS(BY$19:BY$211,"<>0",$F$19:$F$211,$B15) -> 0 | BZ16: =COUNTIFS(BZ$19:BZ$211,"<>0",$F$19:$F$211,$B15) -> 0 | CA16: =COUNTIFS(CA$19:CA$211,"<>0",$F$19:$F$211,$B15) -> 0 | CB16: =COUNTIFS(CB$19:CB$211,"<>0",$F$19:$F$211,$B15) -> 0 | CC16: =COUNTIFS(CC$19:CC$211,"<>0",$F$19:$F$211,$B15) -> 0 | CD16: =COUNTIFS(CD$19:CD$211,"<>0",$F$19:$F$211,$B15) -> 0 | CE16: =COUNTIFS(CE$19:CE$211,"<>0",$F$19:$F$211,$B15) -> 0 | ... CI16: =COUNTIFS(CI$19:CI$211,"<>0",$F$19:$F$211,$B15) -> 0 | CK16: =COUNTIFS(CK$19:CK$211,"<>0",$F$19:$F$211,$B15) -> 0 | CL16: =COUNTIFS(CL$19:CL$211,"<>0",$F$19:$F$211,$B15) -> 0 | CM16: =COUNTIFS(CM$19:CM$211,"<>0",$F$19:$F$211,$B15) -> 0 | CN16: =COUNTIFS(CN$19:CN$211,"<>0",$F$19:$F$211,$B15) -> 0 | CO16: =COUNTIFS(CO$19:CO$211,"<>0",$F$19:$F$211,$B15) -> 0 | CP16: =COUNTIFS(CP$19:CP$211,"<>0",$F$19:$F$211,$B15) -> 0 | CQ16: =COUNTIFS(CQ$19:CQ$211,"<>0",$F$19:$F$211,$B15) -> 0 | CR16: =COUNTIFS(CR$19:CR$211,"<>0",$F$19:$F$211,$B15) -> 0 | ... CV16: =COUNTIFS(CV$19:CV$211,"<>0",$F$19:$F$211,$B15) -> 0 | CX16: =COUNTIFS(CX$19:CX$211,"<>0",$F$19:$F$211,$B15) -> 4 | CY16: =COUNTIFS(CY$19:CY$211,"<>0",$F$19:$F$211,$B15) -> 4 | CZ16: =COUNTIFS(CZ$19:CZ$211,"<>0",$F$19:$F$211,$B15) -> 4 | DA16: =COUNTIFS(DA$19:DA$211,"<>0",$F$19:$F$211,$B15) -> 4 | DB16: =COUNTIFS(DB$19:DB$211,"<>0",$F$19:$F$211,$B15) -> 4 | DC16: =COUNTIFS(DC$19:DC$211,"<>0",$F$19:$F$211,$B15) -> 4 | DD16: =COUNTIFS(DD$19:DD$211,"<>0",$F$19:$F$211,$B15) -> 4 | DE16: =COUNTIFS(DE$19:DE$211,"<>0",$F$19:$F$211,$B15) -> 4 | ... DI16: =COUNTIFS(DI$19:DI$211,"<>0",$F$19:$F$211,$B15) -> 4 | DK16: =COUNTIFS(DK$19:DK$211,"<>0",$F$19:$F$211,$B15) -> 5 | DL16: =COUNTIFS(DL$19:DL$211,"<>0",$F$19:$F$211,$B15) -> 5 | DM16: =COUNTIFS(DM$19:DM$211,"<>0",$F$19:$F$211,$B15) -> 5 | DN16: =COUNTIFS(DN$19:DN$211,"<>0",$F$19:$F$211,$B15) -> 5 | DO16: =COUNTIFS(DO$19:DO$211,"<>0",$F$19:$F$211,$B15) -> 5 | DP16: =COUNTIFS(DP$19:DP$211,"<>0",$F$19:$F$211,$B15) -> 5 | DQ16: =COUNTIFS(DQ$19:DQ$211,"<>0",$F$19:$F$211,$B15) -> 5 | DR16: =COUNTIFS(DR$19:DR$211,"<>0",$F$19:$F$211,$B15) -> 5 | ... DV16: =COUNTIFS(DV$19:DV$211,"<>0",$F$19:$F$211,$B15) -> 5
V17: =SUBTOTAL(9,V20:V208) -> 252700 | W17: =DV17/V17 -> 1.7831631 | DK17: =SUBTOTAL(9,DK20:DK209) -> 115996.65 | DL17: =SUBTOTAL(9,DL20:DL211) -> 180227.79 | DM17: =SUBTOTAL(9,DM20:DM211) -> 296985.72 | DN17: =SUBTOTAL(9,DN20:DN208) -> 333881.15 | DO17: =SUBTOTAL(9,DO20:DO208) -> 389515.58 | DP17: =SUBTOTAL(9,DP20:DP208) -> 389515.58 | DQ17: =SUBTOTAL(9,DQ20:DQ208) -> 444846.78 | DR17: =SUBTOTAL(9,DR20:DR208) -> 450605.31 | DS17: =SUBTOTAL(9,DS20:DS208) -> 450605.31 | DT17: =SUBTOTAL(9,DT20:DT208) -> 450605.31 | DU17: =SUBTOTAL(9,DU20:DU208) -> 450605.31 | DV17: =SUBTOTAL(9,DV20:DV208) -> 450605.31 | DX17: =SUBTOTAL(9,DX174:DX208) -> 0
V18: =SUM(V20:V208) -> 2293995 | AK18: =MONTH(AK19) -> 1 | AL18: =MONTH(AL19) -> 2 | AM18: =MONTH(AM19) -> 3 | AN18: =MONTH(AN19) -> 4 | AO18: =MONTH(AO19) -> 5 | AP18: =MONTH(AP19) -> 6 | AQ18: =MONTH(AQ19) -> 7 | AR18: =MONTH(AR19) -> 8 | ... AV18: =MONTH(AV19) -> 12 | AX18: =MONTH(AX19) -> 1 | AY18: =MONTH(AY19) -> 2 | AZ18: =MONTH(AZ19) -> 3 | BA18: =MONTH(BA19) -> 4 | BB18: =MONTH(BB19) -> 5 | BC18: =MONTH(BC19) -> 6 | BD18: =MONTH(BD19) -> 7 | BE18: =MONTH(BE19) -> 8 | ... BI18: =MONTH(BI19) -> 12 | BK18: =MONTH(BK19) -> 1 | BL18: =MONTH(BL19) -> 2 | BM18: =MONTH(BM19) -> 3 | BN18: =MONTH(BN19) -> 4 | BO18: =MONTH(BO19) -> 5 | BP18: =MONTH(BP19) -> 6 | BQ18: =MONTH(BQ19) -> 7 | BR18: =MONTH(BR19) -> 8 | ... BV18: =MONTH(BV19) -> 12 | BX18: =MONTH(BX19) -> 1 | BY18: =MONTH(BY19) -> 2 | BZ18: =MONTH(BZ19) -> 3 | CA18: =MONTH(CA19) -> 4 | CB18: =MONTH(CB19) -> 5 | CC18: =MONTH(CC19) -> 6 | CD18: =MONTH(CD19) -> 7 | CE18: =MONTH(CE19) -> 8 | ... CI18: =MONTH(CI19) -> 12 | CK18: =MONTH(CK19) -> 1 | CL18: =MONTH(CL19) -> 2 | CM18: =MONTH(CM19) -> 3 | CN18: =MONTH(CN19) -> 4 | CO18: =MONTH(CO19) -> 5 | CP18: =MONTH(CP19) -> 6 | CQ18: =MONTH(CQ19) -> 7 | CR18: =MONTH(CR19) -> 8 | ... CV18: =MONTH(CV19) -> 12 | CX18: =MONTH(CX19) -> 1 | CY18: =MONTH(CY19) -> 2 | CZ18: =MONTH(CZ19) -> 3 | DA18: =MONTH(DA19) -> 4 | DB18: =MONTH(DB19) -> 5 | DC18: =MONTH(DC19) -> 6 | DD18: =MONTH(DD19) -> 7 | DE18: =MONTH(DE19) -> 8 | ... DI18: =MONTH(DI19) -> 12 | DK18: =MONTH(DK19) -> 1 | DL18: =MONTH(DL19) -> 2 | DM18: =MONTH(DM19) -> 3 | DN18: =MONTH(DN19) -> 4 | DO18: =MONTH(DO19) -> 5 | DP18: =MONTH(DP19) -> 6 | DQ18: =MONTH(DQ19) -> 7 | DR18: =MONTH(DR19) -> 8 | ... DV18: =MONTH(DV19) -> 12 | DX18: =MONTH(DX19) -> 12
B19: Cenário | C19: Fall Back | D19: ID/Nome | E19: Regime/Conta | F19: Classificação P&L | G19: BU | H19: Time TBAs | I19: Empresa | K19: 46023 | L19: 46054 | M19: 46082 | N19: 46113 | O19: 46143 | P19: 46174 | Q19: 46204 | R19: 46235 | S19: 46266 | T19: 46296 | U19: 46327 | V19: 46357 | X19: 46023 | Y19: 46054 | Z19: 46082 | AA19: 46113 | AB19: 46143 | AC19: 46174 | AD19: 46204 | AE19: 46235 | AF19: 46266 | AG19: 46296 | AH19: 46327 | AI19: 46357 | AK19: 46023 | AL19: 46054 | AM19: 46082 | AN19: 46113 | AO19: 46143 | AP19: 46174 | AQ19: 46204 | AR19: 46235 | AS19: 46266 | AT19: 46296 | AU19: 46327 | AV19: 46357 | AX19: 46023 | AY19: 46054 | AZ19: 46082 | BA19: 46113 | BB19: 46143 | BC19: 46174 | BD19: 46204 | BE19: 46235 | BF19: 46266 | BG19: 46296 | BH19: 46327 | BI19: 46357 | BK19: 46023 | BL19: 46054 | BM19: 46082 | BN19: 46113 | BO19: 46143 | BP19: 46174 | BQ19: 46204 | BR19: 46235 | BS19: 46266 | BT19: 46296 | BU19: 46327 | BV19: 46357 | BX19: 46023 | BY19: 46054 | BZ19: 46082 | CA19: 46113 | CB19: 46143 | CC19: 46174 | CD19: 46204 | CE19: 46235 | CF19: 46266 | CG19: 46296 | CH19: 46327 | CI19: 46357 | CK19: 46023 | CL19: 46054 | CM19: 46082 | CN19: 46113 | CO19: 46143 | CP19: 46174 | CQ19: 46204 | CR19: 46235 | CS19: 46266 | CT19: 46296 | CU19: 46327 | CV19: 46357 | CX19: 46023 | CY19: 46054 | CZ19: 46082 | DA19: 46113 | DB19: 46143 | DC19: 46174 | DD19: 46204 | DE19: 46235 | DF19: 46266 | DG19: 46296 | DH19: 46327 | DI19: 46357 | DK19: 46023 | DL19: 46054 | DM19: 46082 | DN19: 46113 | DO19: 46143 | DP19: 46174 | DQ19: 46204 | DR19: 46235 | DS19: 46266 | DT19: 46296 | DU19: 46327 | DV19: 46357 | DX19: 46357 | DZ19: CHECK
C20: Sem Fall Back | D20: 290 | E20: CLT | F20: Fopag | H20: PRODUTOS CORPORATE | I20: StartSe Sistemas | K20: 0 | L20: 0 | M20: 0 | N20: 0 | O20: 0 | P20: 0 | Q20: 0 | R20: 0 | S20: 0 | T20: 0 | U20: 0 | V20: 0 | X20: 0 | Y20: 0 | Z20: 0 | AA20: 0 | AB20: 0 | AC20: 0 | AD20: 0 | AE20: 0 | AF20: 0 | AG20: 0 | AH20: 0 | AI20: 0 | AK20: 0 | AL20: 0 | AM20: 0 | AN20: 0 | AO20: 0 | AP20: 0 | AQ20: 0 | AR20: 0 | AS20: 0 | AT20: 0 | AU20: 0 | AV20: 0 | AX20: 0 | AY20: 0 | AZ20: 0 | BA20: 0 | BB20: 0 | BC20: 0 | BD20: 0 | BE20: 0 | BF20: 0 | BG20: 0 | BH20: 0 | BI20: 0 | BK20: 0 | BL20: 0 | BM20: 0 | BN20: 0 | BO20: 0 | BP20: 0 | BQ20: 0 | BR20: 0 | BS20: 0 | BT20: 0 | BU20: 0 | BV20: 0 | BX20: 0 | BY20: 0 | BZ20: 0 | CA20: 0 | CB20: 0 | CC20: 0 | CD20: 0 | CE20: 0 | CF20: 0 | CG20: 0 | CH20: 0 | CI20: 0 | CK20: 0 | CL20: 0 | CM20: 0 | CN20: 0 | CO20: 0 | CP20: 0 | CQ20: 0 | CR20: 0 | CS20: 0 | CT20: 0 | CU20: 0 | CV20: 0 | CX20: 0 | CY20: 0 | CZ20: 0 | DA20: 0 | DB20: 0 | DC20: 0 | DD20: 0 | DE20: 0 | DF20: 0 | DG20: 0 | DH20: 0 | DI20: 0 | DK20: 0 | DL20: 0 | DM20: 0 | DN20: 0 | DO20: 0 | DP20: 0 | DQ20: 0 | DR20: 0 | DS20: 0 | DT20: 0 | DU20: 0 | DV20: 0 | DX20: =SUM(DK20:DV20) -> 0 | DZ20: =ROUND(SUM(X20:AI20,BK20:BV20,BX20:CI20,CX20:DI20,CK20:CV20),2)=ROUND(SUM(DK20:DV20),2) -> TRUE | EB20: =#REF!/4 -> #REF!
C21: Sem Fall Back | D21: Acompanhamento Missões Internacionais | E21: Outras despesas com folha | F21: Custos com Pessoal | G21: Imersões Internacionais | H21: Outras despesas | I21: StartSe Sistemas | K21: 0 | L21: 0 | M21: 37500 | P21: 41250 | Q21: 41250 | R21: 37500 | S21: 112500 | T21: 41250 | U21: 37500 | V21: 41250 | X21: 0 | Y21: 0 | Z21: 37500 | AA21: 0 | AB21: 0 | AC21: 41250 | AD21: 41250 | AE21: 37500 | AF21: 112500 | AG21: 41250 | AH21: 37500 | AI21: 41250 | AK21: 0 | AL21: 0 | AM21: 0 | AN21: 0 | AO21: 0 | AP21: 0 | AQ21: 0 | AR21: 0 | AS21: 0 | AT21: 0 | AU21: 0 | AV21: 0 | AX21: 0 | AY21: 0 | AZ21: 0 | BA21: 0 | BB21: 0 | BC21: 0 | BD21: 0 | BE21: 0 | BF21: 0 | BG21: 0 | BH21: 0 | BI21: 0 | BK21: 0 | BL21: 0 | BM21: 0 | BN21: 0 | BO21: 0 | BP21: 0 | BQ21: 0 | BR21: 0 | BS21: 0 | BT21: 0 | BU21: 0 | BV21: 0 | BX21: 0 | BY21: 0 | BZ21: 0 | CA21: 0 | CB21: 0 | CC21: 0 | CD21: 0 | CE21: 0 | CF21: 0 | CG21: 0 | CH21: 0 | CI21: 0 | CK21: 0 | CL21: 0 | CM21: 0 | CN21: 0 | CO21: 0 | CP21: 0 | CQ21: 0 | CR21: 0 | CS21: 0 | CT21: 0 | CU21: 0 | CV21: 0 | CX21: 0 | CY21: 0 | CZ21: 0 | DA21: 0 | DB21: 0 | DC21: 0 | DD21: 0 | DE21: 0 | DF21: 0 | DG21: 0 | DH21: 0 | DI21: 0 | DK21: 0 | DL21: 0 | DM21: 37500 | DN21: 0 | DO21: 0 | DP21: 41250 | DQ21: 41250 | DR21: 37500 | DS21: 112500 | DT21: 41250 | DU21: 37500 | DV21: 41250 | DX21: =SUM(DK21:DV21) -> 390000 | DZ21: =ROUND(SUM(X21:AI21,BK21:BV21,BX21:CI21,CX21:DI21,CK21:CV21),2)=ROUND(SUM(DK21:DV21),2) -> TRUE | EB21: =EB20/12 -> #REF!
B22: Arrojado | C22: Sem Fall Back | D22: TBA 14 | E22: Estágio | F22: Fopag | H22: Tech | I22: StartSe Consulting | K22: 0 | L22: 0 | M22: 2500 | N22: 2500 | O22: 2500 | P22: 2500 | Q22: 2500 | R22: 2500 | S22: 2500 | T22: 2500 | U22: 2500 | V22: 2500 | X22: 0 | Y22: 0 | Z22: 2500 | AA22: 2500 | AB22: 2500 | AC22: 2500 | AD22: 2500 | AE22: 2500 | AF22: 2500 | AG22: 2500 | AH22: 2500 | AI22: 2500 | AK22: 0 | AL22: 0 | AM22: 0 | AN22: 0 | AO22: 0 | AP22: 0 | AQ22: 0 | AR22: 0 | AS22: 0 | AT22: 0 | AU22: 0 | AV22: 0 | AX22: 0 | AY22: 0 | AZ22: 0 | BA22: 0 | BB22: 0 | BC22: 0 | BD22: 0 | BE22: 0 | BF22: 0 | BG22: 0 | BH22: 0 | BI22: 0 | BK22: 0 | BL22: 0 | BM22: 0 | BN22: 0 | BO22: 0 | BP22: 0 | BQ22: 0 | BR22: 0 | BS22: 0 | BT22: 0 | BU22: 0 | BV22: 0 | BX22: 0 | BY22: 0 | BZ22: 1100 | CA22: 1100 | CB22: 1100 | CC22: 1100 | CD22: 1100 | CE22: 1100 | CF22: 1100 | CG22: 1100 | CH22: 1100 | CI22: 1100 | CK22: 0 | CL22: 0 | CM22: 208.33333 | CN22: 208.33333 | CO22: 208.33333 | CP22: 208.33333 | CQ22: 208.33333 | CR22: 208.33333 | CS22: 208.33333 | CT22: 208.33333 | CU22: 208.33333 | CV22: 208.33333 | CX22: 0 | CY22: 0 | CZ22: 0 | DA22: 0 | DB22: 0 | DC22: 0 | DD22: 0 | DE22: 0 | DF22: 0 | DG22: 0 | DH22: 0 | DI22: 0 | DK22: 0 | DL22: 0 | DM22: 3808.3333 | DN22: 3808.3333 | DO22: 3808.3333 | DP22: 3808.3333 | DQ22: 3808.3333 | DR22: 3808.3333 | DS22: 3808.3333 | DT22: 3808.3333 | DU22: 3808.3333 | DV22: 3808.3333 | DX22: =SUM(DK22:DV22) -> 38083.333 | DZ22: =ROUND(SUM(X22:AI22,BK22:BV22,BX22:CI22,CX22:DI22,CK22:CV22),2)=ROUND(SUM(DK22:DV22),2) -> TRUE | EB22: =EB21/(22*8) -> #REF!
B23: Arrojado | C23: Sem Fall Back | D23: TBA 15 | E23: Estágio | F23: Fopag | H23: Tech | I23: StartSe Consulting | K23: 0 | L23: 0 | O23: 2500 | P23: 2500 | Q23: 2500 | R23: 2500 | S23: 2500 | T23: 2500 | U23: 2500 | V23: 2500 | X23: 0 | Y23: 0 | Z23: 0 | AA23: 0 | AB23: 2500 | AC23: 2500 | AD23: 2500 | AE23: 2500 | AF23: 2500 | AG23: 2500 | AH23: 2500 | AI23: 2500 | AK23: 0 | AL23: 0 | AM23: 0 | AN23: 0 | AO23: 0 | AP23: 0 | AQ23: 0 | AR23: 0 | AS23: 0 | AT23: 0 | AU23: 0 | AV23: 0 | AX23: 0 | AY23: 0 | AZ23: 0 | BA23: 0 | BB23: 0 | BC23: 0 | BD23: 0 | BE23: 0 | BF23: 0 | BG23: 0 | BH23: 0 | BI23: 0 | BK23: 0 | BL23: 0 | BM23: 0 | BN23: 0 | BO23: 0 | BP23: 0 | BQ23: 0 | BR23: 0 | BS23: 0 | BT23: 0 | BU23: 0 | BV23: 0 | BX23: 0 | BY23: 0 | BZ23: 0 | CA23: 0 | CB23: 1100 | CC23: 1100 | CD23: 1100 | CE23: 1100 | CF23: 1100 | CG23: 1100 | CH23: 1100 | CI23: 1100 | CK23: 0 | CL23: 0 | CM23: 0 | CN23: 0 | CO23: 208.33333 | CP23: 208.33333 | CQ23: 208.33333 | CR23: 208.33333 | CS23: 208.33333 | CT23: 208.33333 | CU23: 208.33333 | CV23: 208.33333 | CX23: 0 | CY23: 0 | CZ23: 0 | DA23: 0 | DB23: 0 | DC23: 0 | DD23: 0 | DE23: 0 | DF23: 0 | DG23: 0 | DH23: 0 | DI23: 0 | DK23: 0 | DL23: 0 | DM23: 0 | DN23: 0 | DO23: 3808.3333 | DP23: 3808.3333 | DQ23: 3808.3333 | DR23: 3808.3333 | DS23: 3808.3333 | DT23: 3808.3333 | DU23: 3808.3333 | DV23: 3808.3333 | DX23: =SUM(DK23:DV23) -> 30466.667 | DZ23: =ROUND(SUM(X23:AI23,BK23:BV23,BX23:CI23,CX23:DI23,CK23:CV23),2)=ROUND(SUM(DK23:DV23),2) -> TRUE
B24: Arrojado | C24: Sem Fall Back | D24: TBA 16 | E24: Estágio | F24: Fopag | H24: Tech | I24: StartSe Consulting | K24: 0 | L24: 0 | Q24: 2500 | R24: 2500 | S24: 2500 | T24: 2500 | U24: 2500 | V24: 2500 | X24: 0 | Y24: 0 | Z24: 0 | AA24: 0 | AB24: 0 | AC24: 0 | AD24: 2500 | AE24: 2500 | AF24: 2500 | AG24: 2500 | AH24: 2500 | AI24: 2500 | AK24: 0 | AL24: 0 | AM24: 0 | AN24: 0 | AO24: 0 | AP24: 0 | AQ24: 0 | AR24: 0 | AS24: 0 | AT24: 0 | AU24: 0 | AV24: 0 | AX24: 0 | AY24: 0 | AZ24: 0 | BA24: 0 | BB24: 0 | BC24: 0 | BD24: 0 | BE24: 0 | BF24: 0 | BG24: 0 | BH24: 0 | BI24: 0 | BK24: 0 | BL24: 0 | BM24: 0 | BN24: 0 | BO24: 0 | BP24: 0 | BQ24: 0 | BR24: 0 | BS24: 0 | BT24: 0 | BU24: 0 | BV24: 0 | BX24: 0 | BY24: 0 | BZ24: 0 | CA24: 0 | CB24: 0 | CC24: 0 | CD24: 1100 | CE24: 1100 | CF24: 1100 | CG24: 1100 | CH24: 1100 | CI24: 1100 | CK24: 0 | CL24: 0 | CM24: 0 | CN24: 0 | CO24: 0 | CP24: 0 | CQ24: 208.33333 | CR24: 208.33333 | CS24: 208.33333 | CT24: 208.33333 | CU24: 208.33333 | CV24: 208.33333 | CX24: 0 | CY24: 0 | CZ24: 0 | DA24: 0 | DB24: 0 | DC24: 0 | DD24: 0 | DE24: 0 | DF24: 0 | DG24: 0 | DH24: 0 | DI24: 0 | DK24: 0 | DL24: 0 | DM24: 0 | DN24: 0 | DO24: 0 | DP24: 0 | DQ24: 3808.3333 | DR24: 3808.3333 | DS24: 3808.3333 | DT24: 3808.3333 | DU24: 3808.3333 | DV24: 3808.3333 | DX24: =SUM(DK24:DV24) -> 22850 | DZ24: =ROUND(SUM(X24:AI24,BK24:BV24,BX24:CI24,CX24:DI24,CK24:CV24),2)=ROUND(SUM(DK24:DV24),2) -> TRUE
B25: Base | C25: Sem Fall Back | D25: TBA 18 | E25: CLT | F25: Fopag | H25: Vendas B2B | I25: StartSe Sistemas | K25: 0 | L25: 0 | M25: 10500 | N25: 10500 | O25: 10500 | P25: 10500 | Q25: 10500 | R25: 10500 | S25: 10500 | T25: 10500 | U25: 10500 | V25: 10500 | X25: 0 | Y25: 0 | Z25: 10500 | AA25: 10500 | AB25: 11042.85 | AC25: 11042.85 | AD25: 11042.85 | AE25: 11042.85 | AF25: 11042.85 | AG25: 11042.85 | AH25: 11042.85 | AI25: 11042.85 | AK25: 0 | AL25: 0 | AM25: 1717.079 | AN25: 1717.079 | AO25: 1866.3628 | AP25: 1866.3628 | AQ25: 1866.3628 | AR25: 1866.3628 | AS25: 1866.3628 | AT25: 1866.3628 | AU25: 1866.3628 | AV25: 1866.3628 | AX25: 0 | AY25: 0 | AZ25: 951.6344 | BA25: 951.6344 | BB25: 951.6344 | BC25: 951.6344 | BD25: 951.6344 | BE25: 951.6344 | BF25: 951.6344 | BG25: 951.6344 | BH25: 951.6344 | BI25: 951.6344 | BK25: 0 | BL25: 0 | BM25: 1172.5 | BN25: 1172.5 | BO25: 1233.1182 | BP25: 1233.1182 | BQ25: 1233.1182 | BR25: 1233.1182 | BS25: 1233.1182 | BT25: 1233.1182 | BU25: 1233.1182 | BV25: 1233.1182 | BX25: 0 | BY25: 0 | BZ25: 2895.9438 | CA25: 2895.9438 | CB25: 2934.7738 | CC25: 2934.7738 | CD25: 2934.7738 | CE25: 2934.7738 | CF25: 2934.7738 | CG25: 2934.7738 | CH25: 2934.7738 | CI25: 2934.7738 | CK25: 0 | CL25: 0 | CM25: 1563.3333 | CN25: 1563.3333 | CO25: 1644.1577 | CP25: 1644.1577 | CQ25: 1644.1577 | CR25: 1644.1577 | CS25: 1644.1577 | CT25: 1644.1577 | CU25: 1644.1577 | CV25: 1644.1577 | CX25: 0 | CY25: 0 | CZ25: 3570 | DA25: 3570 | DB25: 3754.569 | DC25: 3754.569 | DD25: 3754.569 | DE25: 3754.569 | DF25: 3754.569 | DG25: 3754.569 | DH25: 3754.569 | DI25: 3754.569 | DK25: 0 | DL25: 0 | DM25: 19701.777 | DN25: 19701.777 | DO25: 20609.469 | DP25: 20609.469 | DQ25: 20609.469 | DR25: 20609.469 | DS25: 20609.469 | DT25: 20609.469 | DU25: 20609.469 | DV25: 20609.469 | DX25: =SUM(DK25:DV25) -> 204279.3 | DZ25: =ROUND(SUM(X25:AI25,BK25:BV25,BX25:CI25,CX25:DI25,CK25:CV25),2)=ROUND(SUM(DK25:DV25),2) -> TRUE
C26: Sem Fall Back | D26: TBA 29 | E26: CLT | F26: Fopag | H26: Vendas B2B | I26: StartSe Sistemas | K26: 0 | L26: 0 | M26: 13000 | N26: 13000 | O26: 13000 | P26: 13000 | Q26: 13000 | R26: 13000 | S26: 13000 | T26: 13000 | U26: 13000 | V26: 13000 | X26: 0 | Y26: 0 | Z26: 13000 | AA26: 13000 | AB26: 13672.1 | AC26: 13672.1 | AD26: 13672.1 | AE26: 13672.1 | AF26: 13672.1 | AG26: 13672.1 | AH26: 13672.1 | AI26: 13672.1 | AK26: 0 | AL26: 0 | AM26: 2404.579 | AN26: 2404.579 | AO26: 2589.4065 | AP26: 2589.4065 | AQ26: 2589.4065 | AR26: 2589.4065 | AS26: 2589.4065 | AT26: 2589.4065 | AU26: 2589.4065 | AV26: 2589.4065 | AX26: 0 | AY26: 0 | AZ26: 951.6344 | BA26: 951.6344 | BB26: 951.6344 | BC26: 951.6344 | BD26: 951.6344 | BE26: 951.6344 | BF26: 951.6344 | BG26: 951.6344 | BH26: 951.6344 | BI26: 951.6344 | BK26: 0 | BL26: 0 | BM26: 1451.6667 | BN26: 1451.6667 | BO26: 1526.7178 | BP26: 1526.7178 | BQ26: 1526.7178 | BR26: 1526.7178 | BS26: 1526.7178 | BT26: 1526.7178 | BU26: 1526.7178 | BV26: 1526.7178 | BX26: 0 | BY26: 0 | BZ26: 3074.7683 | CA26: 3074.7683 | CB26: 3122.8435 | CC26: 3122.8435 | CD26: 3122.8435 | CE26: 3122.8435 | CF26: 3122.8435 | CG26: 3122.8435 | CH26: 3122.8435 | CI26: 3122.8435 | CK26: 0 | CL26: 0 | CM26: 1935.5556 | CN26: 1935.5556 | CO26: 2035.6238 | CP26: 2035.6238 | CQ26: 2035.6238 | CR26: 2035.6238 | CS26: 2035.6238 | CT26: 2035.6238 | CU26: 2035.6238 | CV26: 2035.6238 | CX26: 0 | CY26: 0 | CZ26: 4420 | DA26: 4420 | DB26: 4648.514 | DC26: 4648.514 | DD26: 4648.514 | DE26: 4648.514 | DF26: 4648.514 | DG26: 4648.514 | DH26: 4648.514 | DI26: 4648.514 | DK26: 0 | DL26: 0 | DM26: 23881.991 | DN26: 23881.991 | DO26: 25005.799 | DP26: 25005.799 | DQ26: 25005.799 | DR26: 25005.799 | DS26: 25005.799 | DT26: 25005.799 | DU26: 25005.799 | DV26: 25005.799 | DX26: =SUM(DK26:DV26) -> 247810.37 | DZ26: =ROUND(SUM(X26:AI26,BK26:BV26,BX26:CI26,CX26:DI26,CK26:CV26),2)=ROUND(SUM(DK26:DV26),2) -> TRUE
C27: Sem Fall Back | D27: TBA 30 | E27: CLT | F27: Fopag | H27: Vendas B2B | I27: StartSe Sistemas | K27: 0 | L27: 0 | N27: 16000 | O27: 16000 | P27: 16000 | Q27: 16000 | R27: 16000 | S27: 16000 | T27: 16000 | U27: 16000 | V27: 16000 | X27: 0 | Y27: 0 | Z27: 0 | AA27: 16000 | AB27: 16800 | AC27: 16800 | AD27: 16800 | AE27: 16800 | AF27: 16800 | AG27: 16800 | AH27: 16800 | AI27: 16800 | AK27: 0 | AL27: 0 | AM27: 0 | AN27: 3229.579 | AO27: 3449.579 | AP27: 3449.579 | AQ27: 3449.579 | AR27: 3449.579 | AS27: 3449.579 | AT27: 3449.579 | AU27: 3449.579 | AV27: 3449.579 | AX27: 0 | AY27: 0 | AZ27: 0 | BA27: 951.6344 | BB27: 951.6344 | BC27: 951.6344 | BD27: 951.6344 | BE27: 951.6344 | BF27: 951.6344 | BG27: 951.6344 | BH27: 951.6344 | BI27: 951.6344 | BK27: 0 | BL27: 0 | BM27: 0 | BN27: 1786.6667 | BO27: 1876 | BP27: 1876 | BQ27: 1876 | BR27: 1876 | BS27: 1876 | BT27: 1876 | BU27: 1876 | BV27: 1876 | BX27: 0 | BY27: 0 | BZ27: 0 | CA27: 3289.3577 | CB27: 3346.5815 | CC27: 3346.5815 | CD27: 3346.5815 | CE27: 3346.5815 | CF27: 3346.5815 | CG27: 3346.5815 | CH27: 3346.5815 | CI27: 3346.5815 | CK27: 0 | CL27: 0 | CM27: 0 | CN27: 2382.2222 | CO27: 2501.3333 | CP27: 2501.3333 | CQ27: 2501.3333 | CR27: 2501.3333 | CS27: 2501.3333 | CT27: 2501.3333 | CU27: 2501.3333 | CV27: 2501.3333 | CX27: 0 | CY27: 0 | CZ27: 0 | DA27: 5440 | DB27: 5712 | DC27: 5712 | DD27: 5712 | DE27: 5712 | DF27: 5712 | DG27: 5712 | DH27: 5712 | DI27: 5712 | DK27: 0 | DL27: 0 | DM27: 0 | DN27: 28898.247 | DO27: 30235.915 | DP27: 30235.915 | DQ27: 30235.915 | DR27: 30235.915 | DS27: 30235.915 | DT27: 30235.915 | DU27: 30235.915 | DV27: 30235.915 | DX27: =SUM(DK27:DV27) -> 270785.57 | DZ27: =ROUND(SUM(X27:AI27,BK27:BV27,BX27:CI27,CX27:DI27,CK27:CV27),2)=ROUND(SUM(DK27:DV27),2) -> TRUE
C28: Sem Fall Back | D28: TBA 31 | E28: CLT | F28: Fopag | H28: Vendas B2C | I28: StartSe Sistemas | K28: 0 | L28: 0 | N28: 3500 | O28: 3500 | P28: 3500 | Q28: 3500 | R28: 3500 | S28: 3500 | T28: 3500 | U28: 3500 | V28: 3500 | X28: 0 | Y28: 0 | Z28: 0 | AA28: 3500 | AB28: 3680.95 | AC28: 3680.95 | AD28: 3680.95 | AE28: 3680.95 | AF28: 3680.95 | AG28: 3680.95 | AH28: 3680.95 | AI28: 3680.95 | AK28: 0 | AL28: 0 | AM28: 0 | AN28: 83.82921 | AO28: 107.71461 | AP28: 107.71461 | AQ28: 107.71461 | AR28: 107.71461 | AS28: 107.71461 | AT28: 107.71461 | AU28: 107.71461 | AV28: 107.71461 | AX28: 0 | AY28: 0 | AZ28: 0 | BA28: 313.4136 | BB28: 335.1276 | BC28: 335.1276 | BD28: 335.1276 | BE28: 335.1276 | BF28: 335.1276 | BG28: 335.1276 | BH28: 335.1276 | BI28: 335.1276 | BK28: 0 | BL28: 0 | BM28: 0 | BN28: 390.83333 | BO28: 411.03942 | BP28: 411.03942 | BQ28: 411.03942 | BR28: 411.03942 | BS28: 411.03942 | BT28: 411.03942 | BU28: 411.03942 | BV28: 411.03942 | BX28: 0 | BY28: 0 | BZ28: 0 | CA28: 2395.2353 | CB28: 2408.1786 | CC28: 2408.1786 | CD28: 2408.1786 | CE28: 2408.1786 | CF28: 2408.1786 | CG28: 2408.1786 | CH28: 2408.1786 | CI28: 2408.1786 | CK28: 0 | CL28: 0 | CM28: 0 | CN28: 521.11111 | CO28: 548.05256 | CP28: 548.05256 | CQ28: 548.05256 | CR28: 548.05256 | CS28: 548.05256 | CT28: 548.05256 | CU28: 548.05256 | CV28: 548.05256 | CX28: 0 | CY28: 0 | CZ28: 0 | DA28: 1190 | DB28: 1251.523 | DC28: 1251.523 | DD28: 1251.523 | DE28: 1251.523 | DF28: 1251.523 | DG28: 1251.523 | DH28: 1251.523 | DI28: 1251.523 | DK28: 0 | DL28: 0 | DM28: 0 | DN28: 7997.1797 | DO28: 8299.7436 | DP28: 8299.7436 | DQ28: 8299.7436 | DR28: 8299.7436 | DS28: 8299.7436 | DT28: 8299.7436 | DU28: 8299.7436 | DV28: 8299.7436 | DX28: =SUM(DK28:DV28) -> 74395.128 | DZ28: =ROUND(SUM(X28:AI28,BK28:BV28,BX28:CI28,CX28:DI28,CK28:CV28),2)=ROUND(SUM(DK28:DV28),2) -> TRUE
C29: Sem Fall Back | D29: TBA 32 | E29: CLT | F29: Fopag | H29: Vendas B2C | I29: StartSe Sistemas | K29: 0 | L29: 0 | M29: 4600 | N29: 4600 | O29: 4600 | P29: 4600 | Q29: 4600 | R29: 4600 | S29: 4600 | T29: 4600 | U29: 4600 | V29: 4600 | X29: 0 | Y29: 0 | Z29: 4600 | AA29: 4600 | AB29: 4837.82 | AC29: 4837.82 | AD29: 4837.82 | AE29: 4837.82 | AF29: 4837.82 | AG29: 4837.82 | AH29: 4837.82 | AI29: 4837.82 | AK29: 0 | AL29: 0 | AM29: 257.45317 | AN29: 257.45317 | AO29: 303.47135 | AP29: 303.47135 | AQ29: 303.47135 | AR29: 303.47135 | AS29: 303.47135 | AT29: 303.47135 | AU29: 303.47135 | AV29: 303.47135 | AX29: 0 | AY29: 0 | AZ29: 453.597 | BA29: 453.597 | BB29: 486.8918 | BC29: 486.8918 | BD29: 486.8918 | BE29: 486.8918 | BF29: 486.8918 | BG29: 486.8918 | BH29: 486.8918 | BI29: 486.8918 | BK29: 0 | BL29: 0 | BM29: 513.66667 | BN29: 513.66667 | BO29: 540.22323 | BP29: 540.22323 | BQ29: 540.22323 | BR29: 540.22323 | BS29: 540.22323 | BT29: 540.22323 | BU29: 540.22323 | BV29: 540.22323 | BX29: 0 | BY29: 0 | BZ29: 2473.9181 | CA29: 2473.9181 | CB29: 2490.9293 | CC29: 2490.9293 | CD29: 2490.9293 | CE29: 2490.9293 | CF29: 2490.9293 | CG29: 2490.9293 | CH29: 2490.9293 | CI29: 2490.9293 | CK29: 0 | CL29: 0 | CM29: 684.88889 | CN29: 684.88889 | CO29: 720.29764 | CP29: 720.29764 | CQ29: 720.29764 | CR29: 720.29764 | CS29: 720.29764 | CT29: 720.29764 | CU29: 720.29764 | CV29: 720.29764 | CX29: 0 | CY29: 0 | CZ29: 1564 | DA29: 1564 | DB29: 1644.8588 | DC29: 1644.8588 | DD29: 1644.8588 | DE29: 1644.8588 | DF29: 1644.8588 | DG29: 1644.8588 | DH29: 1644.8588 | DI29: 1644.8588 | DK29: 0 | DL29: 0 | DM29: 9836.4736 | DN29: 9836.4736 | DO29: 10234.129 | DP29: 10234.129 | DQ29: 10234.129 | DR29: 10234.129 | DS29: 10234.129 | DT29: 10234.129 | DU29: 10234.129 | DV29: 10234.129 | DX29: =SUM(DK29:DV29) -> 101545.98 | DZ29: =ROUND(SUM(X29:AI29,BK29:BV29,BX29:CI29,CX29:DI29,CK29:CV29),2)=ROUND(SUM(DK29:DV29),2) -> TRUE
C30: Sem Fall Back | D30: TBA 33 | E30: CLT | F30: Fopag | H30: Vendas B2C | I30: StartSe Sistemas | K30: 0 | L30: 0 | M30: 5200 | N30: 5200 | O30: 5200 | P30: 5200 | Q30: 5200 | R30: 5200 | S30: 5200 | T30: 5200 | U30: 5200 | V30: 5200 | X30: 0 | Y30: 0 | Z30: 5200 | AA30: 5200 | AB30: 5468.84 | AC30: 5468.84 | AD30: 5468.84 | AE30: 5468.84 | AF30: 5468.84 | AG30: 5468.84 | AH30: 5468.84 | AI30: 5468.84 | AK30: 0 | AL30: 0 | AM30: 373.55318 | AN30: 373.55318 | AO30: 437.01999 | AP30: 437.01999 | AQ30: 437.01999 | AR30: 437.01999 | AS30: 437.01999 | AT30: 437.01999 | AU30: 437.01999 | AV30: 437.01999 | AX30: 0 | AY30: 0 | AZ30: 537.597 | BA30: 537.597 | BB30: 575.2346 | BC30: 575.2346 | BD30: 575.2346 | BE30: 575.2346 | BF30: 575.2346 | BG30: 575.2346 | BH30: 575.2346 | BI30: 575.2346 | BK30: 0 | BL30: 0 | BM30: 580.66667 | BN30: 580.66667 | BO30: 610.68713 | BP30: 610.68713 | BQ30: 610.68713 | BR30: 610.68713 | BS30: 610.68713 | BT30: 610.68713 | BU30: 610.68713 | BV30: 610.68713 | BX30: 0 | BY30: 0 | BZ30: 2516.8359 | CA30: 2516.8359 | CB30: 2536.066 | CC30: 2536.066 | CD30: 2536.066 | CE30: 2536.066 | CF30: 2536.066 | CG30: 2536.066 | CH30: 2536.066 | CI30: 2536.066 | CK30: 0 | CL30: 0 | CM30: 774.22222 | CN30: 774.22222 | CO30: 814.24951 | CP30: 814.24951 | CQ30: 814.24951 | CR30: 814.24951 | CS30: 814.24951 | CT30: 814.24951 | CU30: 814.24951 | CV30: 814.24951 | CX30: 0 | CY30: 0 | CZ30: 1768 | DA30: 1768 | DB30: 1859.4056 | DC30: 1859.4056 | DD30: 1859.4056 | DE30: 1859.4056 | DF30: 1859.4056 | DG30: 1859.4056 | DH30: 1859.4056 | DI30: 1859.4056 | DK30: 0 | DL30: 0 | DM30: 10839.725 | DN30: 10839.725 | DO30: 11289.248 | DP30: 11289.248 | DQ30: 11289.248 | DR30: 11289.248 | DS30: 11289.248 | DT30: 11289.248 | DU30: 11289.248 | DV30: 11289.248 | DX30: =SUM(DK30:DV30) -> 111993.44 | DZ30: =ROUND(SUM(X30:AI30,BK30:BV30,BX30:CI30,CX30:DI30,CK30:CV30),2)=ROUND(SUM(DK30:DV30),2) -> TRUE
C31: Sem Fall Back | D31: TBA 34 | E31: CLT | F31: Fopag | H31: Vendas B2C | I31: StartSe Sistemas | K31: 0 | L31: 0 | M31: 5200 | N31: 5200 | O31: 5200 | P31: 5200 | Q31: 5200 | R31: 5200 | S31: 5200 | T31: 5200 | U31: 5200 | V31: 5200 | X31: 0 | Y31: 0 | Z31: 5200 | AA31: 5200 | AB31: 5468.84 | AC31: 5468.84 | AD31: 5468.84 | AE31: 5468.84 | AF31: 5468.84 | AG31: 5468.84 | AH31: 5468.84 | AI31: 5468.84 | AK31: 0 | AL31: 0 | AM31: 373.55318 | AN31: 373.55318 | AO31: 437.01999 | AP31: 437.01999 | AQ31: 437.01999 | AR31: 437.01999 | AS31: 437.01999 | AT31: 437.01999 | AU31: 437.01999 | AV31: 437.01999 | AX31: 0 | AY31: 0 | AZ31: 537.597 | BA31: 537.597 | BB31: 575.2346 | BC31: 575.2346 | BD31: 575.2346 | BE31: 575.2346 | BF31: 575.2346 | BG31: 575.2346 | BH31: 575.2346 | BI31: 575.2346 | BK31: 0 | BL31: 0 | BM31: 580.66667 | BN31: 580.66667 | BO31: 610.68713 | BP31: 610.68713 | BQ31: 610.68713 | BR31: 610.68713 | BS31: 610.68713 | BT31: 610.68713 | BU31: 610.68713 | BV31: 610.68713 | BX31: 0 | BY31: 0 | BZ31: 2516.8359 | CA31: 2516.8359 | CB31: 2536.066 | CC31: 2536.066 | CD31: 2536.066 | CE31: 2536.066 | CF31: 2536.066 | CG31: 2536.066 | CH31: 2536.066 | CI31: 2536.066 | CK31: 0 | CL31: 0 | CM31: 774.22222 | CN31: 774.22222 | CO31: 814.24951 | CP31: 814.24951 | CQ31: 814.24951 | CR31: 814.24951 | CS31: 814.24951 | CT31: 814.24951 | CU31: 814.24951 | CV31: 814.24951 | CX31: 0 | CY31: 0 | CZ31: 1768 | DA31: 1768 | DB31: 1859.4056 | DC31: 1859.4056 | DD31: 1859.4056 | DE31: 1859.4056 | DF31: 1859.4056 | DG31: 1859.4056 | DH31: 1859.4056 | DI31: 1859.4056 | DK31: 0 | DL31: 0 | DM31: 10839.725 | DN31: 10839.725 | DO31: 11289.248 | DP31: 11289.248 | DQ31: 11289.248 | DR31: 11289.248 | DS31: 11289.248 | DT31: 11289.248 | DU31: 11289.248 | DV31: 11289.248 | DX31: =SUM(DK31:DV31) -> 111993.44 | DZ31: =ROUND(SUM(X31:AI31,BK31:BV31,BX31:CI31,CX31:DI31,CK31:CV31),2)=ROUND(SUM(DK31:DV31),2) -> TRUE
C32: Sem Fall Back | D32: TBA 35 | E32: CLT | F32: Fopag | H32: Vendas B2C | I32: StartSe Sistemas | K32: 0 | L32: 0 | M32: 0 | N32: 0 | O32: 0 | P32: 0 | Q32: 15000 | R32: 15000 | S32: 15000 | T32: 15000 | U32: 15000 | V32: 15000 | X32: 0 | Y32: 0 | Z32: 0 | AA32: 0 | AB32: 0 | AC32: 0 | AD32: 15775.5 | AE32: 15775.5 | AF32: 15775.5 | AG32: 15775.5 | AH32: 15775.5 | AI32: 15775.5 | AK32: 0 | AL32: 0 | AM32: 0 | AN32: 0 | AO32: 0 | AP32: 0 | AQ32: 3167.8415 | AR32: 3167.8415 | AS32: 3167.8415 | AT32: 3167.8415 | AU32: 3167.8415 | AV32: 3167.8415 | AX32: 0 | AY32: 0 | AZ32: 0 | BA32: 0 | BB32: 0 | BC32: 0 | BD32: 951.6344 | BE32: 951.6344 | BF32: 951.6344 | BG32: 951.6344 | BH32: 951.6344 | BI32: 951.6344 | BK32: 0 | BL32: 0 | BM32: 0 | BN32: 0 | BO32: 0 | BP32: 0 | BQ32: 1761.5975 | BR32: 1761.5975 | BS32: 1761.5975 | BT32: 1761.5975 | BU32: 1761.5975 | BV32: 1761.5975 | BX32: 0 | BY32: 0 | BZ32: 0 | CA32: 0 | CB32: 0 | CC32: 0 | CD32: 3273.2993 | CE32: 3273.2993 | CF32: 3273.2993 | CG32: 3273.2993 | CH32: 3273.2993 | CI32: 3273.2993 | CK32: 0 | CL32: 0 | CM32: 0 | CN32: 0 | CO32: 0 | CP32: 0 | CQ32: 2348.7967 | CR32: 2348.7967 | CS32: 2348.7967 | CT32: 2348.7967 | CU32: 2348.7967 | CV32: 2348.7967 | CX32: 0 | CY32: 0 | CZ32: 0 | DA32: 0 | DB32: 0 | DC32: 0 | DD32: 5363.67 | DE32: 5363.67 | DF32: 5363.67 | DG32: 5363.67 | DH32: 5363.67 | DI32: 5363.67 | DK32: 0 | DL32: 0 | DM32: 0 | DN32: 0 | DO32: 0 | DP32: 0 | DQ32: 28522.863 | DR32: 28522.863 | DS32: 28522.863 | DT32: 28522.863 | DU32: 28522.863 | DV32: 28522.863 | DX32: =SUM(DK32:DV32) -> 171137.18 | DZ32: =ROUND(SUM(X32:AI32,BK32:BV32,BX32:CI32,CX32:DI32,CK32:CV32),2)=ROUND(SUM(DK32:DV32),2) -> TRUE
B33: Arrojado | C33: Sem Fall Back | D33: TBA 13 | E33: CLT | F33: Fopag | H33: Marketing B2C | I33: StartSe Sistemas | K33: 0 | L33: 5500 | M33: 5500 | N33: 5500 | O33: 5500 | P33: 5500 | Q33: 5500 | R33: 5500 | S33: 5500 | T33: 5500 | U33: 5500 | V33: 5500 | X33: 0 | Y33: 5500 | Z33: 5500 | AA33: 5500 | AB33: 5784.35 | AC33: 5784.35 | AD33: 5784.35 | AE33: 5784.35 | AF33: 5784.35 | AG33: 5784.35 | AH33: 5784.35 | AI33: 5784.35 | AK33: 0 | AL33: 444.38933 | AM33: 444.38933 | AN33: 444.38933 | AO33: 511.6381 | AP33: 511.6381 | AQ33: 511.6381 | AR33: 511.6381 | AS33: 511.6381 | AT33: 511.6381 | AU33: 511.6381 | AV33: 511.6381 | AX33: 0 | AY33: 579.597 | AZ33: 579.597 | BA33: 579.597 | BB33: 619.406 | BC33: 619.406 | BD33: 619.406 | BE33: 619.406 | BF33: 619.406 | BG33: 619.406 | BH33: 619.406 | BI33: 619.406 | BK33: 0 | BL33: 614.16667 | BM33: 614.16667 | BN33: 614.16667 | BO33: 645.91908 | BP33: 645.91908 | BQ33: 645.91908 | BR33: 645.91908 | BS33: 645.91908 | BT33: 645.91908 | BU33: 645.91908 | BV33: 645.91908 | BX33: 0 | BY33: 2538.2949 | BZ33: 2538.2949 | CA33: 2538.2949 | CB33: 2558.6344 | CC33: 2558.6344 | CD33: 2558.6344 | CE33: 2558.6344 | CF33: 2558.6344 | CG33: 2558.6344 | CH33: 2558.6344 | CI33: 2558.6344 | CK33: 0 | CL33: 818.88889 | CM33: 818.88889 | CN33: 818.88889 | CO33: 861.22544 | CP33: 861.22544 | CQ33: 861.22544 | CR33: 861.22544 | CS33: 861.22544 | CT33: 861.22544 | CU33: 861.22544 | CV33: 861.22544 | CX33: 0 | CY33: 1870 | CZ33: 1870 | DA33: 1870 | DB33: 1966.679 | DC33: 1966.679 | DD33: 1966.679 | DE33: 1966.679 | DF33: 1966.679 | DG33: 1966.679 | DH33: 1966.679 | DI33: 1966.679 | DK33: 0 | DL33: 11341.35 | DM33: 11341.35 | DN33: 11341.35 | DO33: 11816.808 | DP33: 11816.808 | DQ33: 11816.808 | DR33: 11816.808 | DS33: 11816.808 | DT33: 11816.808 | DU33: 11816.808 | DV33: 11816.808 | DX33: =SUM(DK33:DV33) -> 128558.51 | DZ33: =ROUND(SUM(X33:AI33,BK33:BV33,BX33:CI33,CX33:DI33,CK33:CV33),2)=ROUND(SUM(DK33:DV33),2) -> TRUE
B34: Base | C34: Sem Fall Back | D34: TBA 17 | E34: CLT | F34: Fopag | H34: Marketing B2C | I34: StartSe Sistemas | K34: 0 | L34: 5500 | M34: 5500 | N34: 5500 | O34: 5500 | P34: 5500 | Q34: 5500 | R34: 5500 | S34: 5500 | T34: 5500 | U34: 5500 | V34: 5500 | X34: 0 | Y34: 5500 | Z34: 5500 | AA34: 5500 | AB34: 5784.35 | AC34: 5784.35 | AD34: 5784.35 | AE34: 5784.35 | AF34: 5784.35 | AG34: 5784.35 | AH34: 5784.35 | AI34: 5784.35 | AK34: 0 | AL34: 444.38933 | AM34: 444.38933 | AN34: 444.38933 | AO34: 511.6381 | AP34: 511.6381 | AQ34: 511.6381 | AR34: 511.6381 | AS34: 511.6381 | AT34: 511.6381 | AU34: 511.6381 | AV34: 511.6381 | AX34: 0 | AY34: 579.597 | AZ34: 579.597 | BA34: 579.597 | BB34: 619.406 | BC34: 619.406 | BD34: 619.406 | BE34: 619.406 | BF34: 619.406 | BG34: 619.406 | BH34: 619.406 | BI34: 619.406 | BK34: 0 | BL34: 614.16667 | BM34: 614.16667 | BN34: 614.16667 | BO34: 645.91908 | BP34: 645.91908 | BQ34: 645.91908 | BR34: 645.91908 | BS34: 645.91908 | BT34: 645.91908 | BU34: 645.91908 | BV34: 645.91908 | BX34: 0 | BY34: 2538.2949 | BZ34: 2538.2949 | CA34: 2538.2949 | CB34: 2558.6344 | CC34: 2558.6344 | CD34: 2558.6344 | CE34: 2558.6344 | CF34: 2558.6344 | CG34: 2558.6344 | CH34: 2558.6344 | CI34: 2558.6344 | CK34: 0 | CL34: 818.88889 | CM34: 818.88889 | CN34: 818.88889 | CO34: 861.22544 | CP34: 861.22544 | CQ34: 861.22544 | CR34: 861.22544 | CS34: 861.22544 | CT34: 861.22544 | CU34: 861.22544 | CV34: 861.22544 | CX34: 0 | CY34: 1870 | CZ34: 1870 | DA34: 1870 | DB34: 1966.679 | DC34: 1966.679 | DD34: 1966.679 | DE34: 1966.679 | DF34: 1966.679 | DG34: 1966.679 | DH34: 1966.679 | DI34: 1966.679 | DK34: 0 | DL34: 11341.35 | DM34: 11341.35 | DN34: 11341.35 | DO34: 11816.808 | DP34: 11816.808 | DQ34: 11816.808 | DR34: 11816.808 | DS34: 11816.808 | DT34: 11816.808 | DU34: 11816.808 | DV34: 11816.808 | DX34: =SUM(DK34:DV34) -> 128558.51 | DZ34: =ROUND(SUM(X34:AI34,BK34:BV34,BX34:CI34,CX34:DI34,CK34:CV34),2)=ROUND(SUM(DK34:DV34),2) -> TRUE
C35: Sem Fall Back | D35: TBA 23 | E35: CLT | F35: Fopag | H35: PEOPLE | I35: StartSe Sistemas | K35: 0 | L35: 6500 | M35: 6500 | N35: 6500 | O35: 6500 | P35: 6500 | Q35: 6500 | R35: 6500 | S35: 6500 | T35: 6500 | U35: 6500 | V35: 6500 | X35: 0 | Y35: 6500 | Z35: 6500 | AA35: 6500 | AB35: 6836.05 | AC35: 6836.05 | AD35: 6836.05 | AE35: 6836.05 | AF35: 6836.05 | AG35: 6836.05 | AH35: 6836.05 | AI35: 6836.05 | AK35: 0 | AL35: 680.88933 | AM35: 680.88933 | AN35: 680.88933 | AO35: 760.36515 | AP35: 760.36515 | AQ35: 760.36515 | AR35: 760.36515 | AS35: 760.36515 | AT35: 760.36515 | AU35: 760.36515 | AV35: 760.36515 | AX35: 0 | AY35: 719.597 | AZ35: 719.597 | BA35: 719.597 | BB35: 766.644 | BC35: 766.644 | BD35: 766.644 | BE35: 766.644 | BF35: 766.644 | BG35: 766.644 | BH35: 766.644 | BI35: 766.644 | BK35: 0 | BL35: 725.83333 | BM35: 725.83333 | BN35: 725.83333 | BO35: 763.35892 | BP35: 763.35892 | BQ35: 763.35892 | BR35: 763.35892 | BS35: 763.35892 | BT35: 763.35892 | BU35: 763.35892 | BV35: 763.35892 | BX35: 0 | BY35: 2609.8247 | BZ35: 2609.8247 | CA35: 2609.8247 | CB35: 2633.8623 | CC35: 2633.8623 | CD35: 2633.8623 | CE35: 2633.8623 | CF35: 2633.8623 | CG35: 2633.8623 | CH35: 2633.8623 | CI35: 2633.8623 | CK35: 0 | CL35: 967.77778 | CM35: 967.77778 | CN35: 967.77778 | CO35: 1017.8119 | CP35: 1017.8119 | CQ35: 1017.8119 | CR35: 1017.8119 | CS35: 1017.8119 | CT35: 1017.8119 | CU35: 1017.8119 | CV35: 1017.8119 | CX35: 0 | CY35: 2210 | CZ35: 2210 | DA35: 2210 | DB35: 2324.257 | DC35: 2324.257 | DD35: 2324.257 | DE35: 2324.257 | DF35: 2324.257 | DG35: 2324.257 | DH35: 2324.257 | DI35: 2324.257 | DK35: 0 | DL35: 13013.436 | DM35: 13013.436 | DN35: 13013.436 | DO35: 13575.34 | DP35: 13575.34 | DQ35: 13575.34 | DR35: 13575.34 | DS35: 13575.34 | DT35: 13575.34 | DU35: 13575.34 | DV35: 13575.34 | DX35: =SUM(DK35:DV35) -> 147643.03 | DZ35: =ROUND(SUM(X35:AI35,BK35:BV35,BX35:CI35,CX35:DI35,CK35:CV35),2)=ROUND(SUM(DK35:DV35),2) -> TRUE
